Workbook
Name LTE: #REF!

Sheet Thông tin xe
A4: 车头：桂FB3272
A5: 拖挂：赣L3858挂
A6: 柜号:
A7: 车型：18.6米大版 | I7: Tổng | J7: 35700
A8: 车厢长18.6米宽3米 | I8: TTP
A9: 车头颜色：红色 | I9: Giang minh | J9: 1120
A10: 备案号： | I10: KTT | J10: 8670
A11: 司机姓名：小刘 | J11: =J7-J9-J10 -> 25910
A12: 电话：18177720051

Sheet HỢP ĐỒNG
A1: HỢP ĐỒNG NGOẠI THƯƠNG | H1: Số hợp đồng: | I1: 0902
A2: ="Số: "&I1&"GF-TH/26" -> Số: 0902 GF-TH/26 | H2: Ngày hợp đồng: | I2: 46270 | L2: =I1&"/19NK-CM" -> 0902 /19NK-CM
C4: ="Hôm nay, ngày "&DAY(I2)&" tháng "&MONTH(I2)&" năm "&YEAR(I2)&" chúng tôi gồm có:" -> Hôm nay, ngày 5 tháng 9 năm 2026 chúng tôi gồm có: | I4: \
C5: BÊN A : PINGXIANG GUIFENG TRADING CO.,LTD
C6: Địa chỉ: NO.6 PHASE II PAVEMENT BAIYUN FIELD TIANNAN SECONDARY PINGXIANG CITY GUANGXI CHINA
C7: Tài khoản ngân hàng số: 800127856500015 tại ngân hàng GUANGXI BEIBU GULF BANK SWIFT code: BGBKCNBJ
C8: Điện thoại: +86-18154645304
C9: Người đại diện: NONG RUN RONG | D9: Chức vụ: Giám đốc
C10: BÊN B: CÔNG TY TNHH THƯƠNG MẠI VÀ XUẤT NHẬP KHẨU TRƯỜNG HẢI
C11: Trụ sở: Số 12 Đường Phụ Số 4, Khu đô thị Phú Lộc 2, Phường Kỳ Lừa, Tỉnh Lạng Sơn, Việt Nam
C12: Mã số thuế: 4900944167 | L12: 25880
C13: Tài khoản ngân hàng số: 9328666888 – Ngân hàng Thương mại Cổ phần Quân đội - CN Tây Hà Nội
C14: Người đại diện: ĐƯỜNG ANH TUẤN | D14: Chức vụ: Giám đốc
C15: Hai bên bàn bạc, thống nhất ý kiến. Bên A đồng ý bán cho bên B lô hàng theo danh mục chi tiết hàng hóa và các điều khoản trong nội dung hợp đồng như sau:
C16: ĐIỀU 1: TÊN HÀNG, SỐ LƯỢNG, GIÁ CẢ | H16: 25844
A18: STT | B18: Mã Hàng | C18: Tên hàng hóa | D18: ĐVT | E18: Số lượng | F18: Đơn giá (USD) | G18: Thành tiền (USD) | H18: Mã biểu thuế ưu đãi | I18: Mã HS | J18: Trị giá | K18: HĐ | L18: Giá tính thuế NK | M18: TS nhập khẩu sau khi có C/O | N18: Thuế NK | O18: Giá tính thuế GTGT | P18: Thuế suất GTGT | Q18: Thuế GTGT | R18: DT đã có lãi | S18: Giá /cân | T18: Trị giá tính thuế CBPG | U18: Thuế suất CBPG | V18: Thuế CBPG
A19: 1 | B19: CN082822-10HN | C19: Khăn lau bụi dùng để lau xe hơi, chất liệu vải dệt kim từ sợi polyester, KT:(30*30)cm, không hiệu, NSX: Qingdao Tao Hui Industrial. Mới 100% | D19: PCE | E19: 20000 | F19: 0.094 | G19: =E19*F19 -> 1880 | H19: B05 | I19: 63071090 | J19: =F19*$L$12 -> 2432.72 | K19: 2500 | L19: =G19*$L$12 -> 48654400 | M19: 0 | N19: =M19*L19 -> 0 | O19: =L19+N19 -> 48654400 | P19: 0.08 | Q19: =O19*P19 -> 3892352 | R19: 115 | S19: =G19/R19 -> 16.347826 | T19: =L19 -> 48654400 | U19: 0 | V19: =T19*U19 -> 0 | W19: 1634 | X19: =G19-W19 -> 246
A20: 2 | B20: CN090109-1HN | C20: Bộ ấm chén pha trà bằng gốm đất nung tráng men rạn Nhữ Diêu,gồm ấm trà dung tích 250ml,chén khải 190ml và chén uống trà 50ml, đóng hộp quà tặng, không hiệu. NSX: Shenzhen Tao Hui Industrial. Mới 100% | D20: SET | E20: 20 | F20: 5.16 | G20: =E20*F20 -> 103.2 | I20: 69120000 | J20: =F20*$L$12 -> 133540.8 | K20: 136880 | L20: =G20*$L$12 -> 2670816 | M20: 0 | N20: =M20*L20 -> 0 | O20: =L20+N20 -> 2670816 | P20: 0.08 | Q20: =O20*P20 -> 213665.28 | R20: 116 | S20: =G20/R20 -> 0.88965517 | T20: =L20 -> 2670816 | U20: 0 | V20: =T20*U20 -> 0 | W20: 360 | X20: =G20-W20 -> -256.8
A21: 3 | C21: Bộ ấm chén pha trà du lịch bằng gốm đất nung tráng men trắng, dáng Tây Thi họa tiết Núi Non, gồm ấm trà dung tích 270ml, tống trà 150ml, chén trà 50ml,đóng hộp quà tặng, không hiệu, Mới 100% | D21: SET | E21: 20 | F21: 4.09 | G21: =E21*F21 -> 81.8 | I21: 69120000 | J21: =F21*$L$12 -> 105849.2 | K21: 108560 | L21: =G21*$L$12 -> 2116984 | M21: 0 | N21: =M21*L21 -> 0 | O21: =L21+N21 -> 2116984 | P21: 0.08 | Q21: =O21*P21 -> 169358.72 | R21: 117 | S21: =G21/R21 -> 0.6991453 | T21: =L21 -> 2116984 | U21: 0 | V21: =T21*U21 -> 0 | W21: 1117.8 | X21: =G21-W21 -> -1036
A22: 4 | C22: Bộ ấm chén trà bằng gốm đất nung, kiểu dáng Nhật gồm 1 ấm 200ml và 4 chén 60ml kèm hộp quà tặng, không hiệu, NSX: Shenzhen Tao Hui Industrial Co., Ltd., Mới 100% | D22: SET | E22: 50 | F22: 5.69 | G22: =E22*F22 -> 284.5 | I22: 69120000 | J22: =F22*$L$12 -> 147257.2 | K22: 151040 | L22: =G22*$L$12 -> 7362860 | M22: 0 | N22: =M22*L22 -> 0 | O22: =L22+N22 -> 7362860 | P22: 0.08 | Q22: =O22*P22 -> 589028.8 | R22: 118 | S22: =G22/R22 -> 2.4110169 | T22: =L22 -> 7362860 | U22: 0 | V22: =T22*U22 -> 0 | W22: 297.2 | X22: =G22-W22 -> -12.7
A23: 5 | B23: CN083010-1HN | C23: Ấm pha trà bằng gốm đất nung không tráng men (Tử Sa) dáng Hán Ngõa, màu xanh Lục Nê, dung tích 240ml, không dùng điện, không hiệu, NSX: Shenzhen Tao Hui Industrial Co., Ltd., Mới 100% | D23: PCE | E23: 10 | F23: 13.6 | G23: =E23*F23 -> 136 | I23: 69120000 | J23: =F23*$L$12 -> 351968 | K23: 360797 | L23: =G23*$L$12 -> 3519680 | M23: 0 | N23: =M23*L23 -> 0 | O23: =L23+N23 -> 3519680 | P23: 0.08 | Q23: =O23*P23 -> 281574.4 | R23: 119 | S23: =G23/R23 -> 1.1428571 | T23: =L23 -> 3519680 | U23: 0 | V23: =T23*U23 -> 0 | W23: 393 | X23: =G23-W23 -> -257
A24: 6 | C24: Ấm pha trà bằng gốm đất nung không tráng men (Tử Sa) dáng Tây Thi, màu đỏ Đại Hồng Bào, dung tích 240ml, không dùng điện, không hiệu, NSX: Shenzhen Tao Hui Industrial Co., Ltd., Mới 100% | D24: PCE | E24: 15 | F24: 10.46 | G24: =E24*F24 -> 156.9 | I24: 69120000 | J24: =F24*$L$12 -> 270704.8 | K24: 277536 | L24: =G24*$L$12 -> 4060572 | M24: 0 | N24: =M24*L24 -> 0 | O24: =L24+N24 -> 4060572 | P24: 0.08 | Q24: =O24*P24 -> 324845.76 | R24: 120 | S24: =G24/R24 -> 1.3075 | T24: =L24 -> 4060572 | U24: 0 | V24: =T24*U24 -> 0 | W24: 1038.2 | X24: =G24-W24 -> -881.3
A25: 7 | C25: Cốc uống trà bằng gốm đất nung không tráng men (Tử Sa) họa tiết Thiên Hương, dung tích 180ml, không hiệu, NSX: Shenzhen Tao Hui Industrial Co., Ltd., Mới 100% | D25: PCE | E25: 20 | F25: 4.49 | G25: =E25*F25 -> 89.8 | I25: 69120000 | J25: =F25*$L$12 -> 116201.2 | K25: 119227 | L25: =G25*$L$12 -> 2324024 | M25: 0 | N25: =M25*L25 -> 0 | O25: =L25+N25 -> 2324024 | P25: 0.08 | Q25: =O25*P25 -> 185921.92 | R25: 121 | S25: =G25/R25 -> 0.74214876 | T25: =L25 -> 2324024 | U25: 0 | V25: =T25*U25 -> 0 | W25: 802.2 | X25: =G25-W25 -> -712.4
A26: 8 | C26: Ấm pha trà bằng gốm đất nung không tráng men (Tử Sa) dáng Bát Phương Nung Củi, màu vàng Đoạn Nê, dung tích 270ml, không dùng điện, không hiệu, NSX: Shenzhen Tao Hui Industrial Co., Ltd., Mới 100% | D26: PCE | E26: 10 | F26: 16.74 | G26: =E26*F26 -> 167.4 | I26: 69120000 | J26: =F26*$L$12 -> 433231.2 | K26: 444058 | L26: =G26*$L$12 -> 4332312 | M26: 0 | N26: =M26*L26 -> 0 | O26: =L26+N26 -> 4332312 | P26: 0.08 | Q26: =O26*P26 -> 346584.96 | R26: 122 | S26: =G26/R26 -> 1.3721311 | T26: =L26 -> 4332312 | U26: 0 | V26: =T26*U26 -> 0 | W26: 651.6 | X26: =G26-W26 -> -484.2
A27: 9 | C27: Ấm pha trà bằng gốm đất nung không tráng men (Tử Sa) dáng Thạch Biều, màu xanh Lục Nê, dung tích 260ml, không dùng điện, không hiệu, NSX: Shenzhen Tao Hui Industrial Co., Ltd., Mới 100% | D27: PCE | E27: 5 | F27: 15.69 | G27: =E27*F27 -> 78.45 | I27: 69120000 | J27: =F27*$L$12 -> 406057.2 | K27: 416304 | L27: =G27*$L$12 -> 2030286 | M27: 0 | N27: =M27*L27 -> 0 | O27: =L27+N27 -> 2030286 | P27: 0.08 | Q27: =O27*P27 -> 162422.88 | R27: 123 | S27: =G27/R27 -> 0.63780488 | T27: =L27 -> 2030286 | U27: 0 | V27: =T27*U27 -> 0 | W27: 937.5 | X27: =G27-W27 -> -859.05
A28: 10 | C28: Ấm pha trà bằng gốm đất nung không tráng men (Tử Sa) dáng Vân Lư, màu nâu Thiết Huyết Hồng Sa, dung tích 260ml, không dùng điện, không hiệu, NSX: Shenzhen Tao Hui Industrial Co., Ltd., Mới 100% | D28: PCE | E28: 10 | F28: 17.09 | G28: =E28*F28 -> 170.9 | I28: 69120000 | J28: =F28*$L$12 -> 442289.2 | K28: 453309 | L28: =G28*$L$12 -> 4422892 | M28: 0 | N28: =M28*L28 -> 0 | O28: =L28+N28 -> 4422892 | P28: 0.08 | Q28: =O28*P28 -> 353831.36 | R28: 124 | S28: =G28/R28 -> 1.3782258 | T28: =L28 -> 4422892 | U28: 0 | V28: =T28*U28 -> 0 | W28: 10912 | X28: =G28-W28 -> -10741.1
A29: 11 | C29: Ấm pha trà bằng gốm đất nung không tráng men (Tử Sa) dáng Tứ Phương Liên Hoa dung tích 230ml, không dùng điện, không hiệu, NSX: Shenzhen Tao Hui Industrial Co., Ltd., Mới 100% | D29: PCE | E29: 10 | F29: 14.47 | G29: =E29*F29 -> 144.7 | I29: 69120000 | J29: =F29*$L$12 -> 374483.6 | K29: 383925 | L29: =G29*$L$12 -> 3744836 | M29: 0 | N29: =M29*L29 -> 0 | O29: =L29+N29 -> 3744836 | P29: 0.08 | Q29: =O29*P29 -> 299586.88 | R29: 125 | S29: =G29/R29 -> 1.1576 | T29: =L29 -> 3744836 | U29: 0 | V29: =T29*U29 -> 0 | W29: 3017.5 | X29: =G29-W29 -> -2872.8
A30: 12 | B30: CN090110-1HN | C30: Ấm pha trà bằng gốm đất nung không tráng men (Tử Sa) dáng Long Đán, màu nâu Tử Nê, dung tích 220ml, không dùng điện, không hiệu, NSX: Shenzhen Tao Hui Industrial Co., Ltd., Mới 100% | D30: PCE | E30: 3 | F30: 20.46 | G30: =E30*F30 -> 61.38 | I30: 69120000 | J30: =F30*$L$12 -> 529504.8 | K30: 542800 | L30: =G30*$L$12 -> 1588514.4 | M30: 0 | N30: =M30*L30 -> 0 | O30: =L30+N30 -> 1588514.4 | P30: 0.08 | Q30: =O30*P30 -> 127081.15 | R30: 126 | S30: =G30/R30 -> 0.48714286 | T30: =L30 -> 1588514.4 | U30: 0 | V30: =T30*U30 -> 0 | W30: 300 | X30: =G30-W30 -> -238.62
A31: 13 | C31: Ấm pha trà bằng gốm đất nung không tráng men (Tử Sa) dáng Phan Hồ, màu đỏ Đại Hồng Bào, dung tích 250ml, không dùng điện, không hiệu, NSX: Shenzhen Tao Hui Industrial Co., Ltd., Mới 100% | D31: PCE | E31: 3 | F31: 28.47 | G31: =E31*F31 -> 85.41 | I31: 69120000 | J31: =F31*$L$12 -> 736803.6 | K31: 755200 | L31: =G31*$L$12 -> 2210410.8 | M31: 0 | N31: =M31*L31 -> 0 | O31: =L31+N31 -> 2210410.8 | P31: 0.08 | Q31: =O31*P31 -> 176832.86 | R31: 127 | S31: =G31/R31 -> 0.67251969 | T31: =L31 -> 2210410.8 | U31: 0 | V31: =T31*U31 -> 0 | W31: 448 | X31: =G31-W31 -> -362.59
A32: 14 | C32: Ấm pha trà bằng gốm đất nung không tráng men (Tử Sa) dáng Tây Thi, dung tích 420ml, không dùng điện, không hiệu, NSX: Shenzhen Tao Hui Industrial Co., Ltd., Mới 100% | D32: PCE | E32: 5 | F32: 39.15 | G32: =E32*F32 -> 195.75 | I32: 69120000 | J32: =F32*$L$12 -> 1013202 | K32: 1038400 | L32: =G32*$L$12 -> 5066010 | M32: 0 | N32: =M32*L32 -> 0 | O32: =L32+N32 -> 5066010 | P32: 0.08 | Q32: =O32*P32 -> 405280.8 | R32: 128 | S32: =G32/R32 -> 1.5292969 | T32: =L32 -> 5066010 | U32: 0 | V32: =T32*U32 -> 0 | W32: 240 | X32: =G32-W32 -> -44.25
A33: 15 | C33: Khay để ấm trà (Thuyền Trà) bằng gốm đất nung không tráng men (Tử Sa) đường kính 19.5cm, họa tiết Sơn Cảnh, đóng hộp quà tặng, không hiệu, NSX: Shenzhen Tao Hui Industrial Co., Ltd., Mới 100% | D33: PCE | E33: 5 | F33: 26.69 | G33: =E33*F33 -> 133.45 | I33: 69120000 | J33: =F33*$L$12 -> 690737.2 | K33: 708000 | L33: =G33*$L$12 -> 3453686 | M33: 0 | N33: =M33*L33 -> 0 | O33: =L33+N33 -> 3453686 | P33: 0.08 | Q33: =O33*P33 -> 276294.88 | R33: 129 | S33: =G33/R33 -> 1.0344961 | T33: =L33 -> 3453686 | U33: 0 | V33: =T33*U33 -> 0 | W33: 217.8 | X33: =G33-W33 -> -84.35
A34: 16 | C34: Ang trà ( bát tráng trà) bằng gốm đất nung không tráng men (Tử Sa), màu cam Chu Nê, họa tiết Tâm Kinh đường kính 27.8cm, không hiệu, NSX: Shenzhen Tao Hui Industrial Co., Ltd., Mới 100% | D34: PCE | E34: 5 | F34: 24.02 | G34: =E34*F34 -> 120.1 | I34: 69120000 | J34: =F34*$L$12 -> 621637.6 | K34: 637200 | L34: =G34*$L$12 -> 3108188 | M34: 0 | N34: =M34*L34 -> 0 | O34: =L34+N34 -> 3108188 | P34: 0.08 | Q34: =O34*P34 -> 248655.04 | R34: 130 | S34: =G34/R34 -> 0.92384615 | T34: =L34 -> 3108188 | U34: 0 | V34: =T34*U34 -> 0 | W34: 3016 | X34: =G34-W34 -> -2895.9
A35: 17 | C35: Ấm pha trà bằng gốm đất nung không tráng men (Tử Sa) dáng Thạch Biều Cảnh Chu, màu nâu Tử Nê, dung tích 230ml, không dùng điện, không hiệu, NSX: Shenzhen Tao Hui Industrial Co., Ltd., Mới 100% | D35: PCE | E35: 5 | F35: 53.38 | G35: =E35*F35 -> 266.9 | I35: 69120000 | J35: =F35*$L$12 -> 1381474.4 | K35: 1416000 | L35: =G35*$L$12 -> 6907372 | M35: 0 | N35: =M35*L35 -> 0 | O35: =L35+N35 -> 6907372 | P35: 0.08 | Q35: =O35*P35 -> 552589.76 | R35: 131 | S35: =G35/R35 -> 2.0374046 | T35: =L35 -> 6907372 | U35: 0 | V35: =T35*U35 -> 0 | W35: 590.4 | X35: =G35-W35 -> -323.5
A36: 18 | C36: Ấm pha trà bằng gốm đất nung không tráng men (Tử Sa) dáng Mỹ Nhân Kiên, màu đỏ Đại Hồng Bào, dung tích 190ml, không dùng điện, không hiệu, NSX: Shenzhen Tao Hui Industrial Co., Ltd., Mới 100% | D36: PCE | E36: 5 | F36: 29.89 | G36: =E36*F36 -> 149.45 | I36: 69120000 | J36: =F36*$L$12 -> 773553.2 | K36: 792960 | L36: =G36*$L$12 -> 3867766 | M36: 0 | N36: =M36*L36 -> 0 | O36: =L36+N36 -> 3867766 | P36: 0.08 | Q36: =O36*P36 -> 309421.28 | R36: 132 | S36: =G36/R36 -> 1.132197 | T36: =L36 -> 3867766 | U36: 0 | V36: =T36*U36 -> 0 | W36: 932.8 | X36: =G36-W36 -> -783.35
A37: 19 | C37: Ấm pha trà bằng gốm đất nung không tráng men (Tử Sa) dáng Tây Thi Song Sắc, dung tích 200ml, không dùng điện, không hiệu, NSX: Shenzhen Tao Hui Industrial Co., Ltd., Mới 100% | D37: PCE | E37: 3 | F37: 32.03 | G37: =E37*F37 -> 96.09 | I37: 69120000 | J37: =F37*$L$12 -> 828936.4 | K37: 849600 | L37: =G37*$L$12 -> 2486809.2 | M37: 0 | N37: =M37*L37 -> 0 | O37: =L37+N37 -> 2486809.2 | P37: 0.08 | Q37: =O37*P37 -> 198944.74 | R37: 133 | S37: =G37/R37 -> 0.7224812 | T37: =L37 -> 2486809.2 | U37: 0 | V37: =T37*U37 -> 0 | W37: 401.76 | X37: =G37-W37 -> -305.67
A38: 20 | B38: CN082415-12HN | C38: Công tắc điều khiển dòng chảy, model: HFS-25, dùng cho công nghiệp đóng ngắt dòng điện 5A. KT: (10*7*5)cm+/-10%, đk: ren 1-3/4inch, đ/áp: 220V, hiệu: SUNSES, mới 100% | D38: PCE | E38: 500 | F38: 5.47 | G38: =E38*F38 -> 2735 | I38: 85365096 | J38: =F38*$L$12 -> 141563.6 | K38: 145000 | L38: =G38*$L$12 -> 70781800 | M38: 0 | N38: =M38*L38 -> 0 | O38: =L38+N38 -> 70781800 | P38: 0.08 | Q38: =O38*P38 -> 5662544 | R38: 134 | S38: =G38/R38 -> 20.410448 | T38: =L38 -> 70781800 | U38: 0 | V38: =T38*U38 -> 0 | W38: 272 | X38: =G38-W38 -> 2463
A39: 21 | C39: Công tắc áp suất khí nén KP, bằng nhựa kết hợp đồng, để điều chỉnh áp suất trong hệ thống khí nén, đ/áp: 220V/5A, không hiệu. NSX: Zhejiang Machinery Technology Co., LTD, mới 100% | D39: PCE | E39: 300 | F39: 8.29 | G39: =E39*F39 -> 2487 | I39: 85365096 | J39: =F39*$L$12 -> 214545.2 | K39: 220000 | L39: =G39*$L$12 -> 64363560 | M39: 0 | N39: =M39*L39 -> 0 | O39: =L39+N39 -> 64363560 | P39: 0.08 | Q39: =O39*P39 -> 5149084.8 | R39: 135 | S39: =G39/R39 -> 18.422222 | T39: =L39 -> 64363560 | U39: 0 | V39: =T39*U39 -> 0 | W39: 572.8 | X39: =G39-W39 -> 1914.2
A40: 22 | C40: Đế chia khí dùng cho đường ống khí nén, bằng hợp kim nhôm, loại 3-5 cổng, ren 13mm, áp suất làm việc 1 MPa. KT: (15*5*2)cm+/-10%, không hiệu, nsx: NSX Aikes Pneumatic Components Co., Ltd, mới 100% | D40: PCE | E40: 300 | F40: 4.49 | G40: =E40*F40 -> 1347 | I40: 73269099 | J40: =F40*$L$12 -> 116201.2 | K40: 119000 | L40: =G40*$L$12 -> 34860360 | M40: 0 | N40: =M40*L40 -> 0 | O40: =L40+N40 -> 34860360 | P40: 0.08 | Q40: =O40*P40 -> 2788828.8 | R40: 136 | S40: =G40/R40 -> 9.9044118 | T40: =L40 -> 34860360 | U40: 0 | V40: =T40*U40 -> 0 | W40: 230 | X40: =G40-W40 -> 1117
A41: 23 | B41: CN082915-4HN | C41: Vợt pickleball, model: Bomba X, sử dụng công nghệ ép nóng, lõi eva foam, bề mặt bằng sợi carbon. KT: (40*20*3)cm+/-10%, hiệu: Do-An, mới 100% | D41: PCE | E41: 400 | F41: 9.24 | G41: =E41*F41 -> 3696 | I41: 95069990 | J41: =F41*$L$12 -> 239131.2 | K41: 245000 | L41: =G41*$L$12 -> 95652480 | M41: 0 | N41: =M41*L41 -> 0 | O41: =L41+N41 -> 95652480 | P41: 0.08 | Q41: =O41*P41 -> 7652198.4 | R41: 137 | S41: =G41/R41 -> 26.978102 | T41: =L41 -> 95652480 | U41: 0 | V41: =T41*U41 -> 0 | W41: 67.5 | X41: =G41-W41 -> 3628.5
A42: 24 | B42: CN082916-5HN | C42: Yếm cho thú cưng, chất liệu vải dệt từ sợi tổng hợp. KT: (25*20*2)cm+/-10%, không hiệu. NSX: Ningbo Jia Chong International Trade Co., Ltd.., mới 100% | D42: PCE | E42: 270 | F42: 0.92 | G42: =E42*F42 -> 248.4 | I42: 42010000 | J42: =F42*$L$12 -> 23809.6 | K42: 24371 | L42: =G42*$L$12 -> 6428592 | M42: 0 | N42: =M42*L42 -> 0 | O42: =L42+N42 -> 6428592 | P42: 0.08 | Q42: =O42*P42 -> 514287.36 | R42: 138 | S42: =G42/R42 -> 1.8 | T42: =L42 -> 6428592 | U42: 0 | V42: =T42*U42 -> 0 | W42: 57 | X42: =G42-W42 -> 191.4
A43: 25 | C43: Dây dắt thú cưng, chất liệu vải dù. KT: 1.2cm*1.5m+/-10%, không hiệu. NSX: Ningbo Jia Chong International Trade Co., Ltd.., mới 100% | D43: PCE | E43: 400 | F43: 0.71 | G43: =E43*F43 -> 284 | I43: 42010000 | J43: =F43*$L$12 -> 18374.8 | K43: 18762 | L43: =G43*$L$12 -> 7349920 | M43: 0 | N43: =M43*L43 -> 0 | O43: =L43+N43 -> 7349920 | P43: 0.08 | Q43: =O43*P43 -> 587993.6 | R43: 139 | S43: =G43/R43 -> 2.0431655 | T43: =L43 -> 7349920 | U43: 0 | V43: =T43*U43 -> 0 | W43: 80.1 | X43: =G43-W43 -> 203.9
A44: 26 | B44: CN083006-50HN | C44: Thanh giá treo của vòi hoa sen cây (gồm 2 thanh), chất liệu thép không gỉ, chống bám bẩn. KT: (1280*370)mm+/-10%, không hiệu,nsx: Jiangyin Yonghao Machinery Co., Ltd. Mới 100% | D44: SET | E44: 1200 | F44: 5.28 | G44: =E44*F44 -> 6336 | I44: 73249099 | J44: =F44*$L$12 -> 136646.4 | K44: 140000 | L44: =G44*$L$12 -> 163975680 | M44: 0 | N44: =M44*L44 -> 0 | O44: =L44+N44 -> 163975680 | P44: 0.08 | Q44: =O44*P44 -> 13118054 | R44: 140 | S44: =G44/R44 -> 45.257143 | T44: =L44 -> 163975680 | U44: 0 | V44: =T44*U44 -> 0 | W44: 122 | X44: =G44-W44 -> 6214
A45: 27 | B45: CN083114-12HN | C45: Khay chữ nhật, kí hiệu: SL-170, dùng để trang trí, trưng bày trong khách sạn, chất liệu nhựa giả gỗ. KT: (29.7*21.5*6)cm+/-10%, không hiệu. Nsx: Shandong Machinery Co., Ltd. Mới 100% | D45: PCE | E45: 48 | F45: 10.18 | G45: =E45*F45 -> 488.64 | I45: 39264000 | J45: =F45*$L$12 -> 263458.4 | K45: 270000 | L45: =G45*$L$12 -> 12646003 | M45: 0 | N45: =M45*L45 -> 0 | O45: =L45+N45 -> 12646003 | P45: 0.08 | Q45: =O45*P45 -> 1011680.3 | R45: 141 | S45: =G45/R45 -> 3.4655319 | T45: =L45 -> 12646003 | U45: 1 | V45: =T45*U45 -> 12646003 | W45: 101.4 | X45: =G45-W45 -> 387.24
A46: 28 | C46: Khay đựng đũa đặt trên bàn ăn dùng trong nhà bếp, không dùng đựng thực phẩm,chất liệu bằng nhựa ABS, kí hiệu: C-1222. KT: (27.3*10.5*6.5)cm+-10%, không hiệu. Nsx: Shandong Machinery Co., Ltd. Mới 100% | D46: PCE | E46: 150 | F46: 4.17 | G46: =E46*F46 -> 625.5 | I46: 39241099 | J46: =F46*$L$12 -> 107919.6 | K46: 110640 | L46: =G46*$L$12 -> 16187940 | M46: 0 | N46: =M46*L46 -> 0 | O46: =L46+N46 -> 16187940 | P46: 0.08 | Q46: =O46*P46 -> 1295035.2 | R46: 142 | S46: =G46/R46 -> 4.4049296 | T46: =L46 -> 16187940 | U46: 2 | V46: =T46*U46 -> 32375880 | W46: 65.95 | X46: =G46-W46 -> 559.55
A47: 29 | C47: Khay đựng đũa đặt trên bàn ăn dùng trong nhà bếp, không dùng đựng thực phẩm, chất liệu bằng nhựa ABS, kí hiệu: C-1223. KT: (26.5*8.7*5)cm+-10%, không hiệu. Nsx: Shandong Machinery Co., Ltd. Mới 100% | D47: PCE | E47: 150 | F47: 4.17 | G47: =E47*F47 -> 625.5 | I47: 39241099 | J47: =F47*$L$12 -> 107919.6 | K47: 110640 | L47: =G47*$L$12 -> 16187940 | M47: 0 | N47: =M47*L47 -> 0 | O47: =L47+N47 -> 16187940 | P47: 0.08 | Q47: =O47*P47 -> 1295035.2 | R47: 143 | S47: =G47/R47 -> 4.3741259 | T47: =L47 -> 16187940 | U47: 3 | V47: =T47*U47 -> 48563820 | W47: 128.4 | X47: =G47-W47 -> 497.1
A48: 30 | B48: CN090113-14HN | C48: Nồi lẩu sần 2 ngăn NLS2N32B, dùng trong nhà bếp, không dùng điện, chất liệu inox. ĐK: 32cm+/-10%, không hiệu, nsx: Jiangmen Jida Stainless Steel Products Co., Ltd.. Mới 100% | D48: PCE | E48: 200 | F48: 13.19 | G48: =E48*F48 -> 2638 | I48: 73239310 | J48: =F48*$L$12 -> 341357.2 | K48: 350000 | L48: =G48*$L$12 -> 68271440 | M48: 0 | N48: =M48*L48 -> 0 | O48: =L48+N48 -> 68271440 | P48: 0.08 | Q48: =O48*P48 -> 5461715.2 | R48: 144 | S48: =G48/R48 -> 18.319444 | T48: =L48 -> 68271440 | U48: 4 | V48: =T48*U48 -> 273085760 | W48: 436 | X48: =G48-W48 -> 2202
A49: 31 | C49: Nồi lẩu inox NLS30B, dùng trong nhà bếp, không dùng điện. ĐK: 28cm+/-10%, không hiệu, nsx: Jiangmen Jida Stainless Steel Products Co., Ltd.. Mới 100% | D49: PCE | E49: 26 | F49: 7.92 | G49: =E49*F49 -> 205.92 | I49: 73239310 | J49: =F49*$L$12 -> 204969.6 | K49: 210000 | L49: =G49*$L$12 -> 5329209.6 | M49: 0 | N49: =M49*L49 -> 0 | O49: =L49+N49 -> 5329209.6 | P49: 0.08 | Q49: =O49*P49 -> 426336.77 | R49: 145 | S49: =G49/R49 -> 1.4201379 | T49: =L49 -> 5329209.6 | U49: 5 | V49: =T49*U49 -> 26646048 | W49: 327 | X49: =G49-W49 -> -121.08
A50: 32 | B50: CN090213-2HN | C50: Khay chữ nhật có đế, dùng trang trí trưng bày trong khách sạn, không đựng thực phẩm, KH: 990808, CL nhựa ABS.KT: (20.4*15*5.8)cm+/-10%, không hiệu.NSX: Jiangmen Jida Stainless Steel Products. Mới 100% | D50: PCE | E50: 120 | F50: 1.88 | G50: =E50*F50 -> 225.6 | I50: 39264000 | J50: =F50*$L$12 -> 48654.4 | K50: 50000 | L50: =G50*$L$12 -> 5838528 | M50: 0 | N50: =M50*L50 -> 0 | O50: =L50+N50 -> 5838528 | P50: 0.08 | Q50: =O50*P50 -> 467082.24 | R50: 146 | S50: =G50/R50 -> 1.5452055 | T50: =L50 -> 5838528 | U50: 6 | V50: =T50*U50 -> 35031168 | W50: 654 | X50: =G50-W50 -> -428.4
A51: 33 | B51: CN090211-18HN | C51: Miếng dán kính cường lực BAIKO GLASS dùng cho điện thoại,loại an toàn 2 lớp (kính dán an toàn nhiều lớp),CL sợi thủy tinh, có lớp bảo vệ bằng nhựa. KT: (185*75*25)mm +/-10%, nhãn hiệu: BAIKO. Mới 100% | D51: PCE | E51: 6500 | F51: 0.183 | G51: =E51*F51 -> 1189.5 | I51: 70072990 | J51: =F51*$L$12 -> 4736.04 | K51: 4847 | L51: =G51*$L$12 -> 30784260 | M51: 0 | N51: =M51*L51 -> 0 | O51: =L51+N51 -> 30784260 | P51: 0.08 | Q51: =O51*P51 -> 2462740.8 | R51: 147 | S51: =G51/R51 -> 8.0918367 | T51: =L51 -> 30784260 | U51: 7 | V51: =T51*U51 -> 215489820 | W51: 894.92 | X51: =G51-W51 -> 294.58
A52: 34 | C52: Miếng dán kính cường lựcBAIKO GLASS trong suốt ko viền đen dùng cho điện thoại,loại an toàn 2lớp(kính dán an toàn nhiều lớp),CLsợi thủy tinh,có lớp bảo vệ bằng nhựa.KT:(185*75*25)mm,hiệu:BAIKO.Mới100% | D52: PCE | E52: 13000 | F52: 0.207 | G52: =E52*F52 -> 2691 | I52: 70072990 | J52: =F52*$L$12 -> 5357.16 | K52: 5500 | L52: =G52*$L$12 -> 69643080 | M52: 0 | N52: =M52*L52 -> 0 | O52: =L52+N52 -> 69643080 | P52: 0.08 | Q52: =O52*P52 -> 5571446.4 | R52: 148 | S52: =G52/R52 -> 18.182432 | T52: =L52 -> 69643080 | U52: 8 | V52: =T52*U52 -> 557144640 | W52: 1080 | X52: =G52-W52 -> 1611
A53: 35 | C53: Miếng dán kính cường lực BAIKO ULTRA THIN PRIVACY dùng cho điện thoại,loại kính dán nhiều lớp,CL sợi thủy tinh, lớp bảo vệ bằng nhựa. KT (185*75*25)mm +/-10%,nhãn hiệu: BAIKO. Mới 100% | D53: PCE | E53: 1620 | F53: 0.66 | G53: =E53*F53 -> 1069.2 | I53: 70072990 | J53: =F53*$L$12 -> 17080.8 | K53: 17500 | L53: =G53*$L$12 -> 27670896 | M53: 0 | N53: =M53*L53 -> 0 | O53: =L53+N53 -> 27670896 | P53: 0.08 | Q53: =O53*P53 -> 2213671.7 | R53: 149 | S53: =G53/R53 -> 7.1758389 | T53: =L53 -> 27670896 | U53: 9 | V53: =T53*U53 -> 249038064 | W53: 654.5 | X53: =G53-W53 -> 414.7
A54: 36 | C54: Miếng dán kính cường lực BAIKO GLASS PRIVACY cho điện thoại,loại an toàn 2 lớp (kính dán an toàn nhiều lớp),CL sợi thủy tinh, có lớp bảo vệ bằng nhựa. KT: (185*75*25)mm, nhãn hiệu: BAIKO. Mới 100% | D54: PCE | E54: 5000 | F54: 0.32 | G54: =E54*F54 -> 1600 | I54: 70072990 | J54: =F54*$L$12 -> 8281.6 | K54: 8500 | L54: =G54*$L$12 -> 41408000 | M54: 0 | N54: =M54*L54 -> 0 | O54: =L54+N54 -> 41408000 | P54: 0.08 | Q54: =O54*P54 -> 3312640 | R54: 150 | S54: =G54/R54 -> 10.666667 | T54: =L54 -> 41408000 | U54: 10 | V54: =T54*U54 -> 414080000 | W54: 428.84 | X54: =G54-W54 -> 1171.16
A55: 37 | C55: Tấm kính cường lực loại an toàn nhiều lớp, dùng để bảo vệ màn hình điện thoại di dộng, ESD GLASS màu tím, chất liệu sợi thuỷ tinh, lớp bảo vệ bằng nhựa. KT: (185*75*25)mm, nhãn hiệu: BAIKO.Mới 100% | D55: PCE | E55: 3000 | F55: 0.26 | G55: =E55*F55 -> 780 | I55: 70072990 | J55: =F55*$L$12 -> 6728.8 | K55: 6800 | L55: =G55*$L$12 -> 20186400 | M55: 0 | N55: =M55*L55 -> 0 | O55: =L55+N55 -> 20186400 | P55: 0.08 | Q55: =O55*P55 -> 1614912 | R55: 151 | S55: =G55/R55 -> 5.1655629 | T55: =L55 -> 20186400 | U55: 11 | V55: =T55*U55 -> 222050400 | W55: 347.3 | X55: =G55-W55 -> 432.7
A56: 38 | B56: CN090301-30HN | C56: Dây kẽm nhung (lõi kẽm bọc vải nhung) dùng để làm hoa giả, 100 sợi/bó. 1 bó=1 set. KT: đường kính 0.8cm, dài 30cm+/-10%, không hiệu. NSX: Yiwu Tianhong Crafts Co., Ltd, mới 100% | D56: SET | E56: 6000 | F56: 0.41 | G56: =E56*F56 -> 2460 | I56: 79070099 | J56: =F56*$L$12 -> 10610.8 | K56: 11000 | L56: =G56*$L$12 -> 63664800 | M56: 0 | N56: =M56*L56 -> 0 | O56: =L56+N56 -> 63664800 | P56: 0.1 | Q56: =O56*P56 -> 6366480 | R56: 152 | S56: =G56/R56 -> 16.184211 | T56: =L56 -> 63664800 | U56: 12 | V56: =T56*U56 -> 763977600 | W56: 265.76 | X56: =G56-W56 -> 2194.24
A57: 39 | B57: CN090304-120HN | C57: Miếng nhám cọ rửa bát đĩa, chất liệu lớp mút xốp bằng nhựa, dạng mút xốp kết hợp lớp nhám. KT: (10*6*2)cm+/-10%, không hiệu, nsx: Fengrun Commodity Co., Ltd. Mới 100% | D57: PCE | E57: 30000 | F57: 0.122 | G57: =E57*F57 -> 3660 | I57: 96039090 | J57: =F57*$L$12 -> 3157.36 | K57: 3240 | L57: =G57*$L$12 -> 94720800 | M57: 0 | N57: =M57*L57 -> 0 | O57: =L57+N57 -> 94720800 | P57: 0.08 | Q57: =O57*P57 -> 7577664 | R57: 153 | S57: =G57/R57 -> 23.921569 | T57: =L57 -> 94720800 | U57: 13 | V57: =T57*U57 -> 1231370400 | W57: 105.7 | X57: =G57-W57 -> 3554.3
A58: 40 | B58: CN090204-36HN | C58: Hộp 4 bút bi mực gel, thân vỏ bút bằng nhựa tổng hợp có in họa tiết. KT: (dài 18*0.8cm)+-10%, không hiệu. Nsx Baiqi Hourglass Pens Co.Ltd, mới 100% | D58: UNK | E58: 2500 | F58: 0.57 | G58: =E58*F58 -> 1425 | I58: 96081010 | J58: =F58*$L$12 -> 14751.6 | K58: 15000 | L58: =G58*$L$12 -> 36879000 | M58: 0 | N58: =M58*L58 -> 0 | O58: =L58+N58 -> 36879000 | P58: 0.08 | Q58: =O58*P58 -> 2950320 | R58: 154 | S58: =G58/R58 -> 9.2532468 | T58: =L58 -> 36879000 | U58: 14 | V58: =T58*U58 -> 5.16306e+08 | W58: 217 | X58: =G58-W58 -> 1208
A59: 41 | C59: Túi đựng dụng cụ học tập 1 ngăn in họa tiết basic loại đựng trong túi, cặp chất liệu và mặt ngoài bằng vải dệt. KT: (20*8*6)cm+/-10%, không hiệu. NSX: Shanghai Stationery Inc. Mới 100% | D59: PCE | E59: 14500 | F59: 0.29 | G59: =E59*F59 -> 4205 | I59: 42023200 | J59: =F59*$L$12 -> 7505.2 | K59: 7800 | L59: =G59*$L$12 -> 108825400 | M59: 0 | N59: =M59*L59 -> 0 | O59: =L59+N59 -> 108825400 | P59: 0.08 | Q59: =O59*P59 -> 8706032 | R59: 155 | S59: =G59/R59 -> 27.129032 | T59: =L59 -> 108825400 | U59: 15 | V59: =T59*U59 -> 1632381000 | W59: 825 | X59: =G59-W59 -> 3380
A60: 42 | C60: Túi đựng dụng cụ học tập 2 ngăn loại đựng trong túi, cặp chất liệu và mặt ngoài bằng vải dệt không thấm nước. KT: (20*10*6)cm+/-10%, không hiệu. NSX:Yiwu Jiayi Daily Necessities Factory,mới 100% | D60: PCE | E60: 1000 | F60: 0.45 | G60: =E60*F60 -> 450 | I60: 42023200 | J60: =F60*$L$12 -> 11646 | K60: 12000 | L60: =G60*$L$12 -> 11646000 | M60: 0 | N60: =M60*L60 -> 0 | O60: =L60+N60 -> 11646000 | P60: 0.08 | Q60: =O60*P60 -> 931680 | R60: 156 | S60: =G60/R60 -> 2.8846154 | T60: =L60 -> 11646000 | U60: 16 | V60: =T60*U60 -> 186336000 | W60: 675 | X60: =G60-W60 -> -225
A61: 43 | B61: CN083005-6HN | C61: Máy làm đá viên, model: FPS-1500P. KT máy: (1225*970*1920)mm, kt thùng chứa đá: (1330*720*930)mm+/-10%, đ/áp: 220V/50Hz, CS: 682kg/24h. Nhãn hiệu: ASIMA, mới 100% | D61: PCE | E61: 3 | F61: 3940.06 | G61: =E61*F61 -> 11820.18 | I61: 84186990 | J61: =F61*$L$12 -> 1.0196875e+08 | K61: 104517950 | L61: =G61*$L$12 -> 3.0590626e+08 | M61: 0 | N61: =M61*L61 -> 0 | O61: =L61+N61 -> 3.0590626e+08 | P61: 0.08 | Q61: =O61*P61 -> 24472501 | R61: 157 | S61: =G61/R61 -> 75.287771 | T61: =L61 -> 3.0590626e+08 | U61: 17 | V61: =T61*U61 -> 5.2004064e+09 | W61: 189 | X61: =G61-W61 -> 11631.18
A62: 44 | B62: CN083104-34HN | C62: Máy massage đầu gối 5 chế độ hoạt động, dùng để massage thư giãn, giảm mỏi cơ vùng đầu gối. Công suất: 3.7V/10W, dung lượng pin 2000 mAh. Model: DG11.Hiệu: DELAX, mới 100% | D62: PCE | E62: 400 | F62: 19.98 | G62: =E62*F62 -> 7992 | I62: 90191010 | J62: =F62*$L$12 -> 517082.4 | K62: 530000 | L62: =G62*$L$12 -> 206832960 | M62: 0 | N62: =M62*L62 -> 0 | O62: =L62+N62 -> 206832960 | P62: 0.08 | Q62: =O62*P62 -> 16546637 | R62: 158 | S62: =G62/R62 -> 50.582278 | T62: =L62 -> 206832960 | U62: 18 | V62: =T62*U62 -> 3722993280 | W62: 147 | X62: =G62-W62 -> 7845
A63: 45 | B63: CN090310-79HN | C63: Chậu rửa bát bằng inox 201, chống ngưng tụ nước, 1 hộc dùng trong nhà bếp. KT: (450*400*215)mm+/-10%, kí hiệu: 4540-D(201)2.7mm, không hiệu. NSX: Foshan Jinyunke Kitchen & Bath Co., Ltd., mới 100% | D63: PCE | E63: 400 | F63: 10.41 | G63: =E63*F63 -> 4164 | I63: 73241010 | J63: =F63*$L$12 -> 269410.8 | K63: 289880 | L63: =G63*$L$12 -> 107764320 | M63: 0.05 | N63: =M63*L63 -> 5388216 | O63: =L63+N63 -> 113152536 | P63: 0.08 | Q63: =O63*P63 -> 9052202.9 | R63: 159 | S63: =G63/R63 -> 26.188679 | T63: =L63 -> 107764320 | U63: 19 | V63: =T63*U63 -> 2047522080 | W63: 177 | X63: =G63-W63 -> 3987
A64: 46 | C64: Chậu rửa bát bằng inox 201, chống ngưng tụ nước, 1 hộc dùng trong nhà bếp. KT: (500*400*215)mm+/-10%, kí hiệu: 5040-D(201)2.7mm, không hiệu. NSX: Foshan Jinyunke Kitchen & Bath Co., Ltd., mới 100% | D64: PCE | E64: 200 | F64: 10.77 | G64: =E64*F64 -> 2154 | I64: 73241010 | J64: =F64*$L$12 -> 278727.6 | K64: 300000 | L64: =G64*$L$12 -> 55745520 | M64: 0.05 | N64: =M64*L64 -> 2787276 | O64: =L64+N64 -> 58532796 | P64: 0.08 | Q64: =O64*P64 -> 4682623.7 | R64: 160 | S64: =G64/R64 -> 13.4625 | T64: =L64 -> 55745520 | U64: 20 | V64: =T64*U64 -> 1114910400 | W64: 367.5 | X64: =G64-W64 -> 1786.5
A65: 47 | C65: Chậu rửa bát bằng inox 201, chống ngưng tụ nước, 1 hộc dùng trong nhà bếp. KT: (600*450*215)mm+/-10%, kí hiệu: 6045-D(201)2.7mm, không hiệu. NSX: Foshan Jinyunke Kitchen & Bath Co., Ltd., mới 100% | D65: PCE | E65: 400 | F65: 11.09 | G65: =E65*F65 -> 4436 | I65: 73241010 | J65: =F65*$L$12 -> 287009.2 | K65: 308906 | L65: =G65*$L$12 -> 114803680 | M65: 0.05 | N65: =M65*L65 -> 5740184 | O65: =L65+N65 -> 120543864 | P65: 0.08 | Q65: =O65*P65 -> 9643509.1 | R65: 161 | S65: =G65/R65 -> 27.552795 | T65: =L65 -> 114803680 | U65: 21 | V65: =T65*U65 -> 2410877280 | W65: 481.5 | X65: =G65-W65 -> 3954.5
A66: 48 | C66: Chậu rửa bát bằng inox 201, chống ngưng tụ nước, 1 hộc dùng trong nhà bếp. KT: (600*450*215)mm+/-10%, kí hiệu: 6045-AE(201)2.7mm, không hiệu. NSX: Foshan Jinyunke Kitchen & Bath Co., Ltd., mới 100% | D66: PCE | E66: 200 | F66: 14.36 | G66: =E66*F66 -> 2872 | I66: 73241010 | J66: =F66*$L$12 -> 371636.8 | K66: 400000 | L66: =G66*$L$12 -> 74327360 | M66: 0.05 | N66: =M66*L66 -> 3716368 | O66: =L66+N66 -> 78043728 | P66: 0.08 | Q66: =O66*P66 -> 6243498.2 | R66: 162 | S66: =G66/R66 -> 17.728395 | T66: =L66 -> 74327360 | U66: 22 | V66: =T66*U66 -> 1635201920 | W66: 600 | X66: =G66-W66 -> 2272
A67: 49 | C67: Chậu rửa bát bằng inox 304, chống ngưng tụ nước, 1 hộc dùng trong nhà bếp, KT: (750*460*215)mm+/-10%, kí hiệu: 7546-B(304)5.0mm, không hiệu. NSX: Foshan Jinyunke Kitchen & Bath Co., Ltd., mới 100% | D67: PCE | E67: 60 | F67: 34.07 | G67: =E67*F67 -> 2044.2 | I67: 73241010 | J67: =F67*$L$12 -> 881731.6 | K67: 949020 | L67: =G67*$L$12 -> 52903896 | M67: 0.05 | N67: =M67*L67 -> 2645194.8 | O67: =L67+N67 -> 55549091 | P67: 0.08 | Q67: =O67*P67 -> 4443927.3 | R67: 163 | S67: =G67/R67 -> 12.541104 | T67: =L67 -> 52903896 | U67: 23 | V67: =T67*U67 -> 1216789608 | W67: 360 | X67: =G67-W67 -> 1684.2
A68: 50 | C68: Chậu rửa bát bằng inox 201, chống ngưng tụ nước, 1 hộc dùng trong nhà bếp, KT: (780*460*215)mm+/-10%, kí hiệu: 7846-A(201)2.7mm, không hiệu. NSX: Foshan Jinyunke Kitchen & Bath Co., Ltd., mới 100% | D68: PCE | E68: 100 | F68: 16.85 | G68: =E68*F68 -> 1685 | I68: 73241010 | J68: =F68*$L$12 -> 436078 | K68: 469300 | L68: =G68*$L$12 -> 43607800 | M68: 0.05 | N68: =M68*L68 -> 2180390 | O68: =L68+N68 -> 45788190 | P68: 0.08 | Q68: =O68*P68 -> 3663055.2 | R68: 164 | S68: =G68/R68 -> 10.27439 | T68: =L68 -> 43607800 | U68: 24 | V68: =T68*U68 -> 1.0465872e+09 | W68: 484 | X68: =G68-W68 -> 1201
A69: 51 | C69: Chậu rửa bát bằng inox 201, chống ngưng tụ nước, 2 hộc dùng trong nhà bếp, KT: (780*460*215)mm+/-10%, kí hiệu: 7846-AE(201)2.7mm, không hiệu. NSX: Foshan Jinyunke Kitchen & Bath Co., Ltd., mới 100% | D69: PCE | E69: 100 | F69: 20.46 | G69: =E69*F69 -> 2046 | I69: 73241010 | J69: =F69*$L$12 -> 529504.8 | K69: 569850 | L69: =G69*$L$12 -> 52950480 | M69: 0.05 | N69: =M69*L69 -> 2647524 | O69: =L69+N69 -> 55598004 | P69: 0.08 | Q69: =O69*P69 -> 4447840.3 | R69: 165 | S69: =G69/R69 -> 12.4 | T69: =L69 -> 52950480 | U69: 25 | V69: =T69*U69 -> 1323762000 | W69: 588 | X69: =G69-W69 -> 1458
A70: 52 | B70: CN080904-4HN CN082823-2HN | C70: Điều khiển cửa cuốn từ xa, loại điều khiển bằng sóng hồng ngoại, vỏ bằng nhựa tổng hợp, không chứa dữ liệu, mật mã dân sự, sử dụng pin 23A/12V, không hiệu. Nsx: Zhejiang Zhiyuan Factory. Mới 100% | D70: PCE | E70: 5000 | F70: 0.94 | G70: =E70*F70 -> 4700 | I70: 85437029 | J70: =F70*$L$12 -> 24327.2 | K70: 25000 | L70: =G70*$L$12 -> 121636000 | M70: 0 | N70: =M70*L70 -> 0 | O70: =L70+N70 -> 121636000 | P70: 0.08 | Q70: =O70*P70 -> 9730880 | R70: 166 | S70: =G70/R70 -> 28.313253 | T70: =L70 -> 121636000 | U70: 26 | V70: =T70*U70 -> 3162536000 | W70: 632 | X70: =G70-W70 -> 4068
A71: 53 | B71: CN081808-1HN | C71: Bộ điều khiển cửa cuốn gồm 1 hộp tín hiệu trung tâm và 2 tay khiển, loại điều khiển bằng sóng hồng ngoại, vỏ bằng nhựa tổng hợp, không chứa dữ liệu, mật mã dân sự,dùng pin 23A/12V, không hiệu.Mới 100% | D71: SET | E71: 200 | F71: 5.65 | G71: =E71*F71 -> 1130 | I71: 85437029 | J71: =F71*$L$12 -> 146222 | K71: 150000 | L71: =G71*$L$12 -> 29244400 | M71: 0 | N71: =M71*L71 -> 0 | O71: =L71+N71 -> 29244400 | P71: 0.08 | Q71: =O71*P71 -> 2339552 | R71: 167 | S71: =G71/R71 -> 6.7664671 | T71: =L71 -> 29244400 | U71: 27 | V71: =T71*U71 -> 789598800 | W71: 980 | X71: =G71-W71 -> 150
A72: 54 | C72: Bộ điều khiển cửa cuốn gồm 1 hộp tín hiệu trung tâm và 2 tay khiển nắp trượt, loại điều khiển bằng sóng hồng ngoại, vỏ bằng nhựa tổng hợp, không chứa dữ liệu, mmds,dùng pin 23A/12V,không hiệu.Mới 100% | D72: SET | E72: 500 | F72: 7.54 | G72: =E72*F72 -> 3770 | I72: 85437029 | J72: =F72*$L$12 -> 195135.2 | K72: 200000 | L72: =G72*$L$12 -> 97567600 | M72: 0 | N72: =M72*L72 -> 0 | O72: =L72+N72 -> 97567600 | P72: 0.08 | Q72: =O72*P72 -> 7805408 | R72: 168 | S72: =G72/R72 -> 22.440476 | T72: =L72 -> 97567600 | U72: 28 | V72: =T72*U72 -> 2731892800 | W72: 82 | X72: =G72-W72 -> 3688
A73: 55 | B73: CN081904-25HN | C73: Công tắc hành trình dùng cho cửa cuốn để xác định điểm dừng khi đóng/mở cửa, đ/a: 250V, dòng điện 5A, đ/a:250V, KH: ME-9101 không hiệu, Nsx: Zhejiang Zhiyuan Factory, mới 100% | D73: PCE | E73: 1000 | F73: 0.68 | G73: =E73*F73 -> 680 | I73: 85365096 | J73: =F73*$L$12 -> 17598.4 | K73: 18000 | L73: =G73*$L$12 -> 17598400 | M73: 0 | N73: =M73*L73 -> 0 | O73: =L73+N73 -> 17598400 | P73: 0.08 | Q73: =O73*P73 -> 1407872 | R73: 169 | S73: =G73/R73 -> 4.0236686 | T73: =L73 -> 17598400 | U73: 29 | V73: =T73*U73 -> 510353600 | W73: 189 | X73: =G73-W73 -> 491
A74: 56 | C74: Công tắc hành trình dùng cho cửa cuốn để xác định điểm dừng khi đóng/mở cửa, đ/a: 220V, dòng điện 5A, đ/a:250V, KH: ME-8108, không hiệu, Nsx: Zhejiang Zhiyuan Factory, mới 100% | D74: PCE | E74: 4000 | F74: 0.75 | G74: =E74*F74 -> 3000 | I74: 85365096 | J74: =F74*$L$12 -> 19410 | K74: 20000 | L74: =G74*$L$12 -> 77640000 | M74: 0 | N74: =M74*L74 -> 0 | O74: =L74+N74 -> 77640000 | P74: 0.08 | Q74: =O74*P74 -> 6211200 | R74: 170 | S74: =G74/R74 -> 17.647059 | T74: =L74 -> 77640000 | U74: 30 | V74: =T74*U74 -> 2329200000 | W74: 94 | X74: =G74-W74 -> 2906
A75: 57 | B75: CN082813-2HN | C75: Bộ nguồn adapter đa năng có núm xoay điều chỉnh điện áp dùng cho thiết bị massage điện đá nóng, model: 31220, đ/a đầu ra: 3-12V, dòng điện 2A, không hiệu, NSX: Shanghai Metal & Plastic. Mới 100% | D75: SET | E75: 2000 | F75: 1.7 | G75: =E75*F75 -> 3400 | I75: 85044090 | J75: =F75*$L$12 -> 43996 | K75: 45000 | L75: =G75*$L$12 -> 87992000 | M75: 0 | N75: =M75*L75 -> 0 | O75: =L75+N75 -> 87992000 | P75: 0.08 | Q75: =O75*P75 -> 7039360 | R75: 171 | S75: =G75/R75 -> 19.883041 | T75: =L75 -> 87992000 | U75: 31 | V75: =T75*U75 -> 2727752000 | W75: 1920 | X75: =G75-W75 -> 1480
A76: 58 | B76: CN083011-3HN | C76: Dây thắt lưng nam nữ đục lỗ hình ngôi sao, 4 màu đen, trắng, hồng, vàng, chất liệu nhựa giả da (PU), KT: rộng 1.8cm, dài 105cm+-10%, không hiệu, Nsx: Qingdao fashion Co., Ltd, Mới 100% | D76: PCE | E76: 800 | F76: 0.17 | G76: =E76*F76 -> 136 | I76: 39262090 | J76: =F76*$L$12 -> 4399.6 | K76: 4500 | L76: =G76*$L$12 -> 3519680 | M76: 0 | N76: =M76*L76 -> 0 | O76: =L76+N76 -> 3519680 | P76: 0.08 | Q76: =O76*P76 -> 281574.4 | R76: 172 | S76: =G76/R76 -> 0.79069767 | T76: =L76 -> 3519680 | U76: 32 | V76: =T76*U76 -> 112629760 | W76: 493.2 | X76: =G76-W76 -> -357.2
A77: 59 | C77: Dây thắt lưng nam nữ Y2K họa tiết ngôi sao, chất liệu nhựa gải da (PU), mặt khóa mạ màu bạc, KH:OLL403, KT: rộng 2.8cm, dài 105cm+-10%, không hiệu, Nsx: Qingdao fashion Co., Ltd, Mới 100% | D77: PCE | E77: 200 | F77: 0.188 | G77: =E77*F77 -> 37.6 | I77: 39262090 | J77: =F77*$L$12 -> 4865.44 | K77: 5000 | L77: =G77*$L$12 -> 973088 | M77: 0 | N77: =M77*L77 -> 0 | O77: =L77+N77 -> 973088 | P77: 0.08 | Q77: =O77*P77 -> 77847.04 | R77: 173 | S77: =G77/R77 -> 0.21734104 | T77: =L77 -> 973088 | U77: 33 | V77: =T77*U77 -> 32111904 | W77: 527 | X77: =G77-W77 -> -489.4
A78: 60 | C78: Dây thắt lưng nam nữ Y2K chất liệu nhựa giả da (PU), KT: rộng 2.8cm, dài 105cm+-10%, KH: OLL402, không hiệu, Nsx: Qingdao fashion Co., Ltd, Mới 100% | D78: PCE | E78: 100 | F78: 0.188 | G78: =E78*F78 -> 18.8 | I78: 39262090 | J78: =F78*$L$12 -> 4865.44 | K78: 5000 | L78: =G78*$L$12 -> 486544 | M78: 0 | N78: =M78*L78 -> 0 | O78: =L78+N78 -> 486544 | P78: 0.08 | Q78: =O78*P78 -> 38923.52 | R78: 174 | S78: =G78/R78 -> 0.10804598 | T78: =L78 -> 486544 | U78: 34 | V78: =T78*U78 -> 16542496 | W78: 150 | X78: =G78-W78 -> -131.2
A79: 61 | B79: CN083102-5HN | C79: Nắp bồn cầu chất liệu nhựa tổng hợp, KT: 445*360mm+-10%, KH: K-4713T, không hiệu,NSX: Toilet Seat Manufacturer (Xiamen), mới 100% | D79: PCE | E79: 100 | F79: 27.14 | G79: =E79*F79 -> 2714 | I79: 39222000 | J79: =F79*$L$12 -> 702383.2 | K79: 720000 | L79: =G79*$L$12 -> 70238320 | M79: 0 | N79: =M79*L79 -> 0 | O79: =L79+N79 -> 70238320 | P79: 0.08 | Q79: =O79*P79 -> 5619065.6 | R79: 175 | S79: =G79/R79 -> 15.508571 | T79: =L79 -> 70238320 | U79: 35 | V79: =T79*U79 -> 2458341200 | W79: 54.72 | X79: =G79-W79 -> 2659.28
A80: 62 | B80: CN083103-2HN | C80: Bàn chải cọ rửa vệ sinh bình sữa, chất liệu nhựa tổng hợp, KT:28*6,5cm+-10%, không hiệu, NSX: Guangdong Stationery Co., Ltd.,mới 100% | D80: PCE | E80: 900 | F80: 0.17 | G80: =E80*F80 -> 153 | I80: 96039040 | J80: =F80*$L$12 -> 4399.6 | K80: 4500 | L80: =G80*$L$12 -> 3959640 | M80: 0 | N80: =M80*L80 -> 0 | O80: =L80+N80 -> 3959640 | P80: 0.08 | Q80: =O80*P80 -> 316771.2 | R80: 176 | S80: =G80/R80 -> 0.86931818 | T80: =L80 -> 3959640 | U80: 36 | V80: =T80*U80 -> 142547040 | W80: 190 | X80: =G80-W80 -> -37
A81: 63 | B81: CN083106-1HN | C81: Bộ khóa cửa dùng cho cửa cuốn gồm thân khóa, 3 chìa dẹt và phụ kiện lắp đặt, chất liệu sắt kết hợp nhựa, KT:4*20cm+-10%, không hiệu, Nsx: Zhejiang Zhiyuan Factory, mới 100% | D81: SET | E81: 1000 | F81: 1.88 | G81: =E81*F81 -> 1880 | I81: 83014020 | J81: =F81*$L$12 -> 48654.4 | K81: 50000 | L81: =G81*$L$12 -> 48654400 | M81: 0.05 | N81: =M81*L81 -> 2432720 | O81: =L81+N81 -> 51087120 | P81: 0.08 | Q81: =O81*P81 -> 4086969.6 | R81: 177 | S81: =G81/R81 -> 10.621469 | T81: =L81 -> 48654400 | U81: 37 | V81: =T81*U81 -> 1800212800 | W81: 76.8 | X81: =G81-W81 -> 1803.2
A82: 64 | C82: Bộ khóa cửa dùng cho cửa cuốn gồm thân khóa, 4 chìa chữ thập và phụ kiện lắp đặt, chất liệu sắt kết hợp nhựa, KT:4*20cm+-10%, không hiệu, Nsx: Zhejiang Zhiyuan Factory, mới 100% | D82: SET | E82: 1000 | F82: 3.39 | G82: =E82*F82 -> 3390 | I82: 83014020 | J82: =F82*$L$12 -> 87733.2 | K82: 90000 | L82: =G82*$L$12 -> 87733200 | M82: 0.05 | N82: =M82*L82 -> 4386660 | O82: =L82+N82 -> 92119860 | P82: 0.08 | Q82: =O82*P82 -> 7369588.8 | R82: 178 | S82: =G82/R82 -> 19.044944 | T82: =L82 -> 87733200 | U82: 38 | V82: =T82*U82 -> 3333861600 | W82: 248.4 | X82: =G82-W82 -> 3141.6
A83: 65 | B83: CN083107-39HN | C83: Dải nhựa dạng cuộn dùng để bọc cạnh bàn chống va đập, bằng nhựa PVC xốp 1 mặt tự dính, KT: dài 200x3cm +/-10%.không hiệu.Nsx: Taizhou Plastic Mould. mới 100% | D83: ROL | E83: 560 | F83: 0.188 | G83: =E83*F83 -> 105.28 | I83: 39191010 | J83: =F83*$L$12 -> 4865.44 | K83: 5000 | L83: =G83*$L$12 -> 2724646.4 | M83: 0 | N83: =M83*L83 -> 0 | O83: =L83+N83 -> 2724646.4 | P83: 0.08 | Q83: =O83*P83 -> 217971.71 | R83: 179 | S83: =G83/R83 -> 0.58815642 | T83: =L83 -> 2724646.4 | U83: 39 | V83: =T83*U83 -> 1.0626121e+08 | W83: 155.5 | X83: =G83-W83 -> -50.22
A84: 66 | C84: Dải nhựa dạng cuộn dùng để bọc cạnh bàn chống va đập, bằng nhựa PVC xốp 1 mặt tự dính, KT: dài 200x8cm +/-10%.không hiệu.Nsx: Taizhou Plastic Mould. mới 100% | D84: ROL | E84: 1500 | F84: 0.38 | G84: =E84*F84 -> 570 | I84: 39191010 | J84: =F84*$L$12 -> 9834.4 | K84: 10000 | L84: =G84*$L$12 -> 14751600 | M84: 0 | N84: =M84*L84 -> 0 | O84: =L84+N84 -> 14751600 | P84: 0.08 | Q84: =O84*P84 -> 1180128 | R84: 141 | S84: =G84/R84 -> 4.0425532 | T84: =L84 -> 14751600 | U84: 0 | V84: =T84*U84 -> 0 | W84: 141 | X84: =G84-W84 -> 429
A85: 67 | C85: Dải nhựa dạng cuộn dùng để bọc cạnh bàn chống va đập, bằng nhựa PVC xốp 1 mặt tự dính, KT: dài 200x5cm +/-10%.không hiệu.Nsx: Taizhou Plastic Mould. mới 100% | D85: ROL | E85: 480 | F85: 0.226 | G85: =E85*F85 -> 108.48 | I85: 39191010 | J85: =F85*$L$12 -> 5848.88 | K85: 6000 | L85: =G85*$L$12 -> 2807462.4 | M85: 0 | N85: =M85*L85 -> 0 | O85: =L85+N85 -> 2807462.4 | P85: 0.08 | Q85: =O85*P85 -> 224596.99 | R85: 142 | S85: =G85/R85 -> 0.76394366 | T85: =L85 -> 2807462.4 | U85: 0 | V85: =T85*U85 -> 0 | W85: 160.6 | X85: =G85-W85 -> -52.12
A86: 68 | C86: Miếng nhựa bọc góc bàn chữ L chống va đập, bằng nhựa PVC xốp, 1 mặt tự dính, 5 cái/ túi, KT: dài 3.5x6cm +/-10%.không hiệu.Nsx: Taizhou Plastic Mould. mới 100% | D86: PCE | E86: 800 | F86: 0.3 | G86: =E86*F86 -> 240 | I86: 39269099 | J86: =F86*$L$12 -> 7764 | K86: 8000 | L86: =G86*$L$12 -> 6211200 | M86: 0 | N86: =M86*L86 -> 0 | O86: =L86+N86 -> 6211200 | P86: 0.08 | Q86: =O86*P86 -> 496896 | R86: 143 | S86: =G86/R86 -> 1.6783217 | T86: =L86 -> 6211200 | U86: 0 | V86: =T86*U86 -> 0 | W86: 160 | X86: =G86-W86 -> 80
A87: 69 | B87: CN083108-2HN | C87: Bộ lọc dầu dùng cho máy nén khí trục vít QX105047. KT: 114x40x230mm+-10%, lưu lượng:120-180l/p, đk ren:38mm, không hiệu. NSX: Jiangxi Sange Filter. Mới 100% | D87: PCE | E87: 18 | F87: 148.9 | G87: =E87*F87 -> 2680.2 | I87: 84212950 | J87: =F87*$L$12 -> 3853532 | K87: 3950000 | L87: =G87*$L$12 -> 69363576 | M87: 0 | N87: =M87*L87 -> 0 | O87: =L87+N87 -> 69363576 | P87: 0.08 | Q87: =O87*P87 -> 5549086.1 | R87: 144 | S87: =G87/R87 -> 18.6125 | T87: =L87 -> 69363576 | U87: 0 | V87: =T87*U87 -> 0 | W87: 63.72 | X87: =G87-W87 -> 2616.48
A88: 70 | C88: Bộ lọc dầu dùng cho máy nén khí trục vít 04425274. KT: 1135*308*100mm+-10%, lưu lượng:120-180l/p, đk ren 38mm, không hiệu. Nsx: Ingersoll Rand. Mới 100% | D88: PCE | E88: 10 | F88: 122.52 | G88: =E88*F88 -> 1225.2 | I88: 84212950 | J88: =F88*$L$12 -> 3170817.6 | K88: 3250000 | L88: =G88*$L$12 -> 31708176 | M88: 0 | N88: =M88*L88 -> 0 | O88: =L88+N88 -> 31708176 | P88: 0.08 | Q88: =O88*P88 -> 2536654.1 | R88: 145 | S88: =G88/R88 -> 8.4496552 | T88: =L88 -> 31708176 | U88: 0 | V88: =T88*U88 -> 0 | W88: 92.4 | X88: =G88-W88 -> 1132.8
A89: 71 | B89: CN083110-60HN | C89: Bộ điều khiển cửa cuốn gồm 1 hộp tín hiệu trung tâm và 3 tay khiển, loại điều khiển bằng sóng hồng ngoại, vỏ bằng nhựa tổng hợp, không chứa dữ liệu, MMDS, sử dụng pin 23A/12V, hiệu: Macdoor. Mới 100% | D89: SET | E89: 500 | F89: 18.85 | G89: =E89*F89 -> 9425 | I89: 85437029 | J89: =F89*$L$12 -> 487838 | K89: 500000 | L89: =G89*$L$12 -> 243919000 | M89: 0 | N89: =M89*L89 -> 0 | O89: =L89+N89 -> 243919000 | P89: 0.08 | Q89: =O89*P89 -> 19513520 | R89: 146 | S89: =G89/R89 -> 64.554795 | T89: =L89 -> 243919000 | U89: 0 | V89: =T89*U89 -> 0 | W89: 92.4 | X89: =G89-W89 -> 9332.6
A90: 72 | C90: Bộ điều khiển cửa cuốn gồm 1 hộp tín hiệu trung tâm và 2 tay khiển, loại điều khiển bằng sóng hồng ngoại, không chứa dữ liệu, MMDS, sử dụng pin 23A/12V, hiệu: Safety controller. Mới 100% | D90: SET | E90: 700 | F90: 11.31 | G90: =E90*F90 -> 7917 | I90: 85437029 | J90: =F90*$L$12 -> 292702.8 | K90: 300000 | L90: =G90*$L$12 -> 204891960 | M90: 0 | N90: =M90*L90 -> 0 | O90: =L90+N90 -> 204891960 | P90: 0.08 | Q90: =O90*P90 -> 16391357 | R90: 147 | S90: =G90/R90 -> 53.857143 | T90: =L90 -> 204891960 | U90: 0 | V90: =T90*U90 -> 0 | W90: 92.4 | X90: =G90-W90 -> 7824.6
A91: 73 | B91: CN083111-7HN | C91: Bàn chải cọ rửa vệ sinh đa năng loại không dùng điện, tay cầm bằng nhựa mặt cọ bằng miếng bọt biển mút xốp. KT: dài 30*8*5cm +/-10, không hiệu, Nsx: Picc property and casualty Co.,ltd, mới 100% | D91: PCE | E91: 980 | F91: 0.3 | G91: =E91*F91 -> 294 | I91: 96039040 | J91: =F91*$L$12 -> 7764 | K91: 8000 | L91: =G91*$L$12 -> 7608720 | M91: 0 | N91: =M91*L91 -> 0 | O91: =L91+N91 -> 7608720 | P91: 0.08 | Q91: =O91*P91 -> 608697.6 | R91: 148 | S91: =G91/R91 -> 1.9864865 | T91: =L91 -> 7608720 | U91: 0 | V91: =T91*U91 -> 0 | W91: 226 | X91: =G91-W91 -> 68
A92: 74 | B92: CN083112-4HN | C92: Động cơ vạn năng dây đồng xoay chiều/1 chiều, dùng cho máy xay thực phẩm, Đ/a: 220V/24V, cs: 600w, Không hiệu. Nsx: Wenzhou Feiding Motor. Mới 100% | D92: PCE | E92: 128 | F92: 6.03 | G92: =E92*F92 -> 771.84 | I92: 85012012 | J92: =F92*$L$12 -> 156056.4 | K92: 160000 | L92: =G92*$L$12 -> 19975219 | M92: 0 | N92: =M92*L92 -> 0 | O92: =L92+N92 -> 19975219 | P92: 0.08 | Q92: =O92*P92 -> 1598017.5 | R92: 149 | S92: =G92/R92 -> 5.1801342 | T92: =L92 -> 19975219 | U92: 0 | V92: =T92*U92 -> 0 | W92: 151 | X92: =G92-W92 -> 620.84
A93: 75 | B93: CN090212-7HN | C93: Động cơ vạn năng 7712 dây đồng xoay chiều/1 chiều dùng để chế tạo các loại máy công cụ mini cầm tay, đ/a: 220v/12V. cs: 200w, Không hiệu. Nsx: Wenzhou Feiding Motor. Mới 100% | D93: PCE | E93: 1000 | F93: 1.06 | G93: =E93*F93 -> 1060 | I93: 85012019 | J93: =F93*$L$12 -> 27432.8 | K93: 28240 | L93: =G93*$L$12 -> 27432800 | M93: 0 | N93: =M93*L93 -> 0 | O93: =L93+N93 -> 27432800 | P93: 0.08 | Q93: =O93*P93 -> 2194624 | W93: 820 | X93: =G93-W93 -> 240
A94: 76 | B94: CN083115-34HN | C94: Khay nhựa tổng hợp vân kim cương, dùng để đựng đồ trang điểm, trang sức (không chứa đựng thực phẩm), KT: (24*15-18*18)cm+/-10%, không hiệu, Nsx: Dongguan Huashuo Industrial Co., Ltd., mới 100% | D94: PCE | E94: 200 | F94: 1.69 | G94: =E94*F94 -> 338 | I94: 39249090 | J94: =F94*$L$12 -> 43737.2 | K94: 45000 | L94: =G94*$L$12 -> 8747440 | M94: 0 | N94: =M94*L94 -> 0 | O94: =L94+N94 -> 8747440 | P94: 0.08 | Q94: =O94*P94 -> 699795.2 | W94: 360 | X94: =G94-W94 -> -22
A95: 77 | B95: CN090102-13HN | C95: Giày thể thao beier viền xanh, viền xám, đế giày bằng cao su mềm, thân và mũi giày bằng da tổng hợp phối vải lưới, màu trắng size 36-40, hiệu Beier, mới 100% | D95: PR | E95: 130 | F95: 3.02 | G95: =E95*F95 -> 392.6 | I95: 64051000 | J95: =F95*$L$12 -> 78157.6 | K95: 80000 | L95: =G95*$L$12 -> 10160488 | M95: 0 | N95: =M95*L95 -> 0 | O95: =L95+N95 -> 10160488 | P95: 0.08 | Q95: =O95*P95 -> 812839.04 | W95: 5280 | X95: =G95-W95 -> -4887.4
A96: 78 | C96: Giày sneaker beier kitty, đế giày bằng cao su mềm, thân và mũi giày bằng da tổng hợp phối vải lưới, 2 màu hồng , be, size 36-40, hiệu Beier, mới 100% | D96: PR | E96: 75 | F96: 3.02 | G96: =E96*F96 -> 226.5 | I96: 64051000 | J96: =F96*$L$12 -> 78157.6 | K96: 80000 | L96: =G96*$L$12 -> 5861820 | M96: 0 | N96: =M96*L96 -> 0 | O96: =L96+N96 -> 5861820 | P96: 0.08 | Q96: =O96*P96 -> 468945.6 | W96: 277.2 | X96: =G96-W96 -> -50.7
A97: 79 | C97: Giày búp bê nữ beier, đế giày bằng cao su mềm, thân và mũi giày bằng da tổng hợp phối vải lưới, 2 màu be, trắng size 36-40, hiệu Beier, mới 100% | D97: PR | E97: 180 | F97: 3.02 | G97: =E97*F97 -> 543.6 | I97: 64051000 | J97: =F97*$L$12 -> 78157.6 | K97: 80000 | L97: =G97*$L$12 -> 14068368 | M97: 0 | N97: =M97*L97 -> 0 | O97: =L97+N97 -> 14068368 | P97: 0.08 | Q97: =O97*P97 -> 1125469.4 | W97: 300 | X97: =G97-W97 -> 243.6
A98: 80 | B98: CN090103-10HN | C98: Đồng hồ đo nhiệt độ và độ ẩm cơ học (Th600B) đo không khí trong phòng, không dùng điện, chất liệu inox. KT: (20.5*16)cm+/-10%, hiệu: ANYMETRE, mới 100% | D98: PCE | E98: 400 | F98: 1.88 | G98: =E98*F98 -> 752 | I98: 90258000 | J98: =F98*$L$12 -> 48654.4 | K98: 50000 | L98: =G98*$L$12 -> 19461760 | M98: 0 | N98: =M98*L98 -> 0 | O98: =L98+N98 -> 19461760 | P98: 0.08 | Q98: =O98*P98 -> 1556940.8 | W98: 144 | X98: =G98-W98 -> 608
A99: 81 | B99: CN090104-3HN | C99: Đế nhựa dùng để cắm hoa bằng nhựa ABS, KT: 6.8*4.4cm, không hiệu, NSX: Ningbo Bonais Stationery Co., Ltd., mới 100% | D99: PCE | E99: 1600 | F99: 0.094 | G99: =E99*F99 -> 150.4 | I99: 39269099 | J99: =F99*$L$12 -> 2432.72 | K99: 2500 | L99: =G99*$L$12 -> 3892352 | M99: 0 | N99: =M99*L99 -> 0 | O99: =L99+N99 -> 3892352 | P99: 0.08 | Q99: =O99*P99 -> 311388.16 | W99: 271.2 | X99: =G99-W99 -> -120.8
A100: 82 | B100: CN090105-40HN | C100: Tấm lưới chắn thùng xe container bằng sợi vải dù polyester, KT:2.4m*2.6m+-10%, không hiệu, NSX: Shandong Zhongxian Rope & Net Co., Ltd, mới 100% | D100: PCE | E100: 2768 | F100: 1.32 | G100: =E100*F100 -> 3653.76 | I100: 56081990 | J100: =F100*$L$12 -> 34161.6 | K100: 35000 | L100: =G100*$L$12 -> 94559309 | M100: 0 | N100: =M100*L100 -> 0 | O100: =L100+N100 -> 94559309 | P100: 0.08 | Q100: =O100*P100 -> 7564744.7 | W100: 271.2 | X100: =G100-W100 -> 3382.56
A101: 83 | B101: CN090108-152HN | C101: Đèn vòm bán nguyệt chuyên dụng lắp trên bàn làm nail, spa, sử dụng nguồn sáng đi-ốt phát quang LED không phải quang điện, model:2415. CS:36W/AC100-240V. Không hiệu. NSX:Zhongshan Ledlighning. Mới 100% | D101: PCE | E101: 600 | F101: 20.73 | G101: =E101*F101 -> 12438 | I101: 94054290 | J101: =F101*$L$12 -> 536492.4 | K101: 550000 | L101: =G101*$L$12 -> 321895440 | M101: 0 | N101: =M101*L101 -> 0 | O101: =L101+N101 -> 321895440 | P101: 0.08 | Q101: =O101*P101 -> 25751635 | W101: 900 | X101: =G101-W101 -> 11538
A102: 84 | B102: CN090112-31HN | C102: Dây cáp truyền dẫn tín hiệu âm thanh cho tivi đã gắn đầu nối dài 1.8m, không phải cáp điện, không dùng cho viễn thông, lõi nhôm, cách điện bằng nhựa, dòng 48V, ĐK lõi 1mm.Không hiệu.Mới 100% | D102: PCE | E102: 2830 | F102: 0.75 | G102: =E102*F102 -> 2122.5 | I102: 85444299 | J102: =F102*$L$12 -> 19410 | K102: 20000 | L102: =G102*$L$12 -> 54930300 | M102: 0 | N102: =M102*L102 -> 0 | O102: =L102+N102 -> 54930300 | P102: 0.08 | Q102: =O102*P102 -> 4394424 | W102: 252 | X102: =G102-W102 -> 1870.5
...

Sheet INV TIẾNG ANH
A1: PINGXIANG GUIFENG TRADING CO.,LTD
A2: ADD: NO.6 PHASE II PAVEMENT BAIYUN FIELD TIANNAN SECONDARY PINGXIANG CITY GUANGXI CHINA
A3: COMMERCIAL INVOICE | H3: CẤM XÓA
D4: No: | E4: =I4&"GF-TH/26" -> 0902 GF-TH/26 | H4: Số HĐ | I4: ='HỢP ĐỒNG'!$I$1 -> 0902 | J4: =I4&"GF-TH/26" -> 0902 GF-TH/26
D5: Date: | E5: ='HỢP ĐỒNG'!I2+1 -> 46271 | H5: Ngày Hợp đồng | I5: ='HỢP ĐỒNG'!I2 -> 46270
A6: BUYER: TRUONG HAI TRADING AND IMPORT-EXPORT COMPANY LIMITED
A7: Address: No. 12, Secondary Road No. 4, Phu Loc 2 Urban Area, Ky Lua Ward, Lang Son Province, Vietnam.
A9: No | B9: Product name | C9: Unit | D9: Quantity | E9: Unit price (USD) | F9: Total (USD) | G9: HS CODE
A10: ='HỢP ĐỒNG'!A19 -> 1 | B10: ='INVOICE lam CO'!B15 -> Dusting cloth | C10: ='INVOICE lam CO'!D15 -> PCE | D10: ='INVOICE lam CO'!E15 -> 20000 | E10: ='HỢP ĐỒNG'!F19 -> 0.094 | F10: ='HỢP ĐỒNG'!G19 -> 1880 | G10: ='HỢP ĐỒNG'!I19 -> 63071090 | H10: ='HỢP ĐỒNG'!I19 -> 63071090
A11: ='HỢP ĐỒNG'!A20 -> 2 | B11: ='INVOICE lam CO'!B16 -> Tea set | C11: ='INVOICE lam CO'!D16 -> SET | D11: ='INVOICE lam CO'!E16 -> 20 | E11: ='HỢP ĐỒNG'!F20 -> 5.16 | F11: ='HỢP ĐỒNG'!G20 -> 103.2 | G11: ='HỢP ĐỒNG'!I20 -> 69120000 | H11: ='HỢP ĐỒNG'!I20 -> 69120000
A12: ='HỢP ĐỒNG'!A21 -> 3 | B12: ='INVOICE lam CO'!B17 -> Tea set | C12: ='INVOICE lam CO'!D17 -> SET | D12: ='INVOICE lam CO'!E17 -> 20 | E12: ='HỢP ĐỒNG'!F21 -> 4.09 | F12: ='HỢP ĐỒNG'!G21 -> 81.8 | G12: ='HỢP ĐỒNG'!I21 -> 69120000 | H12: ='HỢP ĐỒNG'!I21 -> 69120000
A13: ='HỢP ĐỒNG'!A22 -> 4 | B13: ='INVOICE lam CO'!B18 -> Tea set | C13: ='INVOICE lam CO'!D18 -> SET | D13: ='INVOICE lam CO'!E18 -> 50 | E13: ='HỢP ĐỒNG'!F22 -> 5.69 | F13: ='HỢP ĐỒNG'!G22 -> 284.5 | G13: ='HỢP ĐỒNG'!I22 -> 69120000 | H13: ='HỢP ĐỒNG'!I22 -> 69120000
A14: ='HỢP ĐỒNG'!A23 -> 5 | B14: ='INVOICE lam CO'!B19 -> Teapot | C14: ='INVOICE lam CO'!D19 -> PCE | D14: ='INVOICE lam CO'!E19 -> 10 | E14: ='HỢP ĐỒNG'!F23 -> 13.6 | F14: ='HỢP ĐỒNG'!G23 -> 136 | G14: ='HỢP ĐỒNG'!I23 -> 69120000 | H14: ='HỢP ĐỒNG'!I23 -> 69120000
A15: ='HỢP ĐỒNG'!A24 -> 6 | B15: ='INVOICE lam CO'!B20 -> Teapot | C15: ='INVOICE lam CO'!D20 -> PCE | D15: ='INVOICE lam CO'!E20 -> 15 | E15: ='HỢP ĐỒNG'!F24 -> 10.46 | F15: ='HỢP ĐỒNG'!G24 -> 156.9 | G15: ='HỢP ĐỒNG'!I24 -> 69120000 | H15: ='HỢP ĐỒNG'!I24 -> 69120000
A16: ='HỢP ĐỒNG'!A25 -> 7 | B16: ='INVOICE lam CO'!B21 -> Tea cup | C16: ='INVOICE lam CO'!D21 -> PCE | D16: ='INVOICE lam CO'!E21 -> 20 | E16: ='HỢP ĐỒNG'!F25 -> 4.49 | F16: ='HỢP ĐỒNG'!G25 -> 89.8 | G16: ='HỢP ĐỒNG'!I25 -> 69120000 | H16: ='HỢP ĐỒNG'!I25 -> 69120000
A17: ='HỢP ĐỒNG'!A26 -> 8 | B17: ='INVOICE lam CO'!B22 -> Teapot | C17: ='INVOICE lam CO'!D22 -> PCE | D17: ='INVOICE lam CO'!E22 -> 10 | E17: ='HỢP ĐỒNG'!F26 -> 16.74 | F17: ='HỢP ĐỒNG'!G26 -> 167.4 | G17: ='HỢP ĐỒNG'!I26 -> 69120000 | H17: ='HỢP ĐỒNG'!I26 -> 69120000
A18: ='HỢP ĐỒNG'!A27 -> 9 | B18: ='INVOICE lam CO'!B23 -> Teapot | C18: ='INVOICE lam CO'!D23 -> PCE | D18: ='INVOICE lam CO'!E23 -> 5 | E18: ='HỢP ĐỒNG'!F27 -> 15.69 | F18: ='HỢP ĐỒNG'!G27 -> 78.45 | G18: ='HỢP ĐỒNG'!I27 -> 69120000 | H18: ='HỢP ĐỒNG'!I27 -> 69120000
A19: ='HỢP ĐỒNG'!A28 -> 10 | B19: ='INVOICE lam CO'!B24 -> Teapot | C19: ='INVOICE lam CO'!D24 -> PCE | D19: ='INVOICE lam CO'!E24 -> 10 | E19: ='HỢP ĐỒNG'!F28 -> 17.09 | F19: ='HỢP ĐỒNG'!G28 -> 170.9 | G19: ='HỢP ĐỒNG'!I28 -> 69120000 | H19: ='HỢP ĐỒNG'!I28 -> 69120000
A20: ='HỢP ĐỒNG'!A29 -> 11 | B20: ='INVOICE lam CO'!B25 -> Teapot | C20: ='INVOICE lam CO'!D25 -> PCE | D20: ='INVOICE lam CO'!E25 -> 10 | E20: ='HỢP ĐỒNG'!F29 -> 14.47 | F20: ='HỢP ĐỒNG'!G29 -> 144.7 | G20: ='HỢP ĐỒNG'!I29 -> 69120000 | H20: ='HỢP ĐỒNG'!I29 -> 69120000
A21: ='HỢP ĐỒNG'!A30 -> 12 | B21: ='INVOICE lam CO'!B26 -> Teapot | C21: ='INVOICE lam CO'!D26 -> PCE | D21: ='INVOICE lam CO'!E26 -> 3 | E21: ='HỢP ĐỒNG'!F30 -> 20.46 | F21: ='HỢP ĐỒNG'!G30 -> 61.38 | G21: ='HỢP ĐỒNG'!I30 -> 69120000 | H21: ='HỢP ĐỒNG'!I30 -> 69120000
... A131: ='HỢP ĐỒNG'!A140 -> 122 | B131: ='INVOICE lam CO'!B136 -> Artificial tulip | C131: ='INVOICE lam CO'!D136 -> PCE | D131: ='INVOICE lam CO'!E136 -> 10000 | E131: ='HỢP ĐỒNG'!F140 -> 0.075 | F131: ='HỢP ĐỒNG'!G140 -> 750 | G131: ='HỢP ĐỒNG'!I140 -> 67029090 | H131: ='HỢP ĐỒNG'!I140 -> 67029090
A132: ='HỢP ĐỒNG'!A141 -> 123 | B132: ='INVOICE lam CO'!B137 -> Flower wrapping paper | C132: ='INVOICE lam CO'!D137 -> KGM | D132: ='INVOICE lam CO'!E137 -> 398 | E132: ='HỢP ĐỒNG'!F141 -> 0.8 | F132: ='HỢP ĐỒNG'!G141 -> 318.4
A133: ='HỢP ĐỒNG'!A142 -> 124 | B133: ='INVOICE lam CO'!B138 -> Paint spraying machine | C133: ='INVOICE lam CO'!D138 -> PCE | D133: ='INVOICE lam CO'!E138 -> 2 | E133: ='HỢP ĐỒNG'!F142 -> 1884.87 | F133: ='HỢP ĐỒNG'!G142 -> 3769.74
B134: TOTAL: | F134: =SUM(F10:F133) -> 193171.09
B137: - The above price is understood as the DAF Tan Thanh - Lang Son price - Incoterms 2000
B138: - Payment method: TTR or Border Trade
B139: - Currency: USD or CNY
B140: - Transportation method: Truck

Sheet INVOICE
A1: PINGXIANG GUIFENG TRADING CO.,LTD
A2: ADD: NO.6 PHASE II PAVEMENT BAIYUN FIELD TIANNAN SECONDARY PINGXIANG CITY GUANGXI CHINA
A3: HÓA ĐƠN THƯƠNG MẠI | J3: CẤM XÓA
E4: SỐ: | F4: =K4&"GF-TH/26" -> 0902 GF-TH/26 | I4: Số HĐ | J4: Số HĐ | K4: ='HỢP ĐỒNG'!$I$1 -> 0902 | L4: =K4&"GF-TH/26" -> 0902 GF-TH/26
E5: NGÀY: | F5: ='HỢP ĐỒNG'!I2+1 -> 46271 | I5: Ngày Hợp đồng | J5: Ngày Hợp đồng | K5: ='HỢP ĐỒNG'!I2 -> 46270
A6: NGƯỜI MUA: CÔNG TY TNHH THƯƠNG MẠI VÀ XUẤT NHẬP KHẨU TRƯỜNG HẢI
A7: Địa chỉ: Số 12 Đường Phụ Số 4, Khu đô thị Phú Lộc 2, Phường Kỳ Lừa, Tỉnh Lạng Sơn, Việt Nam
A8: Tài khoản ngân hàng số: 9328666888 – Ngân hàng Thương mại Cổ phần Quân đội - CN Tây Hà Nội
A10: STT | B10: Tên TA | C10: Tên hàng hóa | D10: ĐVT | E10: Số lượng | F10: Đơn giá (USD) | G10: Thành tiền (USD) | H10: HS CODE
A11: ='HỢP ĐỒNG'!A19 -> 1 | B11: ='INVOICE lam CO'!B15 -> Dusting cloth | C11: ='HỢP ĐỒNG'!C19 -> Khăn lau bụi dùng để lau xe hơi, chất liệu vải dệt kim từ sợi polyester, KT:(30*30)cm, không hiệu, NSX: Qingdao Tao Hui Industrial. Mới 100% | D11: ='HỢP ĐỒNG'!D19 -> PCE | E11: ='HỢP ĐỒNG'!E19 -> 20000 | F11: ='HỢP ĐỒNG'!F19 -> 0.094 | G11: ='HỢP ĐỒNG'!G19 -> 1880 | H11: ='HỢP ĐỒNG'!I19 -> 63071090 | I11: ='HỢP ĐỒNG'!I19 -> 63071090
A12: ='HỢP ĐỒNG'!A20 -> 2 | B12: ='INVOICE lam CO'!B16 -> Tea set | C12: ='HỢP ĐỒNG'!C20 -> Bộ ấm chén pha trà bằng gốm đất nung tráng men rạn Nhữ Diêu,gồm ấm trà dung tích 250ml,chén khải 190ml và chén uống trà 50ml, đóng hộp quà tặng, không hiệu. NSX: Shenzhen Tao Hui Industrial. Mới 100% | D12: ='HỢP ĐỒNG'!D20 -> SET | E12: ='HỢP ĐỒNG'!E20 -> 20 | F12: ='HỢP ĐỒNG'!F20 -> 5.16 | G12: ='HỢP ĐỒNG'!G20 -> 103.2 | H12: ='HỢP ĐỒNG'!I20 -> 69120000 | I12: ='HỢP ĐỒNG'!I20 -> 69120000
A13: ='HỢP ĐỒNG'!A21 -> 3 | B13: ='INVOICE lam CO'!B17 -> Tea set | C13: ='HỢP ĐỒNG'!C21 -> Bộ ấm chén pha trà du lịch bằng gốm đất nung tráng men trắng, dáng Tây Thi họa tiết Núi Non, gồm ấm trà dung tích 270ml, tống trà 150ml, chén trà 50ml,đóng hộp quà tặng, không hiệu, Mới 100% | D13: ='HỢP ĐỒNG'!D21 -> SET | E13: ='HỢP ĐỒNG'!E21 -> 20 | F13: ='HỢP ĐỒNG'!F21 -> 4.09 | G13: ='HỢP ĐỒNG'!G21 -> 81.8 | H13: ='HỢP ĐỒNG'!I21 -> 69120000 | I13: ='HỢP ĐỒNG'!I21 -> 69120000
A14: ='HỢP ĐỒNG'!A22 -> 4 | B14: ='INVOICE lam CO'!B18 -> Tea set | C14: ='HỢP ĐỒNG'!C22 -> Bộ ấm chén trà bằng gốm đất nung, kiểu dáng Nhật gồm 1 ấm 200ml và 4 chén 60ml kèm hộp quà tặng, không hiệu, NSX: Shenzhen Tao Hui Industrial Co., Ltd., Mới 100% | D14: ='HỢP ĐỒNG'!D22 -> SET | E14: ='HỢP ĐỒNG'!E22 -> 50 | F14: ='HỢP ĐỒNG'!F22 -> 5.69 | G14: ='HỢP ĐỒNG'!G22 -> 284.5 | H14: ='HỢP ĐỒNG'!I22 -> 69120000 | I14: ='HỢP ĐỒNG'!I22 -> 69120000
A15: ='HỢP ĐỒNG'!A23 -> 5 | B15: ='INVOICE lam CO'!B19 -> Teapot | C15: ='HỢP ĐỒNG'!C23 -> Ấm pha trà bằng gốm đất nung không tráng men (Tử Sa) dáng Hán Ngõa, màu xanh Lục Nê, dung tích 240ml, không dùng điện, không hiệu, NSX: Shenzhen Tao Hui Industrial Co., Ltd., Mới 100% | D15: ='HỢP ĐỒNG'!D23 -> PCE | E15: ='HỢP ĐỒNG'!E23 -> 10 | F15: ='HỢP ĐỒNG'!F23 -> 13.6 | G15: ='HỢP ĐỒNG'!G23 -> 136 | H15: ='HỢP ĐỒNG'!I23 -> 69120000 | I15: ='HỢP ĐỒNG'!I23 -> 69120000
A16: ='HỢP ĐỒNG'!A24 -> 6 | B16: ='INVOICE lam CO'!B20 -> Teapot | C16: ='HỢP ĐỒNG'!C24 -> Ấm pha trà bằng gốm đất nung không tráng men (Tử Sa) dáng Tây Thi, màu đỏ Đại Hồng Bào, dung tích 240ml, không dùng điện, không hiệu, NSX: Shenzhen Tao Hui Industrial Co., Ltd., Mới 100% | D16: ='HỢP ĐỒNG'!D24 -> PCE | E16: ='HỢP ĐỒNG'!E24 -> 15 | F16: ='HỢP ĐỒNG'!F24 -> 10.46 | G16: ='HỢP ĐỒNG'!G24 -> 156.9 | H16: ='HỢP ĐỒNG'!I24 -> 69120000 | I16: ='HỢP ĐỒNG'!I24 -> 69120000
A17: ='HỢP ĐỒNG'!A25 -> 7 | B17: ='INVOICE lam CO'!B21 -> Tea cup | C17: ='HỢP ĐỒNG'!C25 -> Cốc uống trà bằng gốm đất nung không tráng men (Tử Sa) họa tiết Thiên Hương, dung tích 180ml, không hiệu, NSX: Shenzhen Tao Hui Industrial Co., Ltd., Mới 100% | D17: ='HỢP ĐỒNG'!D25 -> PCE | E17: ='HỢP ĐỒNG'!E25 -> 20 | F17: ='HỢP ĐỒNG'!F25 -> 4.49 | G17: ='HỢP ĐỒNG'!G25 -> 89.8 | H17: ='HỢP ĐỒNG'!I25 -> 69120000 | I17: ='HỢP ĐỒNG'!I25 -> 69120000
A18: ='HỢP ĐỒNG'!A26 -> 8 | B18: ='INVOICE lam CO'!B22 -> Teapot | C18: ='HỢP ĐỒNG'!C26 -> Ấm pha trà bằng gốm đất nung không tráng men (Tử Sa) dáng Bát Phương Nung Củi, màu vàng Đoạn Nê, dung tích 270ml, không dùng điện, không hiệu, NSX: Shenzhen Tao Hui Industrial Co., Ltd., Mới 100% | D18: ='HỢP ĐỒNG'!D26 -> PCE | E18: ='HỢP ĐỒNG'!E26 -> 10 | F18: ='HỢP ĐỒNG'!F26 -> 16.74 | G18: ='HỢP ĐỒNG'!G26 -> 167.4 | H18: ='HỢP ĐỒNG'!I26 -> 69120000 | I18: ='HỢP ĐỒNG'!I26 -> 69120000
A19: ='HỢP ĐỒNG'!A27 -> 9 | B19: ='INVOICE lam CO'!B23 -> Teapot | C19: ='HỢP ĐỒNG'!C27 -> Ấm pha trà bằng gốm đất nung không tráng men (Tử Sa) dáng Thạch Biều, màu xanh Lục Nê, dung tích 260ml, không dùng điện, không hiệu, NSX: Shenzhen Tao Hui Industrial Co., Ltd., Mới 100% | D19: ='HỢP ĐỒNG'!D27 -> PCE | E19: ='HỢP ĐỒNG'!E27 -> 5 | F19: ='HỢP ĐỒNG'!F27 -> 15.69 | G19: ='HỢP ĐỒNG'!G27 -> 78.45 | H19: ='HỢP ĐỒNG'!I27 -> 69120000 | I19: ='HỢP ĐỒNG'!I27 -> 69120000
A20: ='HỢP ĐỒNG'!A28 -> 10 | B20: ='INVOICE lam CO'!B24 -> Teapot | C20: ='HỢP ĐỒNG'!C28 -> Ấm pha trà bằng gốm đất nung không tráng men (Tử Sa) dáng Vân Lư, màu nâu Thiết Huyết Hồng Sa, dung tích 260ml, không dùng điện, không hiệu, NSX: Shenzhen Tao Hui Industrial Co., Ltd., Mới 100% | D20: ='HỢP ĐỒNG'!D28 -> PCE | E20: ='HỢP ĐỒNG'!E28 -> 10 | F20: ='HỢP ĐỒNG'!F28 -> 17.09 | G20: ='HỢP ĐỒNG'!G28 -> 170.9 | H20: ='HỢP ĐỒNG'!I28 -> 69120000 | I20: ='HỢP ĐỒNG'!I28 -> 69120000
A21: ='HỢP ĐỒNG'!A29 -> 11 | B21: ='INVOICE lam CO'!B25 -> Teapot | C21: ='HỢP ĐỒNG'!C29 -> Ấm pha trà bằng gốm đất nung không tráng men (Tử Sa) dáng Tứ Phương Liên Hoa dung tích 230ml, không dùng điện, không hiệu, NSX: Shenzhen Tao Hui Industrial Co., Ltd., Mới 100% | D21: ='HỢP ĐỒNG'!D29 -> PCE | E21: ='HỢP ĐỒNG'!E29 -> 10 | F21: ='HỢP ĐỒNG'!F29 -> 14.47 | G21: ='HỢP ĐỒNG'!G29 -> 144.7 | H21: ='HỢP ĐỒNG'!I29 -> 69120000 | I21: ='HỢP ĐỒNG'!I29 -> 69120000
A22: ='HỢP ĐỒNG'!A30 -> 12 | B22: ='INVOICE lam CO'!B26 -> Teapot | C22: ='HỢP ĐỒNG'!C30 -> Ấm pha trà bằng gốm đất nung không tráng men (Tử Sa) dáng Long Đán, màu nâu Tử Nê, dung tích 220ml, không dùng điện, không hiệu, NSX: Shenzhen Tao Hui Industrial Co., Ltd., Mới 100% | D22: ='HỢP ĐỒNG'!D30 -> PCE | E22: ='HỢP ĐỒNG'!E30 -> 3 | F22: ='HỢP ĐỒNG'!F30 -> 20.46 | G22: ='HỢP ĐỒNG'!G30 -> 61.38 | H22: ='HỢP ĐỒNG'!I30 -> 69120000 | I22: ='HỢP ĐỒNG'!I30 -> 69120000
... A132: ='HỢP ĐỒNG'!A140 -> 122 | B132: ='INVOICE lam CO'!B136 -> Artificial tulip | C132: ='HỢP ĐỒNG'!C140 -> Bông hoa tuylip nhân tạo, chất liệu nhựa PVC, lõi bằng thép, đã định hình hoàn chỉnh, dùng để trang trí. KT: (35*4)cm+/-10%, không hiệu. NSX: Yuchen Artificial Flower Strength Supplier, mới 100% | D132: ='HỢP ĐỒNG'!D140 -> PCE | E132: ='HỢP ĐỒNG'!E140 -> 10000 | F132: ='HỢP ĐỒNG'!F140 -> 0.075 | G132: ='HỢP ĐỒNG'!G140 -> 750 | H132: ='HỢP ĐỒNG'!I140 -> 67029090 | I132: ='HỢP ĐỒNG'!I140 -> 67029090
B133: ='INVOICE lam CO'!B137 -> Flower wrapping paper | C133: ='HỢP ĐỒNG'!C141 -> Giấy gói hoa dạng giấy nhún, được làm từ bột gỗ xenlulo, đã nhuộm màu bề mặt, dạng tấm, KT: (50*230)cm+/-10%, không hiệu. Nsx: Jiangxi Yuanna Packaging Material Co., Ltd. Mới 100% | D133: ='HỢP ĐỒNG'!D141 -> KGM | E133: ='HỢP ĐỒNG'!E141 -> 398 | F133: ='HỢP ĐỒNG'!F141 -> 0.8 | G133: ='HỢP ĐỒNG'!G141 -> 318.4 | I133: ='HỢP ĐỒNG'!I141 -> 48119093
B134: ='INVOICE lam CO'!B138 -> Paint spraying machine | C134: ='HỢP ĐỒNG'!C142 -> Máy phun sơn tĩnh điện dùng để phun sơn hoàn thiện bề mặt các sản phẩm bằng kim loại,kèm khung đỡ có bánh xe.Model:FlexiSpray F1,điện áp:AC100-240,CS: 50W. NSX: Foshan Debelle Technology,mới 100% | D134: ='HỢP ĐỒNG'!D142 -> PCE | E134: ='HỢP ĐỒNG'!E142 -> 2 | F134: ='HỢP ĐỒNG'!F142 -> 1884.87 | G134: ='HỢP ĐỒNG'!G142 -> 3769.74 | I134: ='HỢP ĐỒNG'!I142 -> 84242029
C135: Tổng cộng: | G135: =SUM(G11:G134) -> 193171.09
C138: - Giá trên được hiểu là giá DAF Tân Thanh - Lạng Sơn - Incoterms 2000
C139: - Phương thức thanh toán: TTR hoặc Biên mậu
C140: - Đồng tiền thanh toán: USD hoặc CNY
C141: - Phương thức vận chuyển: Ô tô tải

Sheet PACKINGLIST
A1: =INVOICE!A1 -> PINGXIANG GUIFENG TRADING CO.,LTD
A2: =INVOICE!A2 -> ADD: NO.6 PHASE II PAVEMENT BAIYUN FIELD TIANNAN SECONDARY PINGXIANG CITY GUANGXI CHINA
A4: PHIẾU ĐÓNG GÓI
B5: Hóa đơn số: | C5: =INVOICE!F4 -> 0902 GF-TH/26 | F5: ="Ngày "&DAY(INVOICE!F5)&"/"&MONTH(INVOICE!F5)&"/"&YEAR(INVOICE!F5) -> Ngày 6/9/2026
B6: Hợp đồng số: | C6: =C5 -> 0902 GF-TH/26 | F6: ="Ngày "&DAY('HỢP ĐỒNG'!I2)&"/"&MONTH('HỢP ĐỒNG'!I2)&"/"&YEAR('HỢP ĐỒNG'!I2) -> Ngày 5/9/2026
A8: =INVOICE!A6 -> NGƯỜI MUA: CÔNG TY TNHH THƯƠNG MẠI VÀ XUẤT NHẬP KHẨU TRƯỜNG HẢI
A9: =INVOICE!A7 -> Địa chỉ: Số 12 Đường Phụ Số 4, Khu đô thị Phú Lộc 2, Phường Kỳ Lừa, Tỉnh Lạng Sơn, Việt Nam
A10: =INVOICE!A8 -> Tài khoản ngân hàng số: 9328666888 – Ngân hàng Thương mại Cổ phần Quân đội - CN Tây Hà Nội
A12: STT | B12: Chi tiết tên hàng | C12: Đvt | D12: Số lượng | E12: Quy cách đóng gói | F12: Số kiện | G12: Trọng lượng hàng | H12: Trọng lượng cả bì
A13: ='HỢP ĐỒNG'!A19 -> 1 | B13: ='HỢP ĐỒNG'!C19 -> Khăn lau bụi dùng để lau xe hơi, chất liệu vải dệt kim từ sợi polyester, KT:(30*30)cm, không hiệu, NSX: Qingdao Tao Hui Industrial. Mới 100% | C13: ='HỢP ĐỒNG'!D19 -> PCE | D13: ='HỢP ĐỒNG'!E19 -> 20000 | E13: =IF(C13="Kg",IF(I13<D13,I13&" "&C13&" "&"/ Kiện",I13&" "&C13&" "&"/ "&F13&" Kiện"),IF(AND(D13=I13),I13&" "&C13&" "&"/ "&F13&" Kiện",I13&" "&C13&" "&"/ Kiện")) -> PCE / Kiện | F13: 10 | G13: 280 | H13: 300
A14: ='HỢP ĐỒNG'!A20 -> 2 | B14: ='HỢP ĐỒNG'!C20 -> Bộ ấm chén pha trà bằng gốm đất nung tráng men rạn Nhữ Diêu,gồm ấm trà dung tích 250ml,chén khải 190ml và chén uống trà 50ml, đóng hộp quà tặng, không hiệu. NSX: Shenzhen Tao Hui Industrial. Mới 100% | C14: ='HỢP ĐỒNG'!D20 -> SET | D14: ='HỢP ĐỒNG'!E20 -> 20 | F14: 1 | G14: 54 | H14: 56
A15: ='HỢP ĐỒNG'!A21 -> 3 | B15: ='HỢP ĐỒNG'!C21 -> Bộ ấm chén pha trà du lịch bằng gốm đất nung tráng men trắng, dáng Tây Thi họa tiết Núi Non, gồm ấm trà dung tích 270ml, tống trà 150ml, chén trà 50ml,đóng hộp quà tặng, không hiệu, Mới 100% | C15: ='HỢP ĐỒNG'!D21 -> SET | D15: ='HỢP ĐỒNG'!E21 -> 20
A16: ='HỢP ĐỒNG'!A22 -> 4 | B16: ='HỢP ĐỒNG'!C22 -> Bộ ấm chén trà bằng gốm đất nung, kiểu dáng Nhật gồm 1 ấm 200ml và 4 chén 60ml kèm hộp quà tặng, không hiệu, NSX: Shenzhen Tao Hui Industrial Co., Ltd., Mới 100% | C16: ='HỢP ĐỒNG'!D22 -> SET | D16: ='HỢP ĐỒNG'!E22 -> 50
A17: ='HỢP ĐỒNG'!A23 -> 5 | B17: ='HỢP ĐỒNG'!C23 -> Ấm pha trà bằng gốm đất nung không tráng men (Tử Sa) dáng Hán Ngõa, màu xanh Lục Nê, dung tích 240ml, không dùng điện, không hiệu, NSX: Shenzhen Tao Hui Industrial Co., Ltd., Mới 100% | C17: ='HỢP ĐỒNG'!D23 -> PCE | D17: ='HỢP ĐỒNG'!E23 -> 10 | F17: 1 | G17: 47 | H17: 49
A18: ='HỢP ĐỒNG'!A24 -> 6 | B18: ='HỢP ĐỒNG'!C24 -> Ấm pha trà bằng gốm đất nung không tráng men (Tử Sa) dáng Tây Thi, màu đỏ Đại Hồng Bào, dung tích 240ml, không dùng điện, không hiệu, NSX: Shenzhen Tao Hui Industrial Co., Ltd., Mới 100% | C18: ='HỢP ĐỒNG'!D24 -> PCE | D18: ='HỢP ĐỒNG'!E24 -> 15
A19: ='HỢP ĐỒNG'!A25 -> 7 | B19: ='HỢP ĐỒNG'!C25 -> Cốc uống trà bằng gốm đất nung không tráng men (Tử Sa) họa tiết Thiên Hương, dung tích 180ml, không hiệu, NSX: Shenzhen Tao Hui Industrial Co., Ltd., Mới 100% | C19: ='HỢP ĐỒNG'!D25 -> PCE | D19: ='HỢP ĐỒNG'!E25 -> 20
A20: ='HỢP ĐỒNG'!A26 -> 8 | B20: ='HỢP ĐỒNG'!C26 -> Ấm pha trà bằng gốm đất nung không tráng men (Tử Sa) dáng Bát Phương Nung Củi, màu vàng Đoạn Nê, dung tích 270ml, không dùng điện, không hiệu, NSX: Shenzhen Tao Hui Industrial Co., Ltd., Mới 100% | C20: ='HỢP ĐỒNG'!D26 -> PCE | D20: ='HỢP ĐỒNG'!E26 -> 10
A21: ='HỢP ĐỒNG'!A27 -> 9 | B21: ='HỢP ĐỒNG'!C27 -> Ấm pha trà bằng gốm đất nung không tráng men (Tử Sa) dáng Thạch Biều, màu xanh Lục Nê, dung tích 260ml, không dùng điện, không hiệu, NSX: Shenzhen Tao Hui Industrial Co., Ltd., Mới 100% | C21: ='HỢP ĐỒNG'!D27 -> PCE | D21: ='HỢP ĐỒNG'!E27 -> 5
A22: ='HỢP ĐỒNG'!A28 -> 10 | B22: ='HỢP ĐỒNG'!C28 -> Ấm pha trà bằng gốm đất nung không tráng men (Tử Sa) dáng Vân Lư, màu nâu Thiết Huyết Hồng Sa, dung tích 260ml, không dùng điện, không hiệu, NSX: Shenzhen Tao Hui Industrial Co., Ltd., Mới 100% | C22: ='HỢP ĐỒNG'!D28 -> PCE | D22: ='HỢP ĐỒNG'!E28 -> 10
A23: ='HỢP ĐỒNG'!A29 -> 11 | B23: ='HỢP ĐỒNG'!C29 -> Ấm pha trà bằng gốm đất nung không tráng men (Tử Sa) dáng Tứ Phương Liên Hoa dung tích 230ml, không dùng điện, không hiệu, NSX: Shenzhen Tao Hui Industrial Co., Ltd., Mới 100% | C23: ='HỢP ĐỒNG'!D29 -> PCE | D23: ='HỢP ĐỒNG'!E29 -> 10
A24: ='HỢP ĐỒNG'!A30 -> 12 | B24: ='HỢP ĐỒNG'!C30 -> Ấm pha trà bằng gốm đất nung không tráng men (Tử Sa) dáng Long Đán, màu nâu Tử Nê, dung tích 220ml, không dùng điện, không hiệu, NSX: Shenzhen Tao Hui Industrial Co., Ltd., Mới 100% | C24: ='HỢP ĐỒNG'!D30 -> PCE | D24: ='HỢP ĐỒNG'!E30 -> 3 | F24: 1 | G24: 45 | H24: 47
A25: ='HỢP ĐỒNG'!A31 -> 13 | B25: ='HỢP ĐỒNG'!C31 -> Ấm pha trà bằng gốm đất nung không tráng men (Tử Sa) dáng Phan Hồ, màu đỏ Đại Hồng Bào, dung tích 250ml, không dùng điện, không hiệu, NSX: Shenzhen Tao Hui Industrial Co., Ltd., Mới 100% | C25: ='HỢP ĐỒNG'!D31 -> PCE | D25: ='HỢP ĐỒNG'!E31 -> 3
A26: ='HỢP ĐỒNG'!A32 -> 14 | B26: ='HỢP ĐỒNG'!C32 -> Ấm pha trà bằng gốm đất nung không tráng men (Tử Sa) dáng Tây Thi, dung tích 420ml, không dùng điện, không hiệu, NSX: Shenzhen Tao Hui Industrial Co., Ltd., Mới 100% | C26: ='HỢP ĐỒNG'!D32 -> PCE | D26: ='HỢP ĐỒNG'!E32 -> 5
A27: ='HỢP ĐỒNG'!A33 -> 15 | B27: ='HỢP ĐỒNG'!C33 -> Khay để ấm trà (Thuyền Trà) bằng gốm đất nung không tráng men (Tử Sa) đường kính 19.5cm, họa tiết Sơn Cảnh, đóng hộp quà tặng, không hiệu, NSX: Shenzhen Tao Hui Industrial Co., Ltd., Mới 100% | C27: ='HỢP ĐỒNG'!D33 -> PCE | D27: ='HỢP ĐỒNG'!E33 -> 5
A28: ='HỢP ĐỒNG'!A34 -> 16 | B28: ='HỢP ĐỒNG'!C34 -> Ang trà ( bát tráng trà) bằng gốm đất nung không tráng men (Tử Sa), màu cam Chu Nê, họa tiết Tâm Kinh đường kính 27.8cm, không hiệu, NSX: Shenzhen Tao Hui Industrial Co., Ltd., Mới 100% | C28: ='HỢP ĐỒNG'!D34 -> PCE | D28: ='HỢP ĐỒNG'!E34 -> 5
A29: ='HỢP ĐỒNG'!A35 -> 17 | B29: ='HỢP ĐỒNG'!C35 -> Ấm pha trà bằng gốm đất nung không tráng men (Tử Sa) dáng Thạch Biều Cảnh Chu, màu nâu Tử Nê, dung tích 230ml, không dùng điện, không hiệu, NSX: Shenzhen Tao Hui Industrial Co., Ltd., Mới 100% | C29: ='HỢP ĐỒNG'!D35 -> PCE | D29: ='HỢP ĐỒNG'!E35 -> 5
A30: ='HỢP ĐỒNG'!A36 -> 18 | B30: ='HỢP ĐỒNG'!C36 -> Ấm pha trà bằng gốm đất nung không tráng men (Tử Sa) dáng Mỹ Nhân Kiên, màu đỏ Đại Hồng Bào, dung tích 190ml, không dùng điện, không hiệu, NSX: Shenzhen Tao Hui Industrial Co., Ltd., Mới 100% | C30: ='HỢP ĐỒNG'!D36 -> PCE | D30: ='HỢP ĐỒNG'!E36 -> 5
A31: ='HỢP ĐỒNG'!A37 -> 19 | B31: ='HỢP ĐỒNG'!C37 -> Ấm pha trà bằng gốm đất nung không tráng men (Tử Sa) dáng Tây Thi Song Sắc, dung tích 200ml, không dùng điện, không hiệu, NSX: Shenzhen Tao Hui Industrial Co., Ltd., Mới 100% | C31: ='HỢP ĐỒNG'!D37 -> PCE | D31: ='HỢP ĐỒNG'!E37 -> 3
A32: ='HỢP ĐỒNG'!A38 -> 20 | B32: ='HỢP ĐỒNG'!C38 -> Công tắc điều khiển dòng chảy, model: HFS-25, dùng cho công nghiệp đóng ngắt dòng điện 5A. KT: (10*7*5)cm+/-10%, đk: ren 1-3/4inch, đ/áp: 220V, hiệu: SUNSES, mới 100% | C32: ='HỢP ĐỒNG'!D38 -> PCE | D32: ='HỢP ĐỒNG'!E38 -> 500 | F32: 12 | G32: 222 | H32: 246
A33: ='HỢP ĐỒNG'!A39 -> 21 | B33: ='HỢP ĐỒNG'!C39 -> Công tắc áp suất khí nén KP, bằng nhựa kết hợp đồng, để điều chỉnh áp suất trong hệ thống khí nén, đ/áp: 220V/5A, không hiệu. NSX: Zhejiang Machinery Technology Co., LTD, mới 100% | C33: ='HỢP ĐỒNG'!D39 -> PCE | D33: ='HỢP ĐỒNG'!E39 -> 300
A34: ='HỢP ĐỒNG'!A40 -> 22 | B34: ='HỢP ĐỒNG'!C40 -> Đế chia khí dùng cho đường ống khí nén, bằng hợp kim nhôm, loại 3-5 cổng, ren 13mm, áp suất làm việc 1 MPa. KT: (15*5*2)cm+/-10%, không hiệu, nsx: NSX Aikes Pneumatic Components Co., Ltd, mới 100% | C34: ='HỢP ĐỒNG'!D40 -> PCE | D34: ='HỢP ĐỒNG'!E40 -> 300
A35: ='HỢP ĐỒNG'!A41 -> 23 | B35: ='HỢP ĐỒNG'!C41 -> Vợt pickleball, model: Bomba X, sử dụng công nghệ ép nóng, lõi eva foam, bề mặt bằng sợi carbon. KT: (40*20*3)cm+/-10%, hiệu: Do-An, mới 100% | C35: ='HỢP ĐỒNG'!D41 -> PCE | D35: ='HỢP ĐỒNG'!E41 -> 400 | F35: 4 | G35: 50 | H35: 58
A36: ='HỢP ĐỒNG'!A42 -> 24 | B36: ='HỢP ĐỒNG'!C42 -> Yếm cho thú cưng, chất liệu vải dệt từ sợi tổng hợp. KT: (25*20*2)cm+/-10%, không hiệu. NSX: Ningbo Jia Chong International Trade Co., Ltd.., mới 100% | C36: ='HỢP ĐỒNG'!D42 -> PCE | D36: ='HỢP ĐỒNG'!E42 -> 270 | F36: 5 | G36: 112 | H36: 122
A37: ='HỢP ĐỒNG'!A43 -> 25 | B37: ='HỢP ĐỒNG'!C43 -> Dây dắt thú cưng, chất liệu vải dù. KT: 1.2cm*1.5m+/-10%, không hiệu. NSX: Ningbo Jia Chong International Trade Co., Ltd.., mới 100% | C37: ='HỢP ĐỒNG'!D43 -> PCE | D37: ='HỢP ĐỒNG'!E43 -> 400
A38: ='HỢP ĐỒNG'!A44 -> 26 | B38: ='HỢP ĐỒNG'!C44 -> Thanh giá treo của vòi hoa sen cây (gồm 2 thanh), chất liệu thép không gỉ, chống bám bẩn. KT: (1280*370)mm+/-10%, không hiệu,nsx: Jiangyin Yonghao Machinery Co., Ltd. Mới 100% | C38: ='HỢP ĐỒNG'!D44 -> SET | D38: ='HỢP ĐỒNG'!E44 -> 1200 | F38: 50 | G38: 960 | H38: 1061
A39: ='HỢP ĐỒNG'!A45 -> 27 | B39: ='HỢP ĐỒNG'!C45 -> Khay chữ nhật, kí hiệu: SL-170, dùng để trang trí, trưng bày trong khách sạn, chất liệu nhựa giả gỗ. KT: (29.7*21.5*6)cm+/-10%, không hiệu. Nsx: Shandong Machinery Co., Ltd. Mới 100% | C39: ='HỢP ĐỒNG'!D45 -> PCE | D39: ='HỢP ĐỒNG'!E45 -> 48 | F39: 12 | G39: 178 | H39: 202
A40: ='HỢP ĐỒNG'!A46 -> 28 | B40: ='HỢP ĐỒNG'!C46 -> Khay đựng đũa đặt trên bàn ăn dùng trong nhà bếp, không dùng đựng thực phẩm,chất liệu bằng nhựa ABS, kí hiệu: C-1222. KT: (27.3*10.5*6.5)cm+-10%, không hiệu. Nsx: Shandong Machinery Co., Ltd. Mới 100% | C40: ='HỢP ĐỒNG'!D46 -> PCE | D40: ='HỢP ĐỒNG'!E46 -> 150
A41: ='HỢP ĐỒNG'!A47 -> 29 | B41: ='HỢP ĐỒNG'!C47 -> Khay đựng đũa đặt trên bàn ăn dùng trong nhà bếp, không dùng đựng thực phẩm, chất liệu bằng nhựa ABS, kí hiệu: C-1223. KT: (26.5*8.7*5)cm+-10%, không hiệu. Nsx: Shandong Machinery Co., Ltd. Mới 100% | C41: ='HỢP ĐỒNG'!D47 -> PCE | D41: ='HỢP ĐỒNG'!E47 -> 150
A42: ='HỢP ĐỒNG'!A48 -> 30 | B42: ='HỢP ĐỒNG'!C48 -> Nồi lẩu sần 2 ngăn NLS2N32B, dùng trong nhà bếp, không dùng điện, chất liệu inox. ĐK: 32cm+/-10%, không hiệu, nsx: Jiangmen Jida Stainless Steel Products Co., Ltd.. Mới 100% | C42: ='HỢP ĐỒNG'!D48 -> PCE | D42: ='HỢP ĐỒNG'!E48 -> 200 | F42: 14 | G42: 297 | H42: 325
A43: ='HỢP ĐỒNG'!A49 -> 31 | B43: ='HỢP ĐỒNG'!C49 -> Nồi lẩu inox NLS30B, dùng trong nhà bếp, không dùng điện. ĐK: 28cm+/-10%, không hiệu, nsx: Jiangmen Jida Stainless Steel Products Co., Ltd.. Mới 100% | C43: ='HỢP ĐỒNG'!D49 -> PCE | D43: ='HỢP ĐỒNG'!E49 -> 26
A44: ='HỢP ĐỒNG'!A50 -> 32 | B44: ='HỢP ĐỒNG'!C50 -> Khay chữ nhật có đế, dùng trang trí trưng bày trong khách sạn, không đựng thực phẩm, KH: 990808, CL nhựa ABS.KT: (20.4*15*5.8)cm+/-10%, không hiệu.NSX: Jiangmen Jida Stainless Steel Products. Mới 100% | C44: ='HỢP ĐỒNG'!D50 -> PCE | D44: ='HỢP ĐỒNG'!E50 -> 120 | F44: 2 | G44: 41 | H44: 45
A45: ='HỢP ĐỒNG'!A51 -> 33 | B45: ='HỢP ĐỒNG'!C51 -> Miếng dán kính cường lực BAIKO GLASS dùng cho điện thoại,loại an toàn 2 lớp (kính dán an toàn nhiều lớp),CL sợi thủy tinh, có lớp bảo vệ bằng nhựa. KT: (185*75*25)mm +/-10%, nhãn hiệu: BAIKO. Mới 100% | C45: ='HỢP ĐỒNG'!D51 -> PCE | D45: ='HỢP ĐỒNG'!E51 -> 6500 | F45: 18 | G45: 558 | H45: 594
A46: ='HỢP ĐỒNG'!A52 -> 34 | B46: ='HỢP ĐỒNG'!C52 -> Miếng dán kính cường lựcBAIKO GLASS trong suốt ko viền đen dùng cho điện thoại,loại an toàn 2lớp(kính dán an toàn nhiều lớp),CLsợi thủy tinh,có lớp bảo vệ bằng nhựa.KT:(185*75*25)mm,hiệu:BAIKO.Mới100% | C46: ='HỢP ĐỒNG'!D52 -> PCE | D46: ='HỢP ĐỒNG'!E52 -> 13000
A47: ='HỢP ĐỒNG'!A53 -> 35 | B47: ='HỢP ĐỒNG'!C53 -> Miếng dán kính cường lực BAIKO ULTRA THIN PRIVACY dùng cho điện thoại,loại kính dán nhiều lớp,CL sợi thủy tinh, lớp bảo vệ bằng nhựa. KT (185*75*25)mm +/-10%,nhãn hiệu: BAIKO. Mới 100% | C47: ='HỢP ĐỒNG'!D53 -> PCE | D47: ='HỢP ĐỒNG'!E53 -> 1620
A48: ='HỢP ĐỒNG'!A54 -> 36 | B48: ='HỢP ĐỒNG'!C54 -> Miếng dán kính cường lực BAIKO GLASS PRIVACY cho điện thoại,loại an toàn 2 lớp (kính dán an toàn nhiều lớp),CL sợi thủy tinh, có lớp bảo vệ bằng nhựa. KT: (185*75*25)mm, nhãn hiệu: BAIKO. Mới 100% | C48: ='HỢP ĐỒNG'!D54 -> PCE | D48: ='HỢP ĐỒNG'!E54 -> 5000
A49: ='HỢP ĐỒNG'!A55 -> 37 | B49: ='HỢP ĐỒNG'!C55 -> Tấm kính cường lực loại an toàn nhiều lớp, dùng để bảo vệ màn hình điện thoại di dộng, ESD GLASS màu tím, chất liệu sợi thuỷ tinh, lớp bảo vệ bằng nhựa. KT: (185*75*25)mm, nhãn hiệu: BAIKO.Mới 100% | C49: ='HỢP ĐỒNG'!D55 -> PCE | D49: ='HỢP ĐỒNG'!E55 -> 3000
A50: ='HỢP ĐỒNG'!A56 -> 38 | B50: ='HỢP ĐỒNG'!C56 -> Dây kẽm nhung (lõi kẽm bọc vải nhung) dùng để làm hoa giả, 100 sợi/bó. 1 bó=1 set. KT: đường kính 0.8cm, dài 30cm+/-10%, không hiệu. NSX: Yiwu Tianhong Crafts Co., Ltd, mới 100% | C50: ='HỢP ĐỒNG'!D56 -> SET | D50: ='HỢP ĐỒNG'!E56 -> 6000 | F50: 30 | G50: 705 | H50: 773
A51: ='HỢP ĐỒNG'!A57 -> 39 | B51: ='HỢP ĐỒNG'!C57 -> Miếng nhám cọ rửa bát đĩa, chất liệu lớp mút xốp bằng nhựa, dạng mút xốp kết hợp lớp nhám. KT: (10*6*2)cm+/-10%, không hiệu, nsx: Fengrun Commodity Co., Ltd. Mới 100% | C51: ='HỢP ĐỒNG'!D57 -> PCE | D51: ='HỢP ĐỒNG'!E57 -> 30000 | F51: 120 | G51: 300 | H51: 480
A52: ='HỢP ĐỒNG'!A58 -> 40 | B52: ='HỢP ĐỒNG'!C58 -> Hộp 4 bút bi mực gel, thân vỏ bút bằng nhựa tổng hợp có in họa tiết. KT: (dài 18*0.8cm)+-10%, không hiệu. Nsx Baiqi Hourglass Pens Co.Ltd, mới 100% | C52: ='HỢP ĐỒNG'!D58 -> UNK | D52: ='HỢP ĐỒNG'!E58 -> 2500 | F52: 36 | G52: 673 | H52: 745
A53: ='HỢP ĐỒNG'!A59 -> 41 | B53: ='HỢP ĐỒNG'!C59 -> Túi đựng dụng cụ học tập 1 ngăn in họa tiết basic loại đựng trong túi, cặp chất liệu và mặt ngoài bằng vải dệt. KT: (20*8*6)cm+/-10%, không hiệu. NSX: Shanghai Stationery Inc. Mới 100% | C53: ='HỢP ĐỒNG'!D59 -> PCE | D53: ='HỢP ĐỒNG'!E59 -> 14500
A54: ='HỢP ĐỒNG'!A60 -> 42 | B54: ='HỢP ĐỒNG'!C60 -> Túi đựng dụng cụ học tập 2 ngăn loại đựng trong túi, cặp chất liệu và mặt ngoài bằng vải dệt không thấm nước. KT: (20*10*6)cm+/-10%, không hiệu. NSX:Yiwu Jiayi Daily Necessities Factory,mới 100% | C54: ='HỢP ĐỒNG'!D60 -> PCE | D54: ='HỢP ĐỒNG'!E60 -> 1000
A55: ='HỢP ĐỒNG'!A61 -> 43 | B55: ='HỢP ĐỒNG'!C61 -> Máy làm đá viên, model: FPS-1500P. KT máy: (1225*970*1920)mm, kt thùng chứa đá: (1330*720*930)mm+/-10%, đ/áp: 220V/50Hz, CS: 682kg/24h. Nhãn hiệu: ASIMA, mới 100% | C55: ='HỢP ĐỒNG'!D61 -> PCE | D55: ='HỢP ĐỒNG'!E61 -> 3 | F55: 6 | G55: 811 | H55: 823
A56: ='HỢP ĐỒNG'!A62 -> 44 | B56: ='HỢP ĐỒNG'!C62 -> Máy massage đầu gối 5 chế độ hoạt động, dùng để massage thư giãn, giảm mỏi cơ vùng đầu gối. Công suất: 3.7V/10W, dung lượng pin 2000 mAh. Model: DG11.Hiệu: DELAX, mới 100% | C56: ='HỢP ĐỒNG'!D62 -> PCE | D56: ='HỢP ĐỒNG'!E62 -> 400 | F56: 34 | G56: 238 | H56: 306
A57: ='HỢP ĐỒNG'!A63 -> 45 | B57: ='HỢP ĐỒNG'!C63 -> Chậu rửa bát bằng inox 201, chống ngưng tụ nước, 1 hộc dùng trong nhà bếp. KT: (450*400*215)mm+/-10%, kí hiệu: 4540-D(201)2.7mm, không hiệu. NSX: Foshan Jinyunke Kitchen & Bath Co., Ltd., mới 100% | C57: ='HỢP ĐỒNG'!D63 -> PCE | D57: ='HỢP ĐỒNG'!E63 -> 400 | F57: 79 | G57: 7029 | H57: 7187.4
A58: ='HỢP ĐỒNG'!A64 -> 46 | B58: ='HỢP ĐỒNG'!C64 -> Chậu rửa bát bằng inox 201, chống ngưng tụ nước, 1 hộc dùng trong nhà bếp. KT: (500*400*215)mm+/-10%, kí hiệu: 5040-D(201)2.7mm, không hiệu. NSX: Foshan Jinyunke Kitchen & Bath Co., Ltd., mới 100% | C58: ='HỢP ĐỒNG'!D64 -> PCE | D58: ='HỢP ĐỒNG'!E64 -> 200
A59: ='HỢP ĐỒNG'!A65 -> 47 | B59: ='HỢP ĐỒNG'!C65 -> Chậu rửa bát bằng inox 201, chống ngưng tụ nước, 1 hộc dùng trong nhà bếp. KT: (600*450*215)mm+/-10%, kí hiệu: 6045-D(201)2.7mm, không hiệu. NSX: Foshan Jinyunke Kitchen & Bath Co., Ltd., mới 100% | C59: ='HỢP ĐỒNG'!D65 -> PCE | D59: ='HỢP ĐỒNG'!E65 -> 400
A60: ='HỢP ĐỒNG'!A66 -> 48 | B60: ='HỢP ĐỒNG'!C66 -> Chậu rửa bát bằng inox 201, chống ngưng tụ nước, 1 hộc dùng trong nhà bếp. KT: (600*450*215)mm+/-10%, kí hiệu: 6045-AE(201)2.7mm, không hiệu. NSX: Foshan Jinyunke Kitchen & Bath Co., Ltd., mới 100% | C60: ='HỢP ĐỒNG'!D66 -> PCE | D60: ='HỢP ĐỒNG'!E66 -> 200
A61: ='HỢP ĐỒNG'!A67 -> 49 | B61: ='HỢP ĐỒNG'!C67 -> Chậu rửa bát bằng inox 304, chống ngưng tụ nước, 1 hộc dùng trong nhà bếp, KT: (750*460*215)mm+/-10%, kí hiệu: 7546-B(304)5.0mm, không hiệu. NSX: Foshan Jinyunke Kitchen & Bath Co., Ltd., mới 100% | C61: ='HỢP ĐỒNG'!D67 -> PCE | D61: ='HỢP ĐỒNG'!E67 -> 60
A62: ='HỢP ĐỒNG'!A68 -> 50 | B62: ='HỢP ĐỒNG'!C68 -> Chậu rửa bát bằng inox 201, chống ngưng tụ nước, 1 hộc dùng trong nhà bếp, KT: (780*460*215)mm+/-10%, kí hiệu: 7846-A(201)2.7mm, không hiệu. NSX: Foshan Jinyunke Kitchen & Bath Co., Ltd., mới 100% | C62: ='HỢP ĐỒNG'!D68 -> PCE | D62: ='HỢP ĐỒNG'!E68 -> 100
A63: ='HỢP ĐỒNG'!A69 -> 51 | B63: ='HỢP ĐỒNG'!C69 -> Chậu rửa bát bằng inox 201, chống ngưng tụ nước, 2 hộc dùng trong nhà bếp, KT: (780*460*215)mm+/-10%, kí hiệu: 7846-AE(201)2.7mm, không hiệu. NSX: Foshan Jinyunke Kitchen & Bath Co., Ltd., mới 100% | C63: ='HỢP ĐỒNG'!D69 -> PCE | D63: ='HỢP ĐỒNG'!E69 -> 100
A64: ='HỢP ĐỒNG'!A70 -> 52 | B64: ='HỢP ĐỒNG'!C70 -> Điều khiển cửa cuốn từ xa, loại điều khiển bằng sóng hồng ngoại, vỏ bằng nhựa tổng hợp, không chứa dữ liệu, mật mã dân sự, sử dụng pin 23A/12V, không hiệu. Nsx: Zhejiang Zhiyuan Factory. Mới 100% | C64: ='HỢP ĐỒNG'!D70 -> PCE | D64: ='HỢP ĐỒNG'!E70 -> 5000 | F64: 6 | G64: 122 | H64: 134
A65: ='HỢP ĐỒNG'!A71 -> 53 | B65: ='HỢP ĐỒNG'!C71 -> Bộ điều khiển cửa cuốn gồm 1 hộp tín hiệu trung tâm và 2 tay khiển, loại điều khiển bằng sóng hồng ngoại, vỏ bằng nhựa tổng hợp, không chứa dữ liệu, mật mã dân sự,dùng pin 23A/12V, không hiệu.Mới 100% | C65: ='HỢP ĐỒNG'!D71 -> SET | D65: ='HỢP ĐỒNG'!E71 -> 200 | F65: 1 | G65: 399 | H65: 401
A66: ='HỢP ĐỒNG'!A72 -> 54 | B66: ='HỢP ĐỒNG'!C72 -> Bộ điều khiển cửa cuốn gồm 1 hộp tín hiệu trung tâm và 2 tay khiển nắp trượt, loại điều khiển bằng sóng hồng ngoại, vỏ bằng nhựa tổng hợp, không chứa dữ liệu, mmds,dùng pin 23A/12V,không hiệu.Mới 100% | C66: ='HỢP ĐỒNG'!D72 -> SET | D66: ='HỢP ĐỒNG'!E72 -> 500
A67: ='HỢP ĐỒNG'!A73 -> 55 | B67: ='HỢP ĐỒNG'!C73 -> Công tắc hành trình dùng cho cửa cuốn để xác định điểm dừng khi đóng/mở cửa, đ/a: 250V, dòng điện 5A, đ/a:250V, KH: ME-9101 không hiệu, Nsx: Zhejiang Zhiyuan Factory, mới 100% | C67: ='HỢP ĐỒNG'!D73 -> PCE | D67: ='HỢP ĐỒNG'!E73 -> 1000 | F67: 25 | G67: 450 | H67: 500
A68: ='HỢP ĐỒNG'!A74 -> 56 | B68: ='HỢP ĐỒNG'!C74 -> Công tắc hành trình dùng cho cửa cuốn để xác định điểm dừng khi đóng/mở cửa, đ/a: 220V, dòng điện 5A, đ/a:250V, KH: ME-8108, không hiệu, Nsx: Zhejiang Zhiyuan Factory, mới 100% | C68: ='HỢP ĐỒNG'!D74 -> PCE | D68: ='HỢP ĐỒNG'!E74 -> 4000
A69: ='HỢP ĐỒNG'!A75 -> 57 | B69: ='HỢP ĐỒNG'!C75 -> Bộ nguồn adapter đa năng có núm xoay điều chỉnh điện áp dùng cho thiết bị massage điện đá nóng, model: 31220, đ/a đầu ra: 3-12V, dòng điện 2A, không hiệu, NSX: Shanghai Metal & Plastic. Mới 100% | C69: ='HỢP ĐỒNG'!D75 -> SET | D69: ='HỢP ĐỒNG'!E75 -> 2000 | F69: 2 | G69: 28 | H69: 32
A70: ='HỢP ĐỒNG'!A76 -> 58 | B70: ='HỢP ĐỒNG'!C76 -> Dây thắt lưng nam nữ đục lỗ hình ngôi sao, 4 màu đen, trắng, hồng, vàng, chất liệu nhựa giả da (PU), KT: rộng 1.8cm, dài 105cm+-10%, không hiệu, Nsx: Qingdao fashion Co., Ltd, Mới 100% | C70: ='HỢP ĐỒNG'!D76 -> PCE | D70: ='HỢP ĐỒNG'!E76 -> 800 | F70: 3 | G70: 67 | H70: 73
A71: ='HỢP ĐỒNG'!A77 -> 59 | B71: ='HỢP ĐỒNG'!C77 -> Dây thắt lưng nam nữ Y2K họa tiết ngôi sao, chất liệu nhựa gải da (PU), mặt khóa mạ màu bạc, KH:OLL403, KT: rộng 2.8cm, dài 105cm+-10%, không hiệu, Nsx: Qingdao fashion Co., Ltd, Mới 100% | C71: ='HỢP ĐỒNG'!D77 -> PCE | D71: ='HỢP ĐỒNG'!E77 -> 200
A72: ='HỢP ĐỒNG'!A78 -> 60 | B72: ='HỢP ĐỒNG'!C78 -> Dây thắt lưng nam nữ Y2K chất liệu nhựa giả da (PU), KT: rộng 2.8cm, dài 105cm+-10%, KH: OLL402, không hiệu, Nsx: Qingdao fashion Co., Ltd, Mới 100% | C72: ='HỢP ĐỒNG'!D78 -> PCE | D72: ='HỢP ĐỒNG'!E78 -> 100
A73: ='HỢP ĐỒNG'!A79 -> 61 | B73: ='HỢP ĐỒNG'!C79 -> Nắp bồn cầu chất liệu nhựa tổng hợp, KT: 445*360mm+-10%, KH: K-4713T, không hiệu,NSX: Toilet Seat Manufacturer (Xiamen), mới 100% | C73: ='HỢP ĐỒNG'!D79 -> PCE | D73: ='HỢP ĐỒNG'!E79 -> 100 | F73: 5 | G73: 118 | H73: 128
A74: ='HỢP ĐỒNG'!A80 -> 62 | B74: ='HỢP ĐỒNG'!C80 -> Bàn chải cọ rửa vệ sinh bình sữa, chất liệu nhựa tổng hợp, KT:28*6,5cm+-10%, không hiệu, NSX: Guangdong Stationery Co., Ltd.,mới 100% | C74: ='HỢP ĐỒNG'!D80 -> PCE | D74: ='HỢP ĐỒNG'!E80 -> 900 | F74: 2 | G74: 25 | H74: 29
A75: ='HỢP ĐỒNG'!A81 -> 63 | B75: ='HỢP ĐỒNG'!C81 -> Bộ khóa cửa dùng cho cửa cuốn gồm thân khóa, 3 chìa dẹt và phụ kiện lắp đặt, chất liệu sắt kết hợp nhựa, KT:4*20cm+-10%, không hiệu, Nsx: Zhejiang Zhiyuan Factory, mới 100% | C75: ='HỢP ĐỒNG'!D81 -> SET | D75: ='HỢP ĐỒNG'!E81 -> 1000 | F75: 1 | G75: 744 | H75: 746
A76: ='HỢP ĐỒNG'!A82 -> 64 | B76: ='HỢP ĐỒNG'!C82 -> Bộ khóa cửa dùng cho cửa cuốn gồm thân khóa, 4 chìa chữ thập và phụ kiện lắp đặt, chất liệu sắt kết hợp nhựa, KT:4*20cm+-10%, không hiệu, Nsx: Zhejiang Zhiyuan Factory, mới 100% | C76: ='HỢP ĐỒNG'!D82 -> SET | D76: ='HỢP ĐỒNG'!E82 -> 1000
A77: ='HỢP ĐỒNG'!A83 -> 65 | B77: ='HỢP ĐỒNG'!C83 -> Dải nhựa dạng cuộn dùng để bọc cạnh bàn chống va đập, bằng nhựa PVC xốp 1 mặt tự dính, KT: dài 200x3cm +/-10%.không hiệu.Nsx: Taizhou Plastic Mould. mới 100% | C77: ='HỢP ĐỒNG'!D83 -> ROL | D77: ='HỢP ĐỒNG'!E83 -> 560 | F77: 39 | G77: 285 | H77: 363
A78: ='HỢP ĐỒNG'!A84 -> 66 | B78: ='HỢP ĐỒNG'!C84 -> Dải nhựa dạng cuộn dùng để bọc cạnh bàn chống va đập, bằng nhựa PVC xốp 1 mặt tự dính, KT: dài 200x8cm +/-10%.không hiệu.Nsx: Taizhou Plastic Mould. mới 100% | C78: ='HỢP ĐỒNG'!D84 -> ROL | D78: ='HỢP ĐỒNG'!E84 -> 1500
A79: ='HỢP ĐỒNG'!A85 -> 67 | B79: ='HỢP ĐỒNG'!C85 -> Dải nhựa dạng cuộn dùng để bọc cạnh bàn chống va đập, bằng nhựa PVC xốp 1 mặt tự dính, KT: dài 200x5cm +/-10%.không hiệu.Nsx: Taizhou Plastic Mould. mới 100% | C79: ='HỢP ĐỒNG'!D85 -> ROL | D79: ='HỢP ĐỒNG'!E85 -> 480
A80: ='HỢP ĐỒNG'!A86 -> 68 | B80: ='HỢP ĐỒNG'!C86 -> Miếng nhựa bọc góc bàn chữ L chống va đập, bằng nhựa PVC xốp, 1 mặt tự dính, 5 cái/ túi, KT: dài 3.5x6cm +/-10%.không hiệu.Nsx: Taizhou Plastic Mould. mới 100% | C80: ='HỢP ĐỒNG'!D86 -> PCE | D80: ='HỢP ĐỒNG'!E86 -> 800
A81: ='HỢP ĐỒNG'!A87 -> 69 | B81: ='HỢP ĐỒNG'!C87 -> Bộ lọc dầu dùng cho máy nén khí trục vít QX105047. KT: 114x40x230mm+-10%, lưu lượng:120-180l/p, đk ren:38mm, không hiệu. NSX: Jiangxi Sange Filter. Mới 100% | C81: ='HỢP ĐỒNG'!D87 -> PCE | D81: ='HỢP ĐỒNG'!E87 -> 18 | F81: 2 | G81: 38 | H81: 42
A82: ='HỢP ĐỒNG'!A88 -> 70 | B82: ='HỢP ĐỒNG'!C88 -> Bộ lọc dầu dùng cho máy nén khí trục vít 04425274. KT: 1135*308*100mm+-10%, lưu lượng:120-180l/p, đk ren 38mm, không hiệu. Nsx: Ingersoll Rand. Mới 100% | C82: ='HỢP ĐỒNG'!D88 -> PCE | D82: ='HỢP ĐỒNG'!E88 -> 10
A83: ='HỢP ĐỒNG'!A89 -> 71 | B83: ='HỢP ĐỒNG'!C89 -> Bộ điều khiển cửa cuốn gồm 1 hộp tín hiệu trung tâm và 3 tay khiển, loại điều khiển bằng sóng hồng ngoại, vỏ bằng nhựa tổng hợp, không chứa dữ liệu, MMDS, sử dụng pin 23A/12V, hiệu: Macdoor. Mới 100% | C83: ='HỢP ĐỒNG'!D89 -> SET | D83: ='HỢP ĐỒNG'!E89 -> 500 | F83: 60 | G83: 536 | H83: 656
A84: ='HỢP ĐỒNG'!A90 -> 72 | B84: ='HỢP ĐỒNG'!C90 -> Bộ điều khiển cửa cuốn gồm 1 hộp tín hiệu trung tâm và 2 tay khiển, loại điều khiển bằng sóng hồng ngoại, không chứa dữ liệu, MMDS, sử dụng pin 23A/12V, hiệu: Safety controller. Mới 100% | C84: ='HỢP ĐỒNG'!D90 -> SET | D84: ='HỢP ĐỒNG'!E90 -> 700
A85: ='HỢP ĐỒNG'!A91 -> 73 | B85: ='HỢP ĐỒNG'!C91 -> Bàn chải cọ rửa vệ sinh đa năng loại không dùng điện, tay cầm bằng nhựa mặt cọ bằng miếng bọt biển mút xốp. KT: dài 30*8*5cm +/-10, không hiệu, Nsx: Picc property and casualty Co.,ltd, mới 100% | C85: ='HỢP ĐỒNG'!D91 -> PCE | D85: ='HỢP ĐỒNG'!E91 -> 980 | F85: 7 | G85: 53 | H85: 67
A86: ='HỢP ĐỒNG'!A92 -> 74 | B86: ='HỢP ĐỒNG'!C92 -> Động cơ vạn năng dây đồng xoay chiều/1 chiều, dùng cho máy xay thực phẩm, Đ/a: 220V/24V, cs: 600w, Không hiệu. Nsx: Wenzhou Feiding Motor. Mới 100% | C86: ='HỢP ĐỒNG'!D92 -> PCE | D86: ='HỢP ĐỒNG'!E92 -> 128 | F86: 4 | G86: 62 | H86: 70
A87: ='HỢP ĐỒNG'!A93 -> 75 | B87: ='HỢP ĐỒNG'!C93 -> Động cơ vạn năng 7712 dây đồng xoay chiều/1 chiều dùng để chế tạo các loại máy công cụ mini cầm tay, đ/a: 220v/12V. cs: 200w, Không hiệu. Nsx: Wenzhou Feiding Motor. Mới 100% | C87: ='HỢP ĐỒNG'!D93 -> PCE | D87: ='HỢP ĐỒNG'!E93 -> 1000 | F87: 7 | G87: 263 | H87: 277
A88: ='HỢP ĐỒNG'!A94 -> 76 | B88: ='HỢP ĐỒNG'!C94 -> Khay nhựa tổng hợp vân kim cương, dùng để đựng đồ trang điểm, trang sức (không chứa đựng thực phẩm), KT: (24*15-18*18)cm+/-10%, không hiệu, Nsx: Dongguan Huashuo Industrial Co., Ltd., mới 100% | C88: ='HỢP ĐỒNG'!D94 -> PCE | D88: ='HỢP ĐỒNG'!E94 -> 200 | F88: 34 | G88: 333 | H88: 401
A89: ='HỢP ĐỒNG'!A95 -> 77 | B89: ='HỢP ĐỒNG'!C95 -> Giày thể thao beier viền xanh, viền xám, đế giày bằng cao su mềm, thân và mũi giày bằng da tổng hợp phối vải lưới, màu trắng size 36-40, hiệu Beier, mới 100% | C89: ='HỢP ĐỒNG'!D95 -> PR | D89: ='HỢP ĐỒNG'!E95 -> 130 | F89: 13 | G89: 264 | H89: 290
A90: ='HỢP ĐỒNG'!A96 -> 78 | B90: ='HỢP ĐỒNG'!C96 -> Giày sneaker beier kitty, đế giày bằng cao su mềm, thân và mũi giày bằng da tổng hợp phối vải lưới, 2 màu hồng , be, size 36-40, hiệu Beier, mới 100% | C90: ='HỢP ĐỒNG'!D96 -> PR | D90: ='HỢP ĐỒNG'!E96 -> 75
A91: ='HỢP ĐỒNG'!A97 -> 79 | B91: ='HỢP ĐỒNG'!C97 -> Giày búp bê nữ beier, đế giày bằng cao su mềm, thân và mũi giày bằng da tổng hợp phối vải lưới, 2 màu be, trắng size 36-40, hiệu Beier, mới 100% | C91: ='HỢP ĐỒNG'!D97 -> PR | D91: ='HỢP ĐỒNG'!E97 -> 180
A92: ='HỢP ĐỒNG'!A98 -> 80 | B92: ='HỢP ĐỒNG'!C98 -> Đồng hồ đo nhiệt độ và độ ẩm cơ học (Th600B) đo không khí trong phòng, không dùng điện, chất liệu inox. KT: (20.5*16)cm+/-10%, hiệu: ANYMETRE, mới 100% | C92: ='HỢP ĐỒNG'!D98 -> PCE | D92: ='HỢP ĐỒNG'!E98 -> 400 | F92: 10 | G92: 84 | H92: 104
A93: ='HỢP ĐỒNG'!A99 -> 81 | B93: ='HỢP ĐỒNG'!C99 -> Đế nhựa dùng để cắm hoa bằng nhựa ABS, KT: 6.8*4.4cm, không hiệu, NSX: Ningbo Bonais Stationery Co., Ltd., mới 100% | C93: ='HỢP ĐỒNG'!D99 -> PCE | D93: ='HỢP ĐỒNG'!E99 -> 1600 | F93: 3 | G93: 32 | H93: 38
A94: ='HỢP ĐỒNG'!A100 -> 82 | B94: ='HỢP ĐỒNG'!C100 -> Tấm lưới chắn thùng xe container bằng sợi vải dù polyester, KT:2.4m*2.6m+-10%, không hiệu, NSX: Shandong Zhongxian Rope & Net Co., Ltd, mới 100% | C94: ='HỢP ĐỒNG'!D100 -> PCE | D94: ='HỢP ĐỒNG'!E100 -> 2768 | F94: 40 | G94: 1050 | H94: 1130
A95: ='HỢP ĐỒNG'!A101 -> 83 | B95: ='HỢP ĐỒNG'!C101 -> Đèn vòm bán nguyệt chuyên dụng lắp trên bàn làm nail, spa, sử dụng nguồn sáng đi-ốt phát quang LED không phải quang điện, model:2415. CS:36W/AC100-240V. Không hiệu. NSX:Zhongshan Ledlighning. Mới 100% | C95: ='HỢP ĐỒNG'!D101 -> PCE | D95: ='HỢP ĐỒNG'!E101 -> 600 | F95: 152 | G95: 1966 | H95: 2270
A96: ='HỢP ĐỒNG'!A102 -> 84 | B96: ='HỢP ĐỒNG'!C102 -> Dây cáp truyền dẫn tín hiệu âm thanh cho tivi đã gắn đầu nối dài 1.8m, không phải cáp điện, không dùng cho viễn thông, lõi nhôm, cách điện bằng nhựa, dòng 48V, ĐK lõi 1mm.Không hiệu.Mới 100% | C96: ='HỢP ĐỒNG'!D102 -> PCE | D96: ='HỢP ĐỒNG'!E102 -> 2830 | F96: 31 | G96: 804 | H96: 866
A97: ='HỢP ĐỒNG'!A103 -> 85 | B97: ='HỢP ĐỒNG'!C103 -> Dây cáp truyền dẫn tín hiệu âm thanh cho loa và micro, không phải cáp điện, không dùng cho viễn thông, lõi đồng kép, cách điện bằng nhựa, Đk lõi 1mm, 100m/cuộn. Đ/a: 48V.Hiệu Huicheng, mới 100% | C97: ='HỢP ĐỒNG'!D103 -> ROL | D97: ='HỢP ĐỒNG'!E103 -> 52
A98: ='HỢP ĐỒNG'!A104 -> 86 | B98: ='HỢP ĐỒNG'!C104 -> Điều khiển tivi từ xa,loại điều khiển bằng sóng hồng ngoại, vỏ bằng nhựa tổng hợp, KT:56*50*34mm, dùng pin 1.5V. Không hiệu. Nsx: Zhiyuan Desheng Co.,Ltd. Mới 100% | C98: ='HỢP ĐỒNG'!D104 -> PCE | D98: ='HỢP ĐỒNG'!E104 -> 350 | E98: =IF(C98="Kg",IF(I98<D98,I98&" "&C98&" "&"/ Kiện",I98&" "&C98&" "&"/ "&F98&" Kiện"),IF(AND(D98=I98),I98&" "&C98&" "&"/ "&F98&" Kiện",I98&" "&C98&" "&"/ Kiện")) -> PCE / Kiện
A99: ='HỢP ĐỒNG'!A105 -> 87 | B99: ='HỢP ĐỒNG'!C105 -> Điều khiển tivi từ xa dùng pin AAA, loại điều khiển bằng sóng hồng ngoại, vỏ bằng nhựa tổng hợp. KT: 15-25*4.5*2cm+/-10%. Không hiệu. Nsx: Zhejiang Zhiyuan Factory. Mới 100% | C99: ='HỢP ĐỒNG'!D105 -> PCE | D99: ='HỢP ĐỒNG'!E105 -> 150 | E99: =IF(C99="Kg",IF(I99<D99,I99&" "&C99&" "&"/ Kiện",I99&" "&C99&" "&"/ "&F99&" Kiện"),IF(AND(D99=I99),I99&" "&C99&" "&"/ "&F99&" Kiện",I99&" "&C99&" "&"/ Kiện")) -> PCE / Kiện
A100: ='HỢP ĐỒNG'!A106 -> 88 | B100: ='HỢP ĐỒNG'!C106 -> Bộ chuyển đổi âm thanh từ loa sang TV(bộ mã hóa),không kết hợp với bộ thu,vỏ bằng nhôm.Đ/a:12V,kí hiệu AQ5601 dòng điện 1A.Hiệu CHOSEAL.Mới 100% | C100: ='HỢP ĐỒNG'!D106 -> PCE | D100: ='HỢP ĐỒNG'!E106 -> 250 | E100: =IF(C100="Kg",IF(I100<D100,I100&" "&C100&" "&"/ Kiện",I100&" "&C100&" "&"/ "&F100&" Kiện"),IF(AND(D100=I100),I100&" "&C100&" "&"/ "&F100&" Kiện",I100&" "&C100&" "&"/ Kiện")) -> PCE / Kiện
A101: ='HỢP ĐỒNG'!A107 -> 89 | B101: ='HỢP ĐỒNG'!C107 -> Đầu nối (Giắc cắm) kết nối thiết bị âm thanh với micro, chất liệu bằng nhựa lõi đồng, KT: 8*3*33mm+-10%, dòng điện 1A, Không hiệu. NSX: Zhongshan Led lighning. Mới 100%. | C101: ='HỢP ĐỒNG'!D107 -> PCE | D101: ='HỢP ĐỒNG'!E107 -> 500 | E101: =IF(C101="Kg",IF(I101<D101,I101&" "&C101&" "&"/ Kiện",I101&" "&C101&" "&"/ "&F101&" Kiện"),IF(AND(D101=I101),I101&" "&C101&" "&"/ "&F101&" Kiện",I101&" "&C101&" "&"/ Kiện")) -> PCE / Kiện
A102: ='HỢP ĐỒNG'!A108 -> 90 | B102: ='HỢP ĐỒNG'!C108 -> Đệm ghế massage toàn thân, model: LX-075E, Cs: 12V/36W, hoạt động bằng điện, chất liệu chính mút xốp bọc vải giả da, KT: 105*61.5*41.5cm+-10%, không hiệu. NSX: Shenzhen Dongjilian Electronics,mới 100% | C102: ='HỢP ĐỒNG'!D108 -> PCE | D102: ='HỢP ĐỒNG'!E108 -> 100 | E102: =IF(C102="Kg",IF(I102<D102,I102&" "&C102&" "&"/ Kiện",I102&" "&C102&" "&"/ "&F102&" Kiện"),IF(AND(D102=I102),I102&" "&C102&" "&"/ "&F102&" Kiện",I102&" "&C102&" "&"/ Kiện")) -> PCE / Kiện | F102: 25 | G102: 488 | H102: 538
A103: ='HỢP ĐỒNG'!A109 -> 91 | B103: ='HỢP ĐỒNG'!C109 -> Động cơ giảm tốc 1 chiều (không phải động cơ bước) dùng tạo chuyển động cho lò quay vịt. Điện áp: 6-24V/150W. Model: ZYT61 6-24VDC. Tốc độ 15-60 vòng/phút, không hiệu. NSX: PINGYANG JINGE. mới 100% | C103: ='HỢP ĐỒNG'!D109 -> PCE | D103: ='HỢP ĐỒNG'!E109 -> 370 | E103: =IF(C103="Kg",IF(I103<D103,I103&" "&C103&" "&"/ Kiện",I103&" "&C103&" "&"/ "&F103&" Kiện"),IF(AND(D103=I103),I103&" "&C103&" "&"/ "&F103&" Kiện",I103&" "&C103&" "&"/ Kiện")) -> PCE / Kiện | F103: 5 | G103: 437 | H103: 447
...

Sheet nhập máy
A1: STT | B1: Mã hàng | C1: Tên hàng (mô tả chi tiết) | D1: Mã HS | E1: Xuất xứ | F1: S. Lượng | G1: Đơn vị tính | H1: S Lượng 2 | I1: ĐVT 2 | J1: Đơn giá hóa đơn | K1: Trị giá hóa đơn | L1: Mã tiền Trị giá tính thuế | M1: Mã biểu thuế NK | N1: TS NK(%) | O1: Mã áp dụng mức thuế tuyệt đối | P1: (2) Số mục khai khoản điều chỉnh | Q1: (3) Số mục khai khoản điều chỉnh | R1: (4) Số mục khai khoản điều chỉnh | S1: Số đăng ký danh mục miễn thuế NK | T1: Số dòng tương ứng trong danh mục | U1: Mã miễn/ giảm/ không chịu thuế nhập khẩu | V1: Thuế suất TTĐB(%) | W1: Tiền thuế TTĐB | X1: Mã miễn giảm thuế TTĐB | Z1: Thuế suất VAT
A2: ='HỢP ĐỒNG'!A19 -> 1 | C2: ='HỢP ĐỒNG'!C19 -> Khăn lau bụi dùng để lau xe hơi, chất liệu vải dệt kim từ sợi polyester, KT:(30*30)cm, không hiệu, NSX: Qingdao Tao Hui Industrial. Mới 100% | D2: ='HỢP ĐỒNG'!I19 -> 63071090 | E2: CN | F2: ='HỢP ĐỒNG'!E19 -> 20000 | G2: ='INVOICE lam CO'!D15 -> PCE | H2: 280 | I2: KGM | J2: ='HỢP ĐỒNG'!F19 -> 0.094 | M2: B05 | Y2: =IF(Z2=8%,"VB245",IF(Z2=10%,"VB901",IF(Z2=5%,"VB185",""))) -> VB245 | Z2: ='HỢP ĐỒNG'!P19 -> 0.08
A3: ='HỢP ĐỒNG'!A20 -> 2 | C3: ='HỢP ĐỒNG'!C20 -> Bộ ấm chén pha trà bằng gốm đất nung tráng men rạn Nhữ Diêu,gồm ấm trà dung tích 250ml,chén khải 190ml và chén uống trà 50ml, đóng hộp quà tặng, không hiệu. NSX: Shenzhen Tao Hui Industrial. Mới 100% | D3: ='HỢP ĐỒNG'!I20 -> 69120000 | E3: CN | F3: ='HỢP ĐỒNG'!E20 -> 20 | G3: ='INVOICE lam CO'!D16 -> SET | H3: 20 | I3: SET | J3: ='HỢP ĐỒNG'!F20 -> 5.16 | M3: B05 | Y3: =IF(Z3=8%,"VB245",IF(Z3=10%,"VB901",IF(Z3=5%,"VB185",""))) -> VB245 | Z3: ='HỢP ĐỒNG'!P20 -> 0.08
A4: ='HỢP ĐỒNG'!A21 -> 3 | C4: ='HỢP ĐỒNG'!C21 -> Bộ ấm chén pha trà du lịch bằng gốm đất nung tráng men trắng, dáng Tây Thi họa tiết Núi Non, gồm ấm trà dung tích 270ml, tống trà 150ml, chén trà 50ml,đóng hộp quà tặng, không hiệu, Mới 100% | D4: ='HỢP ĐỒNG'!I21 -> 69120000 | E4: CN | F4: ='HỢP ĐỒNG'!E21 -> 20 | G4: ='INVOICE lam CO'!D17 -> SET | H4: 20 | I4: SET | J4: ='HỢP ĐỒNG'!F21 -> 4.09 | M4: B05 | Y4: =IF(Z4=8%,"VB245",IF(Z4=10%,"VB901",IF(Z4=5%,"VB185",""))) -> VB245 | Z4: ='HỢP ĐỒNG'!P21 -> 0.08
A5: ='HỢP ĐỒNG'!A22 -> 4 | C5: ='HỢP ĐỒNG'!C22 -> Bộ ấm chén trà bằng gốm đất nung, kiểu dáng Nhật gồm 1 ấm 200ml và 4 chén 60ml kèm hộp quà tặng, không hiệu, NSX: Shenzhen Tao Hui Industrial Co., Ltd., Mới 100% | D5: ='HỢP ĐỒNG'!I22 -> 69120000 | E5: CN | F5: ='HỢP ĐỒNG'!E22 -> 50 | G5: ='INVOICE lam CO'!D18 -> SET | H5: 50 | I5: SET | J5: ='HỢP ĐỒNG'!F22 -> 5.69 | M5: B05 | Y5: =IF(Z5=8%,"VB245",IF(Z5=10%,"VB901",IF(Z5=5%,"VB185",""))) -> VB245 | Z5: ='HỢP ĐỒNG'!P22 -> 0.08
A6: ='HỢP ĐỒNG'!A23 -> 5 | C6: ='HỢP ĐỒNG'!C23 -> Ấm pha trà bằng gốm đất nung không tráng men (Tử Sa) dáng Hán Ngõa, màu xanh Lục Nê, dung tích 240ml, không dùng điện, không hiệu, NSX: Shenzhen Tao Hui Industrial Co., Ltd., Mới 100% | D6: ='HỢP ĐỒNG'!I23 -> 69120000 | E6: CN | F6: ='HỢP ĐỒNG'!E23 -> 10 | G6: ='INVOICE lam CO'!D19 -> PCE | H6: 10 | I6: PCE | J6: ='HỢP ĐỒNG'!F23 -> 13.6 | M6: B05 | Y6: =IF(Z6=8%,"VB245",IF(Z6=10%,"VB901",IF(Z6=5%,"VB185",""))) -> VB245 | Z6: ='HỢP ĐỒNG'!P23 -> 0.08
A7: ='HỢP ĐỒNG'!A24 -> 6 | C7: ='HỢP ĐỒNG'!C24 -> Ấm pha trà bằng gốm đất nung không tráng men (Tử Sa) dáng Tây Thi, màu đỏ Đại Hồng Bào, dung tích 240ml, không dùng điện, không hiệu, NSX: Shenzhen Tao Hui Industrial Co., Ltd., Mới 100% | D7: ='HỢP ĐỒNG'!I24 -> 69120000 | E7: CN | F7: ='HỢP ĐỒNG'!E24 -> 15 | G7: ='INVOICE lam CO'!D20 -> PCE | H7: 15 | I7: PCE | J7: ='HỢP ĐỒNG'!F24 -> 10.46 | M7: B05 | Y7: =IF(Z7=8%,"VB245",IF(Z7=10%,"VB901",IF(Z7=5%,"VB185",""))) -> VB245 | Z7: ='HỢP ĐỒNG'!P24 -> 0.08
A8: ='HỢP ĐỒNG'!A25 -> 7 | C8: ='HỢP ĐỒNG'!C25 -> Cốc uống trà bằng gốm đất nung không tráng men (Tử Sa) họa tiết Thiên Hương, dung tích 180ml, không hiệu, NSX: Shenzhen Tao Hui Industrial Co., Ltd., Mới 100% | D8: ='HỢP ĐỒNG'!I25 -> 69120000 | E8: CN | F8: ='HỢP ĐỒNG'!E25 -> 20 | G8: ='INVOICE lam CO'!D21 -> PCE | H8: 20 | I8: PCE | J8: ='HỢP ĐỒNG'!F25 -> 4.49 | M8: B05 | Y8: =IF(Z8=8%,"VB245",IF(Z8=10%,"VB901",IF(Z8=5%,"VB185",""))) -> VB245 | Z8: ='HỢP ĐỒNG'!P25 -> 0.08
A9: ='HỢP ĐỒNG'!A26 -> 8 | C9: ='HỢP ĐỒNG'!C26 -> Ấm pha trà bằng gốm đất nung không tráng men (Tử Sa) dáng Bát Phương Nung Củi, màu vàng Đoạn Nê, dung tích 270ml, không dùng điện, không hiệu, NSX: Shenzhen Tao Hui Industrial Co., Ltd., Mới 100% | D9: ='HỢP ĐỒNG'!I26 -> 69120000 | E9: CN | F9: ='HỢP ĐỒNG'!E26 -> 10 | G9: ='INVOICE lam CO'!D22 -> PCE | H9: 10 | I9: PCE | J9: ='HỢP ĐỒNG'!F26 -> 16.74 | M9: B05 | Y9: =IF(Z9=8%,"VB245",IF(Z9=10%,"VB901",IF(Z9=5%,"VB185",""))) -> VB245 | Z9: ='HỢP ĐỒNG'!P26 -> 0.08
A10: ='HỢP ĐỒNG'!A27 -> 9 | C10: ='HỢP ĐỒNG'!C27 -> Ấm pha trà bằng gốm đất nung không tráng men (Tử Sa) dáng Thạch Biều, màu xanh Lục Nê, dung tích 260ml, không dùng điện, không hiệu, NSX: Shenzhen Tao Hui Industrial Co., Ltd., Mới 100% | D10: ='HỢP ĐỒNG'!I27 -> 69120000 | E10: CN | F10: ='HỢP ĐỒNG'!E27 -> 5 | G10: ='INVOICE lam CO'!D23 -> PCE | H10: 5 | I10: PCE | J10: ='HỢP ĐỒNG'!F27 -> 15.69 | M10: B05 | Y10: =IF(Z10=8%,"VB245",IF(Z10=10%,"VB901",IF(Z10=5%,"VB185",""))) -> VB245 | Z10: ='HỢP ĐỒNG'!P27 -> 0.08
A11: ='HỢP ĐỒNG'!A28 -> 10 | C11: ='HỢP ĐỒNG'!C28 -> Ấm pha trà bằng gốm đất nung không tráng men (Tử Sa) dáng Vân Lư, màu nâu Thiết Huyết Hồng Sa, dung tích 260ml, không dùng điện, không hiệu, NSX: Shenzhen Tao Hui Industrial Co., Ltd., Mới 100% | D11: ='HỢP ĐỒNG'!I28 -> 69120000 | E11: CN | F11: ='HỢP ĐỒNG'!E28 -> 10 | G11: ='INVOICE lam CO'!D24 -> PCE | H11: 10 | I11: PCE | J11: ='HỢP ĐỒNG'!F28 -> 17.09 | M11: B05 | Y11: =IF(Z11=8%,"VB245",IF(Z11=10%,"VB901",IF(Z11=5%,"VB185",""))) -> VB245 | Z11: ='HỢP ĐỒNG'!P28 -> 0.08
A12: ='HỢP ĐỒNG'!A29 -> 11 | C12: ='HỢP ĐỒNG'!C29 -> Ấm pha trà bằng gốm đất nung không tráng men (Tử Sa) dáng Tứ Phương Liên Hoa dung tích 230ml, không dùng điện, không hiệu, NSX: Shenzhen Tao Hui Industrial Co., Ltd., Mới 100% | D12: ='HỢP ĐỒNG'!I29 -> 69120000 | E12: CN | F12: ='HỢP ĐỒNG'!E29 -> 10 | G12: ='INVOICE lam CO'!D25 -> PCE | H12: 10 | I12: PCE | J12: ='HỢP ĐỒNG'!F29 -> 14.47 | M12: B05 | Y12: =IF(Z12=8%,"VB245",IF(Z12=10%,"VB901",IF(Z12=5%,"VB185",""))) -> VB245 | Z12: ='HỢP ĐỒNG'!P29 -> 0.08
A13: ='HỢP ĐỒNG'!A30 -> 12 | C13: ='HỢP ĐỒNG'!C30 -> Ấm pha trà bằng gốm đất nung không tráng men (Tử Sa) dáng Long Đán, màu nâu Tử Nê, dung tích 220ml, không dùng điện, không hiệu, NSX: Shenzhen Tao Hui Industrial Co., Ltd., Mới 100% | D13: ='HỢP ĐỒNG'!I30 -> 69120000 | E13: CN | F13: ='HỢP ĐỒNG'!E30 -> 3 | G13: ='INVOICE lam CO'!D26 -> PCE | H13: 3 | I13: PCE | J13: ='HỢP ĐỒNG'!F30 -> 20.46 | M13: B05 | Y13: =IF(Z13=8%,"VB245",IF(Z13=10%,"VB901",IF(Z13=5%,"VB185",""))) -> VB245 | Z13: ='HỢP ĐỒNG'!P30 -> 0.08
... A100: ='HỢP ĐỒNG'!A117 -> 99 | C100: ='HỢP ĐỒNG'!C117 -> Điều khiển điều hòa từ xa, điều khiển bằng sóng hồng ngoại, vỏ bằng nhựa PVC. Không hiệu. Nsx: Shanghai shanghua electronic Co.,Ltd. Mới 100% | D100: ='HỢP ĐỒNG'!I117 -> 85437029 | E100: CN | F100: ='HỢP ĐỒNG'!E117 -> 3450 | G100: ='INVOICE lam CO'!D113 -> PCE | H100: 3450 | I100: PCE | J100: ='HỢP ĐỒNG'!F117 -> 0.57 | M100: B05 | Y100: =IF(Z100=8%,"VB245",IF(Z100=10%,"VB901",IF(Z100=5%,"VB185",""))) -> VB245 | Z100: ='HỢP ĐỒNG'!P117 -> 0.08
A101: ='HỢP ĐỒNG'!A118 -> 100 | C101: ='HỢP ĐỒNG'!C118 -> Máy cưa bê tông đĩa tròn cầm tay không chổi than model K6006, hoạt động bằng điện, đ/a: 220V, cs: 55W, tốc độ: 2700 vòng/p, không hiệu,NSX: Ningbo zhihao machinery. Mới 100% | D101: ='HỢP ĐỒNG'!I118 -> 84672900 | E101: CN | F101: ='HỢP ĐỒNG'!E118 -> 16 | G101: UNK | H101: 16 | I101: PCE | J101: ='HỢP ĐỒNG'!F118 -> 30.16 | M101: B05 | Y101: =IF(Z101=8%,"VB245",IF(Z101=10%,"VB901",IF(Z101=5%,"VB185",""))) -> VB245 | Z101: ='HỢP ĐỒNG'!P118 -> 0.08
A102: ='HỢP ĐỒNG'!A119 -> 101 | C102: ='HỢP ĐỒNG'!C119 -> Đèn chiếu sáng trang trí bể cá cảnh, Model:DY-A200, sử dụng nguồn sáng đi ốt phát quang (LED) không phải loại quang điện. KT: 20*15*8cm. CS: 18W/220V. Hiệu:DEYAO. Mới 100% | D102: ='HỢP ĐỒNG'!I119 -> 94054290 | E102: CN | F102: ='HỢP ĐỒNG'!E119 -> 120 | G102: UNK | H102: 120 | I102: PCE | J102: ='HỢP ĐỒNG'!F119 -> 2.07 | M102: B05 | Y102: =IF(Z102=8%,"VB245",IF(Z102=10%,"VB901",IF(Z102=5%,"VB185",""))) -> VB245 | Z102: ='HỢP ĐỒNG'!P119 -> 0.08
A103: ='HỢP ĐỒNG'!A120 -> 102 | C103: ='HỢP ĐỒNG'!C120 -> Đèn chiếu sáng trang trí bể cá cảnh, Model:DY-A300, sử dụng nguồn sáng đi ốt phát quang (LED) không phải loại quang điện. KT: 30*15*8cm. CS: 22W/220V. Hiệu:DEYAO. Mới 100% | D103: ='HỢP ĐỒNG'!I120 -> 94054290 | E103: CN | F103: ='HỢP ĐỒNG'!E120 -> 160 | G103: UNK | H103: 160 | I103: PCE | J103: ='HỢP ĐỒNG'!F120 -> 2.26 | M103: B05 | Y103: =IF(Z103=8%,"VB245",IF(Z103=10%,"VB901",IF(Z103=5%,"VB185",""))) -> VB245 | Z103: ='HỢP ĐỒNG'!P120 -> 0.08
A104: ='HỢP ĐỒNG'!A121 -> 103 | C104: ='HỢP ĐỒNG'!C121 -> Đèn chiếu sáng trang trí bể cá cảnh, Model:DY-A400, sử dụng nguồn sáng đi ốt phát quang (LED) không phải loại quang điện. KT: 40*15*8cm. CS: 28W/220V. Hiệu:DEYAO. Mới 100% | D104: ='HỢP ĐỒNG'!I121 -> 94054290 | E104: CN | F104: ='HỢP ĐỒNG'!E121 -> 200 | G104: ='INVOICE lam CO'!D117 -> PCE | H104: 200 | I104: PCE | J104: ='HỢP ĐỒNG'!F121 -> 2.45 | M104: B05 | Y104: =IF(Z104=8%,"VB245",IF(Z104=10%,"VB901",IF(Z104=5%,"VB185",""))) -> VB245 | Z104: ='HỢP ĐỒNG'!P121 -> 0.08
A105: ='HỢP ĐỒNG'!A122 -> 104 | C105: ='HỢP ĐỒNG'!C122 -> Đèn chiếu sáng trang trí bể cá cảnh, Model:DY-A500, sử dụng nguồn sáng đi ốt phát quang (LED) không phải loại quang điện. KT: 50*15*8cm. CS: 34W/220V. Hiệu:DEYAO. Mới 100% | D105: ='HỢP ĐỒNG'!I122 -> 94054290 | E105: CN | F105: ='HỢP ĐỒNG'!E122 -> 600 | G105: ='INVOICE lam CO'!D118 -> PCE | H105: 600 | I105: PCE | J105: ='HỢP ĐỒNG'!F122 -> 2.64 | M105: B05 | Y105: =IF(Z105=8%,"VB245",IF(Z105=10%,"VB901",IF(Z105=5%,"VB185",""))) -> VB245 | Z105: ='HỢP ĐỒNG'!P122 -> 0.08
A106: ='HỢP ĐỒNG'!A123 -> 105 | C106: ='HỢP ĐỒNG'!C123 -> Đèn chiếu sáng trang trí bể cá cảnh, Model:DY-A600, sử dụng nguồn sáng đi ốt phát quang (LED) không phải loại quang điện. KT: 60*15*8cm. CS: 38W/220V. Hiệu:DEYAO. Mới 100% | D106: ='HỢP ĐỒNG'!I123 -> 94054290 | E106: CN | F106: ='HỢP ĐỒNG'!E123 -> 800 | G106: ='INVOICE lam CO'!D119 -> PCE | H106: 800 | I106: PCE | J106: ='HỢP ĐỒNG'!F123 -> 2.83 | M106: B05 | Y106: =IF(Z106=8%,"VB245",IF(Z106=10%,"VB901",IF(Z106=5%,"VB185",""))) -> VB245 | Z106: ='HỢP ĐỒNG'!P123 -> 0.08
A107: ='HỢP ĐỒNG'!A124 -> 106 | C107: ='HỢP ĐỒNG'!C124 -> Đèn chiếu sáng trang trí bể cá cảnh, Model:DY-A800, sử dụng nguồn sáng đi ốt phát quang (LED) không phải loại quang điện. KT: 80*15*8cm. CS: 46W/220V. Hiệu:DEYAO. Mới 100% | D107: ='HỢP ĐỒNG'!I124 -> 94054290 | E107: CN | F107: ='HỢP ĐỒNG'!E124 -> 600 | G107: UNK | H107: 600 | I107: PCE | J107: ='HỢP ĐỒNG'!F124 -> 3.02 | M107: B05 | Y107: =IF(Z107=8%,"VB245",IF(Z107=10%,"VB901",IF(Z107=5%,"VB185",""))) -> VB245 | Z107: ='HỢP ĐỒNG'!P124 -> 0.08
A108: ='HỢP ĐỒNG'!A125 -> 107 | C108: ='HỢP ĐỒNG'!C125 -> Đèn chiếu sáng trang trí bể cá cảnh, Model:DY-A1000, sử dụng nguồn sáng đi ốt phát quang (LED) không phải loại quang điện. KT: 100*15*8cm. CS: 55W/220V. Hiệu:DEYAO. Mới 100% | D108: ='HỢP ĐỒNG'!I125 -> 94054290 | E108: CN | F108: ='HỢP ĐỒNG'!E125 -> 400 | G108: UNK | H108: 400 | I108: PCE | J108: ='HỢP ĐỒNG'!F125 -> 3.2 | M108: B05 | Y108: =IF(Z108=8%,"VB245",IF(Z108=10%,"VB901",IF(Z108=5%,"VB185",""))) -> VB245 | Z108: ='HỢP ĐỒNG'!P125 -> 0.08
A109: ='HỢP ĐỒNG'!A126 -> 108 | C109: ='HỢP ĐỒNG'!C126 -> Đèn chiếu sáng trang trí bể cá cảnh, Model: E23, sử dụng nguồn sáng đi ốt phát quang (LED) không phải loại quang điện. KT: 30*10*8cm. Công suất:12w/220V. Hiệu:DEYAO. Mới 100% | D109: ='HỢP ĐỒNG'!I126 -> 94054290 | E109: CN | F109: ='HỢP ĐỒNG'!E126 -> 250 | G109: UNK | H109: 250 | I109: PCE | J109: ='HỢP ĐỒNG'!F126 -> 2.26 | M109: B05 | Y109: =IF(Z109=8%,"VB245",IF(Z109=10%,"VB901",IF(Z109=5%,"VB185",""))) -> VB245 | Z109: ='HỢP ĐỒNG'!P126 -> 0.08
A110: ='HỢP ĐỒNG'!A127 -> 109 | C110: ='HỢP ĐỒNG'!C127 -> Đèn chiếu sáng trang trí bể cá cảnh, Model:E29 , sử dụng nguồn sáng đi ốt phát quang (LED) không phải loại quang điện. KT: 40*10*8cm. Công suất:16w/220V. Hiệu:DEYAO. Mới 100% | D110: ='HỢP ĐỒNG'!I127 -> 94054290 | E110: CN | F110: ='HỢP ĐỒNG'!E127 -> 250 | G110: UNK | H110: 250 | I110: PCE | J110: ='HỢP ĐỒNG'!F127 -> 2.64 | M110: B05 | Y110: =IF(Z110=8%,"VB245",IF(Z110=10%,"VB901",IF(Z110=5%,"VB185",""))) -> VB245 | Z110: ='HỢP ĐỒNG'!P127 -> 0.08
A111: ='HỢP ĐỒNG'!A128 -> 110 | C111: ='HỢP ĐỒNG'!C128 -> Đèn chiếu sáng trang trí bể cá cảnh, Model: E39, sử dụng nguồn sáng đi ốt phát quang (LED) không phải loại quang điện. KT: 40*10*8cm. Công suất:20w/220V. Hiệu:DEYAO. Mới 100% | D111: ='HỢP ĐỒNG'!I128 -> 94054290 | E111: CN | F111: ='HỢP ĐỒNG'!E128 -> 250 | G111: UNK | H111: 250 | I111: PCE | J111: ='HỢP ĐỒNG'!F128 -> 3.02 | M111: B05 | Y111: =IF(Z111=8%,"VB245",IF(Z111=10%,"VB901",IF(Z111=5%,"VB185",""))) -> VB245 | Z111: ='HỢP ĐỒNG'!P128 -> 0.08
A112: ='HỢP ĐỒNG'!A129 -> 111 | C112: ='HỢP ĐỒNG'!C129 -> Đèn chiếu sáng trang trí bể cá cảnh, Model: E49 , sử dụng nguồn sáng đi ốt phát quang (LED) không phải loại quang điện. KT: 40*10*8cm. Công suất:24w/220V. Hiệu:DEYAO. Mới 100% | D112: ='HỢP ĐỒNG'!I129 -> 94054290 | E112: CN | F112: ='HỢP ĐỒNG'!E129 -> 250 | G112: UNK | H112: 250 | I112: PCE | J112: ='HỢP ĐỒNG'!F129 -> 3.39 | M112: B05 | Y112: =IF(Z112=8%,"VB245",IF(Z112=10%,"VB901",IF(Z112=5%,"VB185",""))) -> VB245 | Z112: ='HỢP ĐỒNG'!P129 -> 0.08
A113: ='HỢP ĐỒNG'!A130 -> 112 | C113: ='HỢP ĐỒNG'!C130 -> Đèn chiếu sáng trang trí bể cá cảnh, Model:CF02, sử dụng nguồn sáng đi ốt phát quang (LED), không phải loại quang điện. KT: 18*15*6cm.Công suất: 13W-220V. Hiệu:DEYAO. Mới 100% | D113: ='HỢP ĐỒNG'!I130 -> 94054290 | E113: CN | F113: ='HỢP ĐỒNG'!E130 -> 2000 | G113: UNK | H113: 2000 | I113: PCE | J113: ='HỢP ĐỒNG'!F130 -> 2.07 | M113: B05 | Y113: =IF(Z113=8%,"VB245",IF(Z113=10%,"VB901",IF(Z113=5%,"VB185",""))) -> VB245 | Z113: ='HỢP ĐỒNG'!P130 -> 0.08
A114: ='HỢP ĐỒNG'!A131 -> 113 | C114: ='HỢP ĐỒNG'!C131 -> Đèn chiếu sáng trang trí bể cá cảnh, Model:F-01, sử dụng nguồn sáng đi ốt phát quang (LED), không phải loại quang điện KT: 35*15*10cm.Công suất: 12W-220V. Hiệu:DEYAO. Mới 100% | D114: ='HỢP ĐỒNG'!I131 -> 94054290 | E114: CN | F114: ='HỢP ĐỒNG'!E131 -> 300 | G114: UNK | H114: 300 | I114: PCE | J114: ='HỢP ĐỒNG'!F131 -> 2.64 | M114: B05 | Y114: =IF(Z114=8%,"VB245",IF(Z114=10%,"VB901",IF(Z114=5%,"VB185",""))) -> VB245 | Z114: ='HỢP ĐỒNG'!P131 -> 0.08
A115: ='HỢP ĐỒNG'!A132 -> 114 | C115: ='HỢP ĐỒNG'!C132 -> Đèn chiếu sáng trang trí bể cá cảnh, Model:F-07, sử dụng nguồn sáng đi ốt phát quang (LED), không phải loại quang điện. KT: 35*15*10cm.Công suất: 20W-220V. Hiệu:DEYAO. Mới 100% | D115: ='HỢP ĐỒNG'!I132 -> 94054290 | E115: CN | F115: ='HỢP ĐỒNG'!E132 -> 250 | G115: UNK | H115: 250 | I115: PCE | J115: ='HỢP ĐỒNG'!F132 -> 3.39 | M115: B05 | Y115: =IF(Z115=8%,"VB245",IF(Z115=10%,"VB901",IF(Z115=5%,"VB185",""))) -> VB245 | Z115: ='HỢP ĐỒNG'!P132 -> 0.08
A116: ='HỢP ĐỒNG'!A133 -> 115 | C116: ='HỢP ĐỒNG'!C133 -> Đèn chiếu sáng trang trí bể cá cảnh, Model:F-09, sử dụng nguồn sáng đi ốt phát quang (LED, không phải loại quang điện. KT: 35*15*10cm.Công suất: 15W-220V. Hiệu:DEYAO. Mới 100% | D116: ='HỢP ĐỒNG'!I133 -> 94054290 | E116: CN | F116: ='HỢP ĐỒNG'!E133 -> 400 | G116: UNK | H116: 400 | I116: PCE | J116: ='HỢP ĐỒNG'!F133 -> 4.9 | M116: B05 | Y116: =IF(Z116=8%,"VB245",IF(Z116=10%,"VB901",IF(Z116=5%,"VB185",""))) -> VB245 | Z116: ='HỢP ĐỒNG'!P133 -> 0.08
A117: ='HỢP ĐỒNG'!A134 -> 116 | C117: ='HỢP ĐỒNG'!C134 -> Hộp giấy bìa không sóng có thể gấp lại dùng để đóng gói, vận chuyển hoa sáp, KT: 46*24*8cm+-10%, không hiệu. Nsx: Guangdong Daming Decoration Co., Ltd, Mới 100% | D117: ='HỢP ĐỒNG'!I134 -> 48192000 | E117: CN | F117: ='HỢP ĐỒNG'!E134 -> 400 | G117: ='INVOICE lam CO'!D130 -> KGM | H117: 400 | I117: KGM | J117: ='HỢP ĐỒNG'!F134 -> 0.8 | M117: B01 | Y117: =IF(Z117=8%,"VB245",IF(Z117=10%,"VB901",IF(Z117=5%,"VB185",""))) -> VB245 | Z117: ='HỢP ĐỒNG'!P134 -> 0.08
A118: ='HỢP ĐỒNG'!A135 -> 117 | C118: ='HỢP ĐỒNG'!C135 -> Khay nhựa PVC định hình bóng khí, dùng lót đáy hộp quà tặng khi đóng gói vận chuyển, chất liệu nhựa PVC, KT: 44*22*3.1cm+-10%, không hiệu. Nsx: Guangdong Daming Decoration Co., Ltd, Mới 100% | D118: ='HỢP ĐỒNG'!I135 -> 39239090 | E118: CN | F118: ='HỢP ĐỒNG'!E135 -> 100 | G118: ='INVOICE lam CO'!D131 -> KGM | H118: 100 | I118: KGM | J118: ='HỢP ĐỒNG'!F135 -> 1.3 | M118: B05 | Y118: =IF(Z118=8%,"VB245",IF(Z118=10%,"VB901",IF(Z118=5%,"VB185",""))) -> VB245 | Z118: ='HỢP ĐỒNG'!P135 -> 0.08
A119: ='HỢP ĐỒNG'!A136 -> 118 | C119: ='HỢP ĐỒNG'!C136 -> Giày bốt trẻ em cổ cao quá mắt cá chân, không đúc, đế bằng cao su mềm, mũ giày bằng nhựa giả da, mũi không gắn bảo vệ, size 22-31. KH:D509, không hiệu. NSX:Jinjiang Anao Footwear Co.,Ltd. mới 100% | D119: ='HỢP ĐỒNG'!I136 -> 64029199 | E119: CN | F119: ='HỢP ĐỒNG'!E136 -> 200 | G119: ='INVOICE lam CO'!D132 -> PR | H119: 200 | I119: PR | J119: ='HỢP ĐỒNG'!F136 -> 1.13 | M119: B05 | Y119: =IF(Z119=8%,"VB245",IF(Z119=10%,"VB901",IF(Z119=5%,"VB185",""))) -> VB245 | Z119: ='HỢP ĐỒNG'!P136 -> 0.08
A120: ='HỢP ĐỒNG'!A137 -> 119 | C120: ='HỢP ĐỒNG'!C137 -> Trạm mồi chống mối nổi kèm phụ kiện lắp đặt, không thấm tẩm hóa chất, chất liệu bằng nhựa tổng hợp, KT: 16.5*8.5*6.5cm+-10%, không hiệu. NSX: Shenzhen iPest Technology Co., Ltd. mới 100% | D120: ='HỢP ĐỒNG'!I137 -> 39269099 | E120: CN | F120: ='HỢP ĐỒNG'!E137 -> 500 | G120: ='INVOICE lam CO'!D133 -> SET | H120: 500 | I120: SET | J120: ='HỢP ĐỒNG'!F137 -> 0.89 | M120: B05 | Y120: =IF(Z120=8%,"VB245",IF(Z120=10%,"VB901",IF(Z120=5%,"VB185",""))) -> VB245 | Z120: ='HỢP ĐỒNG'!P137 -> 0.08
A121: ='HỢP ĐỒNG'!A138 -> 120 | C121: ='HỢP ĐỒNG'!C138 -> Bánh xe treo cửa thang máy, chất liệu bằng thép không gỉ. KT: (56*14)mm, model: 6201RS, không hiệu. NSX: Tiyou Elevator Parts. Mới 100% | D121: ='HỢP ĐỒNG'!I138 -> 84313120 | E121: CN | F121: ='HỢP ĐỒNG'!E138 -> 200 | G121: ='INVOICE lam CO'!D134 -> PCE | H121: 200 | I121: PCE | J121: ='HỢP ĐỒNG'!F138 -> 1.39 | M121: B05 | Y121: =IF(Z121=8%,"VB245",IF(Z121=10%,"VB901",IF(Z121=5%,"VB185",""))) -> VB245 | Z121: ='HỢP ĐỒNG'!P138 -> 0.08
A122: ='HỢP ĐỒNG'!A139 -> 121 | C122: ='HỢP ĐỒNG'!C139 -> Bánh xe treo cửa thang máy, rãnh phẳng, chất liệu bằng thép không gỉ. KT: (62*16)mm, model: 6203, không hiệu. NSX: Tiyou Elevator Parts. Mới 100% | D122: ='HỢP ĐỒNG'!I139 -> 84313120 | E122: CN | F122: ='HỢP ĐỒNG'!E139 -> 150 | G122: ='INVOICE lam CO'!D135 -> PCE | H122: 150 | I122: PCE | J122: ='HỢP ĐỒNG'!F139 -> 2.07 | M122: B05 | Y122: =IF(Z122=8%,"VB245",IF(Z122=10%,"VB901",IF(Z122=5%,"VB185",""))) -> VB245 | Z122: ='HỢP ĐỒNG'!P139 -> 0.08
A123: ='HỢP ĐỒNG'!A140 -> 122 | C123: ='HỢP ĐỒNG'!C140 -> Bông hoa tuylip nhân tạo, chất liệu nhựa PVC, lõi bằng thép, đã định hình hoàn chỉnh, dùng để trang trí. KT: (35*4)cm+/-10%, không hiệu. NSX: Yuchen Artificial Flower Strength Supplier, mới 100% | D123: ='HỢP ĐỒNG'!I140 -> 67029090 | E123: CN | F123: ='HỢP ĐỒNG'!E140 -> 10000 | G123: ='INVOICE lam CO'!D136 -> PCE | H123: 105 | I123: KGM | J123: ='HỢP ĐỒNG'!F140 -> 0.075 | M123: B05 | Y123: =IF(Z123=8%,"VB245",IF(Z123=10%,"VB901",IF(Z123=5%,"VB185",""))) -> VB245 | Z123: ='HỢP ĐỒNG'!P140 -> 0.08
A124: ='HỢP ĐỒNG'!A141 -> 123 | C124: ='HỢP ĐỒNG'!C141 -> Giấy gói hoa dạng giấy nhún, được làm từ bột gỗ xenlulo, đã nhuộm màu bề mặt, dạng tấm, KT: (50*230)cm+/-10%, không hiệu. Nsx: Jiangxi Yuanna Packaging Material Co., Ltd. Mới 100% | D124: ='HỢP ĐỒNG'!I141 -> 48119093 | E124: CN | F124: ='HỢP ĐỒNG'!E141 -> 398 | G124: ='INVOICE lam CO'!D137 -> KGM | H124: 398 | I124: KGM | J124: ='HỢP ĐỒNG'!F141 -> 0.8 | M124: B05 | Y124: =IF(Z124=8%,"VB245",IF(Z124=10%,"VB901",IF(Z124=5%,"VB185",""))) -> VB245 | Z124: ='HỢP ĐỒNG'!P141 -> 0.08
A125: ='HỢP ĐỒNG'!A142 -> 124 | C125: ='HỢP ĐỒNG'!C142 -> Máy phun sơn tĩnh điện dùng để phun sơn hoàn thiện bề mặt các sản phẩm bằng kim loại,kèm khung đỡ có bánh xe.Model:FlexiSpray F1,điện áp:AC100-240,CS: 50W. NSX: Foshan Debelle Technology,mới 100% | D125: ='HỢP ĐỒNG'!I142 -> 84242029 | E125: CN | F125: ='HỢP ĐỒNG'!E142 -> 2 | G125: ='INVOICE lam CO'!D138 -> PCE | H125: 2 | I125: PCE | J125: ='HỢP ĐỒNG'!F142 -> 1884.87 | M125: B05 | Y125: =IF(Z125=8%,"VB245",IF(Z125=10%,"VB901",IF(Z125=5%,"VB185",""))) -> VB245 | Z125: ='HỢP ĐỒNG'!P142 -> 0.08

Sheet INVOICE lam CO
A1: INVOICE
B3: INVOICE NO: | C3: =INVOICE!F4 -> 0902 GF-TH/26
B4: DATE: | C4: =INVOICE!F5 -> 46271
A6: BUYER: TRUONG HAI TRADING AND IMPORT-EXPORT COMPANY LIMITED
A7: Address: No. 12, Secondary Road No. 4, Phu Loc 2 Urban Area, Ky Lua Ward, Lang Son Province, Vietnam.
A9: TRANSPORT: BY TRUCK
A11: FROM : CHINA: VIA TANTHANH | C11: BORDER GATE :
E12: DAF TAN THANH - VIET NAM
A14: N0 | B14: Description of good | C14: HS code | D14: Unit | E14: Q.ty | F14: Unit price (USD) | G14: Amount (USD) | H14: Số kiện
A15: ='HỢP ĐỒNG'!A19 -> 1 | B15: Dusting cloth | C15: ='HỢP ĐỒNG'!I19 -> 63071090 | D15: ='HỢP ĐỒNG'!D19 -> PCE | E15: ='HỢP ĐỒNG'!E19 -> 20000 | F15: ='HỢP ĐỒNG'!F19 -> 0.094 | G15: =F15*E15 -> 1880 | H15: =PACKINGLIST!F13 -> 10 | I15: ='HỢP ĐỒNG'!C19 -> Khăn lau bụi dùng để lau xe hơi, chất liệu vải dệt kim từ sợi polyester, KT:(30*30)cm, không hiệu, NSX: Qingdao Tao Hui Industrial. Mới 100% | J15: ='HỢP ĐỒNG'!D19 -> PCE | K15: ='HỢP ĐỒNG'!B19 -> CN082822-10HN
A16: ='HỢP ĐỒNG'!A20 -> 2 | B16: Tea set | C16: ='HỢP ĐỒNG'!I20 -> 69120000 | D16: ='HỢP ĐỒNG'!D20 -> SET | E16: ='HỢP ĐỒNG'!E20 -> 20 | F16: ='HỢP ĐỒNG'!F20 -> 5.16 | G16: =F16*E16 -> 103.2
A17: ='HỢP ĐỒNG'!A21 -> 3 | B17: Tea set | C17: ='HỢP ĐỒNG'!I21 -> 69120000 | D17: ='HỢP ĐỒNG'!D21 -> SET | E17: ='HỢP ĐỒNG'!E21 -> 20 | F17: ='HỢP ĐỒNG'!F21 -> 4.09 | G17: =F17*E17 -> 81.8
A18: ='HỢP ĐỒNG'!A22 -> 4 | B18: Tea set | C18: ='HỢP ĐỒNG'!I22 -> 69120000 | D18: ='HỢP ĐỒNG'!D22 -> SET | E18: ='HỢP ĐỒNG'!E22 -> 50 | F18: ='HỢP ĐỒNG'!F22 -> 5.69 | G18: =F18*E18 -> 284.5
A19: ='HỢP ĐỒNG'!A23 -> 5 | B19: Teapot | C19: ='HỢP ĐỒNG'!I23 -> 69120000 | D19: ='HỢP ĐỒNG'!D23 -> PCE | E19: ='HỢP ĐỒNG'!E23 -> 10 | F19: ='HỢP ĐỒNG'!F23 -> 13.6 | G19: =F19*E19 -> 136
A20: ='HỢP ĐỒNG'!A24 -> 6 | B20: Teapot | C20: ='HỢP ĐỒNG'!I24 -> 69120000 | D20: ='HỢP ĐỒNG'!D24 -> PCE | E20: ='HỢP ĐỒNG'!E24 -> 15 | F20: ='HỢP ĐỒNG'!F24 -> 10.46 | G20: =F20*E20 -> 156.9
A21: ='HỢP ĐỒNG'!A25 -> 7 | B21: Tea cup | C21: ='HỢP ĐỒNG'!I25 -> 69120000 | D21: ='HỢP ĐỒNG'!D25 -> PCE | E21: ='HỢP ĐỒNG'!E25 -> 20 | F21: ='HỢP ĐỒNG'!F25 -> 4.49 | G21: =F21*E21 -> 89.8
A22: ='HỢP ĐỒNG'!A26 -> 8 | B22: Teapot | C22: ='HỢP ĐỒNG'!I26 -> 69120000 | D22: ='HỢP ĐỒNG'!D26 -> PCE | E22: ='HỢP ĐỒNG'!E26 -> 10 | F22: ='HỢP ĐỒNG'!F26 -> 16.74 | G22: =F22*E22 -> 167.4
A23: ='HỢP ĐỒNG'!A27 -> 9 | B23: Teapot | C23: ='HỢP ĐỒNG'!I27 -> 69120000 | D23: ='HỢP ĐỒNG'!D27 -> PCE | E23: ='HỢP ĐỒNG'!E27 -> 5 | F23: ='HỢP ĐỒNG'!F27 -> 15.69 | G23: =F23*E23 -> 78.45
A24: ='HỢP ĐỒNG'!A28 -> 10 | B24: Teapot | C24: ='HỢP ĐỒNG'!I28 -> 69120000 | D24: ='HỢP ĐỒNG'!D28 -> PCE | E24: ='HỢP ĐỒNG'!E28 -> 10 | F24: ='HỢP ĐỒNG'!F28 -> 17.09 | G24: =F24*E24 -> 170.9
A25: ='HỢP ĐỒNG'!A29 -> 11 | B25: Teapot | C25: ='HỢP ĐỒNG'!I29 -> 69120000 | D25: ='HỢP ĐỒNG'!D29 -> PCE | E25: ='HỢP ĐỒNG'!E29 -> 10 | F25: ='HỢP ĐỒNG'!F29 -> 14.47 | G25: =F25*E25 -> 144.7
A26: ='HỢP ĐỒNG'!A30 -> 12 | B26: Teapot | C26: ='HỢP ĐỒNG'!I30 -> 69120000 | D26: ='HỢP ĐỒNG'!D30 -> PCE | E26: ='HỢP ĐỒNG'!E30 -> 3 | F26: ='HỢP ĐỒNG'!F30 -> 20.46 | G26: =F26*E26 -> 61.38
A27: ='HỢP ĐỒNG'!A31 -> 13 | B27: Teapot | C27: ='HỢP ĐỒNG'!I31 -> 69120000 | D27: ='HỢP ĐỒNG'!D31 -> PCE | E27: ='HỢP ĐỒNG'!E31 -> 3 | F27: ='HỢP ĐỒNG'!F31 -> 28.47 | G27: =F27*E27 -> 85.41
... A33: ='HỢP ĐỒNG'!A37 -> 19 | B33: Teapot | C33: ='HỢP ĐỒNG'!I37 -> 69120000 | D33: ='HỢP ĐỒNG'!D37 -> PCE | E33: ='HỢP ĐỒNG'!E37 -> 3 | F33: ='HỢP ĐỒNG'!F37 -> 32.03 | G33: =F33*E33 -> 96.09
A34: ='HỢP ĐỒNG'!A38 -> 20 | B34: Flow control switch | C34: 85363090 | D34: ='HỢP ĐỒNG'!D38 -> PCE | E34: ='HỢP ĐỒNG'!E38 -> 500 | F34: ='HỢP ĐỒNG'!F38 -> 5.47 | G34: =F34*E34 -> 2735
A35: ='HỢP ĐỒNG'!A39 -> 21 | B35: Flow control switch | C35: 85363090 | D35: ='HỢP ĐỒNG'!D39 -> PCE | E35: ='HỢP ĐỒNG'!E39 -> 300 | F35: ='HỢP ĐỒNG'!F39 -> 8.29 | G35: =F35*E35 -> 2487
A36: ='HỢP ĐỒNG'!A40 -> 22 | B36: Pneumatic Manifold | C36: ='HỢP ĐỒNG'!I40 -> 73269099 | D36: ='HỢP ĐỒNG'!D40 -> PCE | E36: ='HỢP ĐỒNG'!E40 -> 300 | F36: ='HỢP ĐỒNG'!F40 -> 4.49 | G36: =F36*E36 -> 1347
A37: ='HỢP ĐỒNG'!A41 -> 23 | B37: Pickleball racket | C37: ='HỢP ĐỒNG'!I41 -> 95069990 | D37: ='HỢP ĐỒNG'!D41 -> PCE | E37: ='HỢP ĐỒNG'!E41 -> 400 | F37: ='HỢP ĐỒNG'!F41 -> 9.24 | G37: =F37*E37 -> 3696
A38: ='HỢP ĐỒNG'!A42 -> 24 | B38: Pet bodice | C38: ='HỢP ĐỒNG'!I42 -> 42010000 | D38: ='HỢP ĐỒNG'!D42 -> PCE | E38: ='HỢP ĐỒNG'!E42 -> 270 | F38: ='HỢP ĐỒNG'!F42 -> 0.92 | G38: =F38*E38 -> 248.4
A39: ='HỢP ĐỒNG'!A43 -> 25 | B39: Pet leash | C39: ='HỢP ĐỒNG'!I43 -> 42010000 | D39: ='HỢP ĐỒNG'!D43 -> PCE | E39: ='HỢP ĐỒNG'!E43 -> 400 | F39: ='HỢP ĐỒNG'!F43 -> 0.71 | G39: =F39*E39 -> 284
A40: ='HỢP ĐỒNG'!A44 -> 26 | B40: Shower head holder | C40: ='HỢP ĐỒNG'!I44 -> 73249099 | D40: ='HỢP ĐỒNG'!D44 -> SET | E40: ='HỢP ĐỒNG'!E44 -> 1200 | F40: ='HỢP ĐỒNG'!F44 -> 5.28 | G40: =F40*E40 -> 6336
A41: ='HỢP ĐỒNG'!A45 -> 27 | B41: Trays | C41: ='HỢP ĐỒNG'!I45 -> 39264000 | D41: ='HỢP ĐỒNG'!D45 -> PCE | E41: ='HỢP ĐỒNG'!E45 -> 48 | F41: ='HỢP ĐỒNG'!F45 -> 10.18 | G41: =F41*E41 -> 488.64
A42: ='HỢP ĐỒNG'!A46 -> 28 | B42: Trays | C42: ='HỢP ĐỒNG'!I46 -> 39241099 | D42: ='HỢP ĐỒNG'!D46 -> PCE | E42: ='HỢP ĐỒNG'!E46 -> 150 | F42: ='HỢP ĐỒNG'!F46 -> 4.17 | G42: =F42*E42 -> 625.5
A43: ='HỢP ĐỒNG'!A47 -> 29 | B43: Trays | C43: ='HỢP ĐỒNG'!I47 -> 39241099 | D43: ='HỢP ĐỒNG'!D47 -> PCE | E43: ='HỢP ĐỒNG'!E47 -> 150 | F43: ='HỢP ĐỒNG'!F47 -> 4.17 | G43: =F43*E43 -> 625.5
A44: ='HỢP ĐỒNG'!A48 -> 30 | B44: Hotpot pot | C44: ='HỢP ĐỒNG'!I48 -> 73239310 | D44: ='HỢP ĐỒNG'!D48 -> PCE | E44: ='HỢP ĐỒNG'!E48 -> 200 | F44: ='HỢP ĐỒNG'!F48 -> 13.19 | G44: =F44*E44 -> 2638
A45: ='HỢP ĐỒNG'!A49 -> 31 | B45: Hotpot pot | C45: ='HỢP ĐỒNG'!I49 -> 73239310 | D45: ='HỢP ĐỒNG'!D49 -> PCE | E45: ='HỢP ĐỒNG'!E49 -> 26 | F45: ='HỢP ĐỒNG'!F49 -> 7.92 | G45: =F45*E45 -> 205.92
A46: ='HỢP ĐỒNG'!A50 -> 32 | B46: Trays | C46: ='HỢP ĐỒNG'!I50 -> 39264000 | D46: ='HỢP ĐỒNG'!D50 -> PCE | E46: ='HỢP ĐỒNG'!E50 -> 120 | F46: ='HỢP ĐỒNG'!F50 -> 1.88 | G46: =F46*E46 -> 225.6
A47: ='HỢP ĐỒNG'!A51 -> 33 | B47: Screen protector | C47: ='HỢP ĐỒNG'!I51 -> 70072990 | D47: ='HỢP ĐỒNG'!D51 -> PCE | E47: ='HỢP ĐỒNG'!E51 -> 6500 | F47: ='HỢP ĐỒNG'!F51 -> 0.183 | G47: =F47*E47 -> 1189.5
... A138: ='HỢP ĐỒNG'!A142 -> 124 | B138: Paint spraying machine | C138: ='HỢP ĐỒNG'!I142 -> 84242029 | D138: ='HỢP ĐỒNG'!D142 -> PCE | E138: ='HỢP ĐỒNG'!E142 -> 2 | F138: ='HỢP ĐỒNG'!F142 -> 1884.87 | G138: =F138*E138 -> 3769.74
C139: TOTAL: 1330 Cartons

Sheet Sheet1
A1: =IF(ROUND('HỢP ĐỒNG'!G143,0)>'HỢP ĐỒNG'!G143,'HỢP ĐỒNG'!G143-1,'HỢP ĐỒNG'!G143) -> 193171.09 | B1: =RIGHT("000000000000"&ROUND(A1,0),12) -> 000000193171 | C1: 1 | D1: 2 | E1: 3 | F1: 4 | G1: 5 | H1: 6 | I1: 7 | J1: 8 | K1: 9 | L1: 10 | M1: 11 | N1: 12
C2: =VALUE(MID(B1,C1,1)) -> 0 | D2: =VALUE(MID(B1,D1,1)) -> 0 | E2: =VALUE(MID(B1,E1,1)) -> 0 | F2: =VALUE(MID(B1,F1,1)) -> 0 | G2: =VALUE(MID(B1,G1,1)) -> 0 | H2: =VALUE(MID(B1,H1,1)) -> 0 | I2: =VALUE(MID(B1,I1,1)) -> 1 | J2: =VALUE(MID(B1,J1,1)) -> 9 | K2: =VALUE(MID(B1,K1,1)) -> 3 | L2: =VALUE(MID(B1,L1,1)) -> 1 | M2: =VALUE(MID(B1,M1,1)) -> 7 | N2: =VALUE(MID(B1,N1,1)) -> 1
C3: =SUM(C2:C2) -> 0 | D3: =SUM(C2:D2) -> 0 | E3: =SUM(C2:E2) -> 0 | F3: =SUM(F2:F2) -> 0 | G3: =SUM(F2:G2) -> 0 | H3: =SUM(F2:H2) -> 0 | I3: =SUM(I2:I2) -> 1 | J3: =SUM(I2:J2) -> 10 | K3: =SUM(I2:K2) -> 13 | L3: =SUM(L2:L2) -> 1 | M3: =SUM(L2:M2) -> 8 | N3: =SUM(L2:N2) -> 9
C4: =IF(C2=0,"",CHOOSE(C2,"một","hai","ba","bốn","năm","sáu","bảy","tám","chín")) | D4: =IF(D2=0,IF(AND(C2<>0,E2<>0),"lẻ",""),CHOOSE(D2,"mười","hai","ba","bốn","năm","sáu","bảy","tám","chín")) | E4: =IF(E2=0,"",CHOOSE(E2,IF(D2>1,"mốt","một"),"hai","ba","bốn",IF(D2=0,"năm","lăm"),"sáu","bảy","tám","chín")) | F4: =IF(F2=0,"",CHOOSE(F2,"một","hai","ba","bốn","năm","sáu","bảy","tám","chín")) | G4: =IF(G2=0,IF(AND(F2<>0,H2<>0),"lẻ",""),CHOOSE(G2,"mười","hai","ba","bốn","năm","sáu","bảy","tám","chín")) | H4: =IF(H2=0,"",CHOOSE(H2,IF(G2>1,"mốt","một"),"hai","ba","bốn",IF(G2=0,"năm","lăm"),"sáu","bảy","tám","chín")) | I4: =IF(I2=0,"",CHOOSE(I2,"một","hai","ba","bốn","năm","sáu","bảy","tám","chín")) -> một | J4: =IF(J2=0,IF(AND(I2<>0,K2<>0),"lẻ",""),CHOOSE(J2,"mười","hai","ba","bốn","năm","sáu","bảy","tám","chín")) -> chín | K4: =IF(K2=0,"",CHOOSE(K2,IF(J2>1,"mốt","một"),"hai","ba","bốn",IF(J2=0,"năm","lăm"),"sáu","bảy","tám","chín")) -> ba | L4: =IF(L2=0,IF(A1>100,"không trăm"," "),CHOOSE(L2,"một","hai","ba","bốn","năm","sáu","bảy","tám","chín")) -> một | M4: =IF(M2=0,IF(AND(L2<>0,N2<>0),"lẻ",""),CHOOSE(M2,"mười","hai","ba","bốn","năm","sáu","bảy","tám","chín")) -> bảy | N4: =IF(N2=0,"",CHOOSE(N2,IF(M2>1,"mốt","một"),"hai","ba","bốn",IF(M2=0,"năm","lăm"),"sáu","bảy","tám","chín")) -> mốt
C5: =IF(C2=0,"","trăm") | D5: =IF(D2=0,"",IF(D2=1,"","mươi")) | E5: =IF(AND(E2=0,E3=0),"","tỷ") | F5: =IF(F2=0,"","trăm") | G5: =IF(G2=0,"",IF(G2=1,"","mươi")) | H5: =IF(AND(H2=0,H3=0),"","triệu") | I5: =IF(I2=0,"","trăm") -> trăm | J5: =IF(J2=0,"",IF(J2=1,"","mươi")) -> mươi | K5: =IF(AND(K2=0,K3=0),"","nghìn") -> nghìn | L5: =IF(L2=0,"","trăm") -> trăm | M5: =IF(M2=0,"",IF(M2=1,"","mươi")) -> mươi
B6: =UPPER(LEFT(TRIM(IF(A1=0,"không ",C4&" "&C5&" "&D4&" "&D5&" "&E4&" "&E5&" "&F4&" "&F5&" "&G4&" "&G5&" "&H4&" "&H5&" "&I4&" "&I5&" "&J4&" "&J5&" "&K4&" "&K5&" "&L4&" "&L5&" "&M4&" "&M5&" "&N4&" "&N5)),1))&RIGHT(TRIM(IF(A1=0,"không ",C4&" "&C5&" "&D4&" "&D5&" "&E4&" "&E5&" "&F4&" "&F5&" "&G4&" "&G5&" "&H4&" "&H5&" "&I4&" "&I5&" "&J4&" "&J5&" "&K4&" "&K5&" "&L4&" "&L5&" "&M4&" "&M5&" "&N4&" "&N5)),LEN(TRIM(IF(A1=0,"không ",C4&" "&C5&" "&D4&" "&D5&" "&E4&" "&E5&" "&F4&" "&F5&" "&G4&" "&G5&" "&H4&" "&H5&" "&I4&" "&I5&" "&J4&" "&J5&" "&K4&" "&K5&" "&L4&" "&L5&" "&M4&" "&M5&" "&N4&" "&N5)))-1) -> Một trăm chín mươi ba nghìn một trăm bảy mươi mốt
A8: =MOD(A1,1)*100 -> 9 | B8: =RIGHT("000000000000"&ROUND(A8,0),12) -> 000000000009 | C8: 1 | D8: 2 | E8: 3 | F8: 4 | G8: 5 | H8: 6 | I8: 7 | J8: 8 | K8: 9 | L8: 10 | M8: 11 | N8: 12
C9: =VALUE(MID(B8,C8,1)) -> 0 | D9: =VALUE(MID(B8,D8,1)) -> 0 | E9: =VALUE(MID(B8,E8,1)) -> 0 | F9: =VALUE(MID(B8,F8,1)) -> 0 | G9: =VALUE(MID(B8,G8,1)) -> 0 | H9: =VALUE(MID(B8,H8,1)) -> 0 | I9: =VALUE(MID(B8,I8,1)) -> 0 | J9: =VALUE(MID(B8,J8,1)) -> 0 | K9: =VALUE(MID(B8,K8,1)) -> 0 | L9: =VALUE(MID(B8,L8,1)) -> 0 | M9: =VALUE(MID(B8,M8,1)) -> 0 | N9: =VALUE(MID(B8,N8,1)) -> 9
C10: =SUM(C9:C9) -> 0 | D10: =SUM(C9:D9) -> 0 | E10: =SUM(C9:E9) -> 0 | F10: =SUM(F9:F9) -> 0 | G10: =SUM(F9:G9) -> 0 | H10: =SUM(F9:H9) -> 0 | I10: =SUM(I9:I9) -> 0 | J10: =SUM(I9:J9) -> 0 | K10: =SUM(I9:K9) -> 0 | L10: =SUM(L9:L9) -> 0 | M10: =SUM(L9:M9) -> 0 | N10: =SUM(L9:N9) -> 9
C11: =IF(C9=0,"",CHOOSE(C9,"một","hai","ba","bốn","năm","sáu","bảy","tám","chín")) | D11: =IF(D9=0,IF(AND(C9<>0,E9<>0),"lẻ",""),CHOOSE(D9,"mười","hai","ba","bốn","năm","sáu","bảy","tám","chín")) | E11: =IF(E9=0,"",CHOOSE(E9,IF(D9>1,"mốt","một"),"hai","ba","bốn",IF(D9=0,"năm","lăm"),"sáu","bảy","tám","chín")) | F11: =IF(F9=0,"",CHOOSE(F9,"một","hai","ba","bốn","năm","sáu","bảy","tám","chín")) | G11: =IF(G9=0,IF(AND(F9<>0,H9<>0),"lẻ",""),CHOOSE(G9,"mười","hai","ba","bốn","năm","sáu","bảy","tám","chín")) | H11: =IF(H9=0,"",CHOOSE(H9,IF(G9>1,"mốt","một"),"hai","ba","bốn",IF(G9=0,"năm","lăm"),"sáu","bảy","tám","chín")) | I11: =IF(I9=0,"",CHOOSE(I9,"một","hai","ba","bốn","năm","sáu","bảy","tám","chín")) | J11: =IF(J9=0,IF(AND(I9<>0,K9<>0),"lẻ",""),CHOOSE(J9,"mười","hai","ba","bốn","năm","sáu","bảy","tám","chín")) | K11: =IF(K9=0,"",CHOOSE(K9,IF(J9>1,"mốt","một"),"hai","ba","bốn",IF(J9=0,"năm","lăm"),"sáu","bảy","tám","chín")) | L11: =IF(L9=0,"",CHOOSE(L9,"một","hai","ba","bốn","năm","sáu","bảy","tám","chín")) | M11: =IF(M9=0,IF(AND(L9<>0,N9<>0),"lẻ",""),CHOOSE(M9,"mười","hai","ba","bốn","năm","sáu","bảy","tám","chín")) | N11: =IF(N9=0,"",CHOOSE(N9,IF(M9>1,"mốt","một"),"hai","ba","bốn",IF(M9=0,"năm","lăm"),"sáu","bảy","tám","chín")) -> chín
C12: =IF(C9=0,"","trăm") | D12: =IF(D9=0,"",IF(D9=1,"","mươi")) | E12: =IF(AND(E9=0,E10=0),"","tỷ") | F12: =IF(F9=0,"","trăm") | G12: =IF(G9=0,"",IF(G9=1,"","mươi")) | H12: =IF(AND(H9=0,H10=0),"","triệu") | I12: =IF(I9=0,"","trăm") | J12: =IF(J9=0,"",IF(J9=1,"","mươi")) | K12: =IF(AND(K9=0,K10=0),"","nghìn") | L12: =IF(L9=0,"","trăm") | M12: =IF(M9=0,"",IF(M9=1,"","mươi"))
B13: =LEFT(TRIM(IF(A8=0,"không đồng.",C11&" "&C12&" "&D11&" "&D12&" "&E11&" "&E12&" "&F11&" "&F12&" "&G11&" "&G12&" "&H11&" "&H12&" "&I11&" "&I12&" "&J11&" "&J12&" "&K11&" "&K12&" "&L11&" "&L12&" "&M11&" "&M12&" "&N11&" "&N12)),1)&RIGHT(TRIM(IF(A8=0,"không đồng.",C11&" "&C12&" "&D11&" "&D12&" "&E11&" "&E12&" "&F11&" "&F12&" "&G11&" "&G12&" "&H11&" "&H12&" "&I11&" "&I12&" "&J11&" "&J12&" "&K11&" "&K12&" "&L11&" "&L12&" "&M11&" "&M12&" "&N11&" "&N12)),LEN(TRIM(IF(A8=0,"không đồng.",C11&" "&C12&" "&D11&" "&D12&" "&E11&" "&E12&" "&F11&" "&F12&" "&G11&" "&G12&" "&H11&" "&H12&" "&I11&" "&I12&" "&J11&" "&J12&" "&K11&" "&K12&" "&L11&" "&L12&" "&M11&" "&M12&" "&N11&" "&N12)))-1) -> chín
B15: =IF(A8<>0,"Số tiền bằng chữ: "&B6&" Đô la Mỹ và "&B13&" cent./.","Số tiền bằng chữ: "&B6&" Đô la Mỹ./.") -> Số tiền bằng chữ: Một trăm chín mươi ba nghìn một trăm bảy mươi mốt Đô la Mỹ và chín cent./.

Sheet LIST SOAT
A1: ='HỢP ĐỒNG'!A18 -> STT | B1: ='HỢP ĐỒNG'!B18 -> Mã Hàng | C1: ='HỢP ĐỒNG'!C18 -> Tên hàng hóa | D1: ='HỢP ĐỒNG'!D18 -> ĐVT | E1: ='HỢP ĐỒNG'!E18 -> Số lượng | F1: =PACKINGLIST!E12 -> Quy cách đóng gói | G1: =PACKINGLIST!F12 -> Số kiện | H1: =PACKINGLIST!G12 -> Trọng lượng hàng | I1: =PACKINGLIST!H12 -> Trọng lượng cả bì
A2: ='HỢP ĐỒNG'!A19 -> 1 | B2: ='HỢP ĐỒNG'!B19 -> CN082822-10HN | C2: ='HỢP ĐỒNG'!C19 -> Khăn lau bụi dùng để lau xe hơi, chất liệu vải dệt kim từ sợi polyester, KT:(30*30)cm, không hiệu, NSX: Qingdao Tao Hui Industrial. Mới 100% | D2: ='HỢP ĐỒNG'!D19 -> PCE | E2: ='HỢP ĐỒNG'!E19 -> 20000 | F2: =PACKINGLIST!E13 -> PCE / Kiện | G2: =PACKINGLIST!F13 -> 10 | H2: =PACKINGLIST!G13 -> 280 | I2: =PACKINGLIST!H13 -> 300
A3: ='HỢP ĐỒNG'!#REF! -> #REF! | B3: ='HỢP ĐỒNG'!#REF! -> #REF! | C3: ='HỢP ĐỒNG'!#REF! -> #REF! | D3: ='HỢP ĐỒNG'!#REF! -> #REF! | E3: ='HỢP ĐỒNG'!#REF! -> #REF! | F3: =PACKINGLIST!#REF! -> #REF! | G3: =PACKINGLIST!#REF! -> #REF! | H3: =PACKINGLIST!#REF! -> #REF! | I3: =PACKINGLIST!#REF! -> #REF!
A4: ='HỢP ĐỒNG'!#REF! -> #REF! | B4: ='HỢP ĐỒNG'!#REF! -> #REF! | C4: ='HỢP ĐỒNG'!#REF! -> #REF! | D4: ='HỢP ĐỒNG'!#REF! -> #REF! | E4: ='HỢP ĐỒNG'!#REF! -> #REF! | F4: =PACKINGLIST!#REF! -> #REF! | G4: =PACKINGLIST!#REF! -> #REF! | H4: =PACKINGLIST!#REF! -> #REF! | I4: =PACKINGLIST!#REF! -> #REF!
A5: ='HỢP ĐỒNG'!#REF! -> #REF! | B5: ='HỢP ĐỒNG'!#REF! -> #REF! | C5: ='HỢP ĐỒNG'!#REF! -> #REF! | D5: ='HỢP ĐỒNG'!#REF! -> #REF! | E5: ='HỢP ĐỒNG'!#REF! -> #REF! | H5: =PACKINGLIST!#REF! -> #REF! | I5: =PACKINGLIST!#REF! -> #REF!
A6: ='HỢP ĐỒNG'!#REF! -> #REF! | B6: ='HỢP ĐỒNG'!#REF! -> #REF! | C6: ='HỢP ĐỒNG'!#REF! -> #REF! | D6: ='HỢP ĐỒNG'!#REF! -> #REF! | E6: ='HỢP ĐỒNG'!#REF! -> #REF! | H6: =PACKINGLIST!#REF! -> #REF! | I6: =PACKINGLIST!#REF! -> #REF!
A7: ='HỢP ĐỒNG'!#REF! -> #REF! | B7: ='HỢP ĐỒNG'!#REF! -> #REF! | C7: ='HỢP ĐỒNG'!#REF! -> #REF! | D7: ='HỢP ĐỒNG'!#REF! -> #REF! | E7: ='HỢP ĐỒNG'!#REF! -> #REF! | F7: =PACKINGLIST!#REF! -> #REF! | G7: =PACKINGLIST!#REF! -> #REF! | H7: =PACKINGLIST!#REF! -> #REF! | I7: =PACKINGLIST!#REF! -> #REF!
A8: ='HỢP ĐỒNG'!#REF! -> #REF! | B8: ='HỢP ĐỒNG'!#REF! -> #REF! | C8: ='HỢP ĐỒNG'!#REF! -> #REF! | D8: ='HỢP ĐỒNG'!#REF! -> #REF! | E8: ='HỢP ĐỒNG'!#REF! -> #REF! | F8: =PACKINGLIST!#REF! -> #REF! | G8: =PACKINGLIST!#REF! -> #REF! | H8: =PACKINGLIST!#REF! -> #REF! | I8: =PACKINGLIST!#REF! -> #REF!
A9: ='HỢP ĐỒNG'!#REF! -> #REF! | B9: ='HỢP ĐỒNG'!#REF! -> #REF! | C9: ='HỢP ĐỒNG'!#REF! -> #REF! | D9: ='HỢP ĐỒNG'!#REF! -> #REF! | E9: ='HỢP ĐỒNG'!#REF! -> #REF! | F9: =PACKINGLIST!#REF! -> #REF! | G9: =PACKINGLIST!#REF! -> #REF! | H9: =PACKINGLIST!#REF! -> #REF! | I9: =PACKINGLIST!#REF! -> #REF!
A10: ='HỢP ĐỒNG'!#REF! -> #REF! | B10: ='HỢP ĐỒNG'!#REF! -> #REF! | C10: ='HỢP ĐỒNG'!#REF! -> #REF! | D10: ='HỢP ĐỒNG'!#REF! -> #REF! | E10: ='HỢP ĐỒNG'!#REF! -> #REF! | F10: =PACKINGLIST!#REF! -> #REF! | G10: =PACKINGLIST!#REF! -> #REF! | H10: =PACKINGLIST!#REF! -> #REF! | I10: =PACKINGLIST!#REF! -> #REF!
A11: ='HỢP ĐỒNG'!#REF! -> #REF! | B11: ='HỢP ĐỒNG'!#REF! -> #REF! | C11: ='HỢP ĐỒNG'!#REF! -> #REF! | D11: ='HỢP ĐỒNG'!#REF! -> #REF! | E11: ='HỢP ĐỒNG'!#REF! -> #REF! | F11: =PACKINGLIST!#REF! -> #REF! | G11: =PACKINGLIST!#REF! -> #REF! | H11: =PACKINGLIST!#REF! -> #REF! | I11: =PACKINGLIST!#REF! -> #REF!
A12: ='HỢP ĐỒNG'!#REF! -> #REF! | B12: ='HỢP ĐỒNG'!#REF! -> #REF! | C12: ='HỢP ĐỒNG'!#REF! -> #REF! | D12: ='HỢP ĐỒNG'!#REF! -> #REF! | E12: ='HỢP ĐỒNG'!#REF! -> #REF! | F12: =PACKINGLIST!#REF! -> #REF! | G12: =PACKINGLIST!#REF! -> #REF! | H12: =PACKINGLIST!#REF! -> #REF! | I12: =PACKINGLIST!#REF! -> #REF!
A13: ='HỢP ĐỒNG'!#REF! -> #REF! | B13: ='HỢP ĐỒNG'!#REF! -> #REF! | C13: ='HỢP ĐỒNG'!#REF! -> #REF! | D13: ='HỢP ĐỒNG'!#REF! -> #REF! | E13: ='HỢP ĐỒNG'!#REF! -> #REF! | F13: =PACKINGLIST!#REF! -> #REF! | G13: =PACKINGLIST!#REF! -> #REF! | H13: =PACKINGLIST!#REF! -> #REF! | I13: =PACKINGLIST!#REF! -> #REF!
A14: ='HỢP ĐỒNG'!#REF! -> #REF! | B14: ='HỢP ĐỒNG'!#REF! -> #REF! | C14: ='HỢP ĐỒNG'!#REF! -> #REF! | D14: ='HỢP ĐỒNG'!#REF! -> #REF! | E14: ='HỢP ĐỒNG'!#REF! -> #REF! | F14: =PACKINGLIST!#REF! -> #REF! | G14: =PACKINGLIST!#REF! -> #REF! | H14: =PACKINGLIST!#REF! -> #REF! | I14: =PACKINGLIST!#REF! -> #REF!
A15: ='HỢP ĐỒNG'!#REF! -> #REF! | B15: ='HỢP ĐỒNG'!#REF! -> #REF! | C15: ='HỢP ĐỒNG'!#REF! -> #REF! | D15: ='HỢP ĐỒNG'!#REF! -> #REF! | E15: ='HỢP ĐỒNG'!#REF! -> #REF! | F15: =PACKINGLIST!#REF! -> #REF! | G15: =PACKINGLIST!#REF! -> #REF! | H15: =PACKINGLIST!#REF! -> #REF! | I15: =PACKINGLIST!#REF! -> #REF!
A16: ='HỢP ĐỒNG'!#REF! -> #REF! | B16: ='HỢP ĐỒNG'!#REF! -> #REF! | C16: ='HỢP ĐỒNG'!#REF! -> #REF! | D16: ='HỢP ĐỒNG'!#REF! -> #REF! | E16: ='HỢP ĐỒNG'!#REF! -> #REF! | F16: =PACKINGLIST!#REF! -> #REF! | G16: =PACKINGLIST!#REF! -> #REF! | H16: =PACKINGLIST!#REF! -> #REF! | I16: =PACKINGLIST!#REF! -> #REF!
A17: ='HỢP ĐỒNG'!#REF! -> #REF! | B17: ='HỢP ĐỒNG'!#REF! -> #REF! | C17: ='HỢP ĐỒNG'!#REF! -> #REF! | D17: ='HỢP ĐỒNG'!#REF! -> #REF! | E17: ='HỢP ĐỒNG'!#REF! -> #REF! | F17: =PACKINGLIST!#REF! -> #REF! | G17: =PACKINGLIST!#REF! -> #REF! | H17: =PACKINGLIST!#REF! -> #REF! | I17: =PACKINGLIST!#REF! -> #REF!
A18: ='HỢP ĐỒNG'!#REF! -> #REF! | B18: ='HỢP ĐỒNG'!#REF! -> #REF! | C18: ='HỢP ĐỒNG'!#REF! -> #REF! | D18: ='HỢP ĐỒNG'!#REF! -> #REF! | E18: ='HỢP ĐỒNG'!#REF! -> #REF! | F18: =PACKINGLIST!#REF! -> #REF! | G18: =PACKINGLIST!#REF! -> #REF! | H18: =PACKINGLIST!#REF! -> #REF! | I18: =PACKINGLIST!#REF! -> #REF!
... A23: ='HỢP ĐỒNG'!#REF! -> #REF! | B23: ='HỢP ĐỒNG'!#REF! -> #REF! | C23: ='HỢP ĐỒNG'!#REF! -> #REF! | D23: ='HỢP ĐỒNG'!#REF! -> #REF! | E23: ='HỢP ĐỒNG'!#REF! -> #REF! | F23: =PACKINGLIST!#REF! -> #REF! | G23: =PACKINGLIST!#REF! -> #REF! | H23: =PACKINGLIST!#REF! -> #REF! | I23: =PACKINGLIST!#REF! -> #REF!
A24: ='HỢP ĐỒNG'!#REF! -> #REF! | B24: ='HỢP ĐỒNG'!#REF! -> #REF! | C24: ='HỢP ĐỒNG'!#REF! -> #REF! | D24: ='HỢP ĐỒNG'!#REF! -> #REF! | E24: ='HỢP ĐỒNG'!#REF! -> #REF! | H24: =PACKINGLIST!#REF! -> #REF! | I24: =PACKINGLIST!#REF! -> #REF!
A25: ='HỢP ĐỒNG'!#REF! -> #REF! | B25: ='HỢP ĐỒNG'!#REF! -> #REF! | C25: ='HỢP ĐỒNG'!#REF! -> #REF! | D25: ='HỢP ĐỒNG'!#REF! -> #REF! | E25: ='HỢP ĐỒNG'!#REF! -> #REF! | H25: =PACKINGLIST!#REF! -> #REF! | I25: =PACKINGLIST!#REF! -> #REF!
A26: ='HỢP ĐỒNG'!#REF! -> #REF! | B26: ='HỢP ĐỒNG'!#REF! -> #REF! | C26: ='HỢP ĐỒNG'!#REF! -> #REF! | D26: ='HỢP ĐỒNG'!#REF! -> #REF! | E26: ='HỢP ĐỒNG'!#REF! -> #REF! | H26: =PACKINGLIST!#REF! -> #REF! | I26: =PACKINGLIST!#REF! -> #REF!
A27: ='HỢP ĐỒNG'!#REF! -> #REF! | B27: ='HỢP ĐỒNG'!#REF! -> #REF! | C27: ='HỢP ĐỒNG'!#REF! -> #REF! | D27: ='HỢP ĐỒNG'!#REF! -> #REF! | E27: ='HỢP ĐỒNG'!#REF! -> #REF! | F27: =PACKINGLIST!#REF! -> #REF! | G27: =PACKINGLIST!#REF! -> #REF! | H27: =PACKINGLIST!#REF! -> #REF! | I27: =PACKINGLIST!#REF! -> #REF!
A28: ='HỢP ĐỒNG'!#REF! -> #REF! | B28: ='HỢP ĐỒNG'!#REF! -> #REF! | C28: ='HỢP ĐỒNG'!#REF! -> #REF! | D28: ='HỢP ĐỒNG'!#REF! -> #REF! | E28: ='HỢP ĐỒNG'!#REF! -> #REF! | F28: =PACKINGLIST!#REF! -> #REF! | G28: =PACKINGLIST!#REF! -> #REF! | H28: =PACKINGLIST!#REF! -> #REF! | I28: =PACKINGLIST!#REF! -> #REF!
A29: ='HỢP ĐỒNG'!#REF! -> #REF! | B29: ='HỢP ĐỒNG'!#REF! -> #REF! | C29: ='HỢP ĐỒNG'!#REF! -> #REF! | D29: ='HỢP ĐỒNG'!#REF! -> #REF! | E29: ='HỢP ĐỒNG'!#REF! -> #REF! | F29: =PACKINGLIST!#REF! -> #REF! | G29: =PACKINGLIST!#REF! -> #REF! | H29: =PACKINGLIST!#REF! -> #REF! | I29: =PACKINGLIST!#REF! -> #REF!
A30: ='HỢP ĐỒNG'!#REF! -> #REF! | B30: ='HỢP ĐỒNG'!#REF! -> #REF! | C30: ='HỢP ĐỒNG'!#REF! -> #REF! | D30: ='HỢP ĐỒNG'!#REF! -> #REF! | E30: ='HỢP ĐỒNG'!#REF! -> #REF! | F30: =PACKINGLIST!#REF! -> #REF! | H30: =PACKINGLIST!#REF! -> #REF! | I30: =PACKINGLIST!#REF! -> #REF!
A31: ='HỢP ĐỒNG'!#REF! -> #REF! | B31: ='HỢP ĐỒNG'!#REF! -> #REF! | C31: ='HỢP ĐỒNG'!#REF! -> #REF! | D31: ='HỢP ĐỒNG'!#REF! -> #REF! | E31: ='HỢP ĐỒNG'!#REF! -> #REF! | F31: =PACKINGLIST!#REF! -> #REF! | H31: =PACKINGLIST!#REF! -> #REF! | I31: =PACKINGLIST!#REF! -> #REF!
A32: ='HỢP ĐỒNG'!#REF! -> #REF! | B32: ='HỢP ĐỒNG'!#REF! -> #REF! | C32: ='HỢP ĐỒNG'!#REF! -> #REF! | D32: ='HỢP ĐỒNG'!#REF! -> #REF! | E32: ='HỢP ĐỒNG'!#REF! -> #REF! | F32: =PACKINGLIST!#REF! -> #REF! | G32: =PACKINGLIST!#REF! -> #REF! | H32: =PACKINGLIST!#REF! -> #REF! | I32: =PACKINGLIST!#REF! -> #REF!
A33: ='HỢP ĐỒNG'!#REF! -> #REF! | B33: ='HỢP ĐỒNG'!#REF! -> #REF! | C33: ='HỢP ĐỒNG'!#REF! -> #REF! | D33: ='HỢP ĐỒNG'!#REF! -> #REF! | E33: ='HỢP ĐỒNG'!#REF! -> #REF! | F33: =PACKINGLIST!#REF! -> #REF! | G33: =PACKINGLIST!#REF! -> #REF! | H33: =PACKINGLIST!#REF! -> #REF! | I33: =PACKINGLIST!#REF! -> #REF!
A34: ='HỢP ĐỒNG'!#REF! -> #REF! | B34: ='HỢP ĐỒNG'!#REF! -> #REF! | C34: ='HỢP ĐỒNG'!#REF! -> #REF! | D34: ='HỢP ĐỒNG'!#REF! -> #REF! | E34: ='HỢP ĐỒNG'!#REF! -> #REF! | F34: =PACKINGLIST!#REF! -> #REF! | G34: =PACKINGLIST!#REF! -> #REF! | H34: =PACKINGLIST!#REF! -> #REF! | I34: =PACKINGLIST!#REF! -> #REF!
A35: ='HỢP ĐỒNG'!#REF! -> #REF! | B35: ='HỢP ĐỒNG'!#REF! -> #REF! | C35: ='HỢP ĐỒNG'!#REF! -> #REF! | D35: ='HỢP ĐỒNG'!#REF! -> #REF! | E35: ='HỢP ĐỒNG'!#REF! -> #REF! | F35: =PACKINGLIST!#REF! -> #REF! | G35: =PACKINGLIST!#REF! -> #REF! | H35: =PACKINGLIST!#REF! -> #REF! | I35: =PACKINGLIST!#REF! -> #REF!
A36: ='HỢP ĐỒNG'!#REF! -> #REF! | B36: ='HỢP ĐỒNG'!#REF! -> #REF! | C36: ='HỢP ĐỒNG'!#REF! -> #REF! | D36: ='HỢP ĐỒNG'!#REF! -> #REF! | E36: ='HỢP ĐỒNG'!#REF! -> #REF! | F36: =PACKINGLIST!#REF! -> #REF! | G36: =PACKINGLIST!#REF! -> #REF! | H36: =PACKINGLIST!#REF! -> #REF! | I36: =PACKINGLIST!#REF! -> #REF!
A37: ='HỢP ĐỒNG'!#REF! -> #REF! | B37: ='HỢP ĐỒNG'!#REF! -> #REF! | C37: ='HỢP ĐỒNG'!#REF! -> #REF! | D37: ='HỢP ĐỒNG'!#REF! -> #REF! | E37: ='HỢP ĐỒNG'!#REF! -> #REF! | F37: =PACKINGLIST!#REF! -> #REF! | G37: =PACKINGLIST!#REF! -> #REF! | H37: =PACKINGLIST!#REF! -> #REF! | I37: =PACKINGLIST!#REF! -> #REF!
A38: ='HỢP ĐỒNG'!#REF! -> #REF! | B38: ='HỢP ĐỒNG'!#REF! -> #REF! | C38: ='HỢP ĐỒNG'!#REF! -> #REF! | D38: ='HỢP ĐỒNG'!#REF! -> #REF! | E38: ='HỢP ĐỒNG'!#REF! -> #REF! | F38: =PACKINGLIST!#REF! -> #REF! | G38: =PACKINGLIST!#REF! -> #REF! | H38: =PACKINGLIST!#REF! -> #REF! | I38: =PACKINGLIST!#REF! -> #REF!
A39: ='HỢP ĐỒNG'!#REF! -> #REF! | B39: ='HỢP ĐỒNG'!#REF! -> #REF! | C39: ='HỢP ĐỒNG'!#REF! -> #REF! | D39: ='HỢP ĐỒNG'!#REF! -> #REF! | E39: ='HỢP ĐỒNG'!#REF! -> #REF! | F39: =PACKINGLIST!#REF! -> #REF! | G39: =PACKINGLIST!#REF! -> #REF! | H39: =PACKINGLIST!#REF! -> #REF! | I39: =PACKINGLIST!#REF! -> #REF!
A40: ='HỢP ĐỒNG'!#REF! -> #REF! | B40: ='HỢP ĐỒNG'!#REF! -> #REF! | C40: ='HỢP ĐỒNG'!#REF! -> #REF! | D40: ='HỢP ĐỒNG'!#REF! -> #REF! | E40: ='HỢP ĐỒNG'!#REF! -> #REF! | F40: =PACKINGLIST!#REF! -> #REF! | G40: =PACKINGLIST!#REF! -> #REF! | H40: =PACKINGLIST!#REF! -> #REF! | I40: =PACKINGLIST!#REF! -> #REF!
A41: ='HỢP ĐỒNG'!#REF! -> #REF! | B41: ='HỢP ĐỒNG'!#REF! -> #REF! | C41: ='HỢP ĐỒNG'!#REF! -> #REF! | D41: ='HỢP ĐỒNG'!#REF! -> #REF! | E41: ='HỢP ĐỒNG'!#REF! -> #REF! | F41: =PACKINGLIST!#REF! -> #REF! | G41: =PACKINGLIST!#REF! -> #REF! | H41: =PACKINGLIST!#REF! -> #REF! | I41: =PACKINGLIST!#REF! -> #REF!
A42: ='HỢP ĐỒNG'!#REF! -> #REF! | B42: ='HỢP ĐỒNG'!#REF! -> #REF! | C42: ='HỢP ĐỒNG'!#REF! -> #REF! | D42: ='HỢP ĐỒNG'!#REF! -> #REF! | E42: ='HỢP ĐỒNG'!#REF! -> #REF! | F42: =PACKINGLIST!#REF! -> #REF! | G42: =PACKINGLIST!#REF! -> #REF! | H42: =PACKINGLIST!#REF! -> #REF! | I42: =PACKINGLIST!#REF! -> #REF!
A43: ='HỢP ĐỒNG'!#REF! -> #REF! | B43: ='HỢP ĐỒNG'!#REF! -> #REF! | C43: ='HỢP ĐỒNG'!#REF! -> #REF! | D43: ='HỢP ĐỒNG'!#REF! -> #REF! | E43: ='HỢP ĐỒNG'!#REF! -> #REF! | F43: =PACKINGLIST!#REF! -> #REF! | G43: =PACKINGLIST!#REF! -> #REF! | H43: =PACKINGLIST!#REF! -> #REF! | I43: =PACKINGLIST!#REF! -> #REF!
... A46: ='HỢP ĐỒNG'!#REF! -> #REF! | B46: ='HỢP ĐỒNG'!#REF! -> #REF! | C46: ='HỢP ĐỒNG'!#REF! -> #REF! | D46: ='HỢP ĐỒNG'!#REF! -> #REF! | E46: ='HỢP ĐỒNG'!#REF! -> #REF! | F46: =PACKINGLIST!#REF! -> #REF! | G46: =PACKINGLIST!#REF! -> #REF! | H46: =PACKINGLIST!#REF! -> #REF! | I46: =PACKINGLIST!#REF! -> #REF!
A47: ='HỢP ĐỒNG'!#REF! -> #REF! | B47: ='HỢP ĐỒNG'!#REF! -> #REF! | C47: ='HỢP ĐỒNG'!#REF! -> #REF! | D47: ='HỢP ĐỒNG'!#REF! -> #REF! | E47: ='HỢP ĐỒNG'!#REF! -> #REF! | F47: =PACKINGLIST!#REF! -> #REF! | H47: =PACKINGLIST!#REF! -> #REF! | I47: =PACKINGLIST!#REF! -> #REF!
A48: ='HỢP ĐỒNG'!#REF! -> #REF! | B48: ='HỢP ĐỒNG'!#REF! -> #REF! | C48: ='HỢP ĐỒNG'!#REF! -> #REF! | D48: ='HỢP ĐỒNG'!#REF! -> #REF! | E48: ='HỢP ĐỒNG'!#REF! -> #REF! | F48: =PACKINGLIST!#REF! -> #REF! | H48: =PACKINGLIST!#REF! -> #REF! | I48: =PACKINGLIST!#REF! -> #REF!
A49: ='HỢP ĐỒNG'!#REF! -> #REF! | B49: ='HỢP ĐỒNG'!#REF! -> #REF! | C49: ='HỢP ĐỒNG'!#REF! -> #REF! | D49: ='HỢP ĐỒNG'!#REF! -> #REF! | E49: ='HỢP ĐỒNG'!#REF! -> #REF! | F49: =PACKINGLIST!#REF! -> #REF! | H49: =PACKINGLIST!#REF! -> #REF! | I49: =PACKINGLIST!#REF! -> #REF!
A50: ='HỢP ĐỒNG'!#REF! -> #REF! | B50: ='HỢP ĐỒNG'!#REF! -> #REF! | C50: ='HỢP ĐỒNG'!#REF! -> #REF! | D50: ='HỢP ĐỒNG'!#REF! -> #REF! | E50: ='HỢP ĐỒNG'!#REF! -> #REF! | F50: =PACKINGLIST!#REF! -> #REF! | G50: =PACKINGLIST!#REF! -> #REF! | H50: =PACKINGLIST!#REF! -> #REF! | I50: =PACKINGLIST!#REF! -> #REF!
A51: ='HỢP ĐỒNG'!#REF! -> #REF! | B51: ='HỢP ĐỒNG'!#REF! -> #REF! | C51: ='HỢP ĐỒNG'!#REF! -> #REF! | D51: ='HỢP ĐỒNG'!#REF! -> #REF! | E51: ='HỢP ĐỒNG'!#REF! -> #REF! | F51: =PACKINGLIST!#REF! -> #REF! | H51: =PACKINGLIST!#REF! -> #REF! | I51: =PACKINGLIST!#REF! -> #REF!
A52: ='HỢP ĐỒNG'!#REF! -> #REF! | B52: ='HỢP ĐỒNG'!#REF! -> #REF! | C52: ='HỢP ĐỒNG'!#REF! -> #REF! | D52: ='HỢP ĐỒNG'!#REF! -> #REF! | E52: ='HỢP ĐỒNG'!#REF! -> #REF! | F52: =PACKINGLIST!#REF! -> #REF! | H52: =PACKINGLIST!#REF! -> #REF! | I52: =PACKINGLIST!#REF! -> #REF!
A53: ='HỢP ĐỒNG'!#REF! -> #REF! | B53: ='HỢP ĐỒNG'!#REF! -> #REF! | C53: ='HỢP ĐỒNG'!#REF! -> #REF! | D53: ='HỢP ĐỒNG'!#REF! -> #REF! | E53: ='HỢP ĐỒNG'!#REF! -> #REF! | F53: =PACKINGLIST!#REF! -> #REF! | H53: =PACKINGLIST!#REF! -> #REF! | I53: =PACKINGLIST!#REF! -> #REF!
A54: ='HỢP ĐỒNG'!#REF! -> #REF! | B54: ='HỢP ĐỒNG'!#REF! -> #REF! | C54: ='HỢP ĐỒNG'!#REF! -> #REF! | D54: ='HỢP ĐỒNG'!#REF! -> #REF! | E54: ='HỢP ĐỒNG'!#REF! -> #REF! | F54: =PACKINGLIST!#REF! -> #REF! | G54: =PACKINGLIST!#REF! -> #REF! | H54: =PACKINGLIST!#REF! -> #REF! | I54: =PACKINGLIST!#REF! -> #REF!
A55: ='HỢP ĐỒNG'!#REF! -> #REF! | B55: ='HỢP ĐỒNG'!#REF! -> #REF! | C55: ='HỢP ĐỒNG'!#REF! -> #REF! | D55: ='HỢP ĐỒNG'!#REF! -> #REF! | E55: ='HỢP ĐỒNG'!#REF! -> #REF! | F55: =PACKINGLIST!#REF! -> #REF! | G55: =PACKINGLIST!#REF! -> #REF! | H55: =PACKINGLIST!#REF! -> #REF! | I55: =PACKINGLIST!#REF! -> #REF!
A56: ='HỢP ĐỒNG'!#REF! -> #REF! | B56: ='HỢP ĐỒNG'!#REF! -> #REF! | C56: ='HỢP ĐỒNG'!#REF! -> #REF! | D56: ='HỢP ĐỒNG'!#REF! -> #REF! | E56: ='HỢP ĐỒNG'!#REF! -> #REF! | F56: =PACKINGLIST!#REF! -> #REF! | G56: =PACKINGLIST!#REF! -> #REF! | H56: =PACKINGLIST!#REF! -> #REF! | I56: =PACKINGLIST!#REF! -> #REF!
A57: ='HỢP ĐỒNG'!#REF! -> #REF! | B57: ='HỢP ĐỒNG'!#REF! -> #REF! | C57: ='HỢP ĐỒNG'!#REF! -> #REF! | D57: ='HỢP ĐỒNG'!#REF! -> #REF! | E57: ='HỢP ĐỒNG'!#REF! -> #REF! | H57: =PACKINGLIST!#REF! -> #REF! | I57: =PACKINGLIST!#REF! -> #REF!
A58: ='HỢP ĐỒNG'!#REF! -> #REF! | B58: ='HỢP ĐỒNG'!#REF! -> #REF! | C58: ='HỢP ĐỒNG'!#REF! -> #REF! | D58: ='HỢP ĐỒNG'!#REF! -> #REF! | E58: ='HỢP ĐỒNG'!#REF! -> #REF! | H58: =PACKINGLIST!#REF! -> #REF! | I58: =PACKINGLIST!#REF! -> #REF!
A59: ='HỢP ĐỒNG'!#REF! -> #REF! | B59: ='HỢP ĐỒNG'!#REF! -> #REF! | C59: ='HỢP ĐỒNG'!#REF! -> #REF! | D59: ='HỢP ĐỒNG'!#REF! -> #REF! | E59: ='HỢP ĐỒNG'!#REF! -> #REF! | H59: =PACKINGLIST!#REF! -> #REF! | I59: =PACKINGLIST!#REF! -> #REF!
A60: ='HỢP ĐỒNG'!#REF! -> #REF! | B60: ='HỢP ĐỒNG'!#REF! -> #REF! | C60: ='HỢP ĐỒNG'!#REF! -> #REF! | D60: ='HỢP ĐỒNG'!#REF! -> #REF! | E60: ='HỢP ĐỒNG'!#REF! -> #REF! | H60: =PACKINGLIST!#REF! -> #REF! | I60: =PACKINGLIST!#REF! -> #REF!
A61: ='HỢP ĐỒNG'!#REF! -> #REF! | B61: ='HỢP ĐỒNG'!#REF! -> #REF! | C61: ='HỢP ĐỒNG'!#REF! -> #REF! | D61: ='HỢP ĐỒNG'!#REF! -> #REF! | E61: ='HỢP ĐỒNG'!#REF! -> #REF! | H61: =PACKINGLIST!#REF! -> #REF! | I61: =PACKINGLIST!#REF! -> #REF!
A62: ='HỢP ĐỒNG'!#REF! -> #REF! | B62: ='HỢP ĐỒNG'!#REF! -> #REF! | C62: ='HỢP ĐỒNG'!#REF! -> #REF! | D62: ='HỢP ĐỒNG'!#REF! -> #REF! | E62: ='HỢP ĐỒNG'!#REF! -> #REF! | H62: =PACKINGLIST!#REF! -> #REF! | I62: =PACKINGLIST!#REF! -> #REF!
A63: ='HỢP ĐỒNG'!#REF! -> #REF! | B63: ='HỢP ĐỒNG'!#REF! -> #REF! | C63: ='HỢP ĐỒNG'!#REF! -> #REF! | D63: ='HỢP ĐỒNG'!#REF! -> #REF! | E63: ='HỢP ĐỒNG'!#REF! -> #REF! | F63: =PACKINGLIST!#REF! -> #REF! | G63: =PACKINGLIST!#REF! -> #REF! | H63: =PACKINGLIST!#REF! -> #REF! | I63: =PACKINGLIST!#REF! -> #REF!
A64: ='HỢP ĐỒNG'!#REF! -> #REF! | B64: ='HỢP ĐỒNG'!#REF! -> #REF! | C64: ='HỢP ĐỒNG'!#REF! -> #REF! | D64: ='HỢP ĐỒNG'!#REF! -> #REF! | E64: ='HỢP ĐỒNG'!#REF! -> #REF! | F64: =PACKINGLIST!#REF! -> #REF! | G64: =PACKINGLIST!#REF! -> #REF! | H64: =PACKINGLIST!#REF! -> #REF! | I64: =PACKINGLIST!#REF! -> #REF!
A65: Tổng | G65: =PACKINGLIST!F137 -> 0 | H65: =PACKINGLIST!G137 -> 29018 | I65: =PACKINGLIST!H137 -> 31304.4

Sheet BAN_KE
A1: STT | B1: TT_DONG_HANG | C1: MA_HS | D1: MO_TA_HANG_HOA | E1: SO_LUONG | F1: DVT_SO_LUONG | G1: TRONG_LUONG | H1: DVT_TRONG_LUONG
A2: 1 | B2: =A2 -> 1 | C2: ='HỢP ĐỒNG'!I19 -> 63071090 | D2: ='HỢP ĐỒNG'!C19 -> Khăn lau bụi dùng để lau xe hơi, chất liệu vải dệt kim từ sợi polyester, KT:(30*30)cm, không hiệu, NSX: Qingdao Tao Hui Industrial. Mới 100% | E2: ='HỢP ĐỒNG'!E19 -> 20000 | F2: ='nhập máy'!G2 -> PCE | G2: =PACKINGLIST!G13 -> 280 | H2: KGM
A3: =A2+1 -> 2 | B3: =A3 -> 2 | C3: ='HỢP ĐỒNG'!#REF! -> #REF! | D3: ='HỢP ĐỒNG'!#REF! -> #REF! | E3: ='HỢP ĐỒNG'!#REF! -> #REF! | F3: ='nhập máy'!G6 -> PCE | G3: =PACKINGLIST!#REF! -> #REF! | H3: KGM
A4: =A3+1 -> 3 | B4: =A4 -> 3 | C4: ='HỢP ĐỒNG'!#REF! -> #REF! | D4: ='HỢP ĐỒNG'!#REF! -> #REF! | E4: ='HỢP ĐỒNG'!#REF! -> #REF! | F4: ='nhập máy'!G7 -> PCE | G4: =PACKINGLIST!#REF! -> #REF! | H4: KGM
A5: =A4+1 -> 4 | B5: =A5 -> 4 | C5: ='HỢP ĐỒNG'!#REF! -> #REF! | D5: ='HỢP ĐỒNG'!#REF! -> #REF! | E5: ='HỢP ĐỒNG'!#REF! -> #REF! | F5: ='nhập máy'!G8 -> PCE | G5: =PACKINGLIST!#REF! -> #REF! | H5: KGM
A6: =A5+1 -> 5 | B6: =A6 -> 5 | C6: ='HỢP ĐỒNG'!#REF! -> #REF! | D6: ='HỢP ĐỒNG'!#REF! -> #REF! | E6: ='HỢP ĐỒNG'!#REF! -> #REF! | F6: ='nhập máy'!G9 -> PCE | G6: =PACKINGLIST!#REF! -> #REF! | H6: KGM
A7: =A6+1 -> 6 | B7: =A7 -> 6 | C7: ='HỢP ĐỒNG'!#REF! -> #REF! | D7: ='HỢP ĐỒNG'!#REF! -> #REF! | E7: ='HỢP ĐỒNG'!#REF! -> #REF! | F7: ='nhập máy'!G10 -> PCE | G7: =PACKINGLIST!#REF! -> #REF! | H7: KGM
A8: =A7+1 -> 7 | B8: =A8 -> 7 | C8: ='HỢP ĐỒNG'!#REF! -> #REF! | D8: ='HỢP ĐỒNG'!#REF! -> #REF! | E8: ='HỢP ĐỒNG'!#REF! -> #REF! | F8: ='nhập máy'!G11 -> PCE | G8: =PACKINGLIST!#REF! -> #REF! | H8: KGM
A9: =A8+1 -> 8 | B9: =A9 -> 8 | C9: ='HỢP ĐỒNG'!#REF! -> #REF! | D9: ='HỢP ĐỒNG'!#REF! -> #REF! | E9: ='HỢP ĐỒNG'!#REF! -> #REF! | F9: ='nhập máy'!G12 -> PCE | G9: =PACKINGLIST!#REF! -> #REF! | H9: KGM
A10: =A9+1 -> 9 | B10: =A10 -> 9 | C10: ='HỢP ĐỒNG'!#REF! -> #REF! | D10: ='HỢP ĐỒNG'!#REF! -> #REF! | E10: ='HỢP ĐỒNG'!#REF! -> #REF! | F10: ='nhập máy'!#REF! -> #REF! | G10: =PACKINGLIST!#REF! -> #REF! | H10: KGM
A11: =A10+1 -> 10 | B11: =A11 -> 10 | C11: ='HỢP ĐỒNG'!#REF! -> #REF! | D11: ='HỢP ĐỒNG'!#REF! -> #REF! | E11: ='HỢP ĐỒNG'!#REF! -> #REF! | F11: ='nhập máy'!G13 -> PCE | G11: =PACKINGLIST!#REF! -> #REF! | H11: KGM
A12: =A11+1 -> 11 | B12: =A12 -> 11 | C12: ='HỢP ĐỒNG'!#REF! -> #REF! | D12: ='HỢP ĐỒNG'!#REF! -> #REF! | E12: ='HỢP ĐỒNG'!#REF! -> #REF! | F12: ='nhập máy'!G14 -> PCE | G12: =PACKINGLIST!#REF! -> #REF! | H12: KGM
A13: =A12+1 -> 12 | B13: =A13 -> 12 | C13: ='HỢP ĐỒNG'!#REF! -> #REF! | D13: ='HỢP ĐỒNG'!#REF! -> #REF! | E13: ='HỢP ĐỒNG'!#REF! -> #REF! | F13: ='nhập máy'!G15 -> PCE | G13: =PACKINGLIST!#REF! -> #REF! | H13: KGM
A14: =A13+1 -> 13 | B14: =A14 -> 13 | C14: ='HỢP ĐỒNG'!#REF! -> #REF! | D14: ='HỢP ĐỒNG'!#REF! -> #REF! | E14: ='HỢP ĐỒNG'!#REF! -> #REF! | F14: ='nhập máy'!G16 -> PCE | G14: =PACKINGLIST!#REF! -> #REF! | H14: KGM
A15: =A14+1 -> 14 | B15: =A15 -> 14 | C15: ='HỢP ĐỒNG'!#REF! -> #REF! | D15: ='HỢP ĐỒNG'!#REF! -> #REF! | E15: ='HỢP ĐỒNG'!#REF! -> #REF! | F15: ='nhập máy'!G17 -> PCE | G15: =PACKINGLIST!#REF! -> #REF! | H15: KGM
A16: =A15+1 -> 15 | B16: =A16 -> 15 | C16: ='HỢP ĐỒNG'!#REF! -> #REF! | D16: ='HỢP ĐỒNG'!#REF! -> #REF! | E16: ='HỢP ĐỒNG'!#REF! -> #REF! | F16: ='nhập máy'!G18 -> PCE | G16: =PACKINGLIST!#REF! -> #REF! | H16: KGM
A17: =A16+1 -> 16 | B17: =A17 -> 16 | C17: ='HỢP ĐỒNG'!#REF! -> #REF! | D17: ='HỢP ĐỒNG'!#REF! -> #REF! | E17: ='HỢP ĐỒNG'!#REF! -> #REF! | F17: ='nhập máy'!G20 -> PCE | G17: =PACKINGLIST!#REF! -> #REF! | H17: KGM
A18: =A17+1 -> 17 | B18: =A18 -> 17 | C18: ='HỢP ĐỒNG'!#REF! -> #REF! | D18: ='HỢP ĐỒNG'!#REF! -> #REF! | E18: ='HỢP ĐỒNG'!#REF! -> #REF! | F18: ='nhập máy'!G21 -> PCE | G18: =PACKINGLIST!#REF! -> #REF! | H18: KGM
A19: =A18+1 -> 18 | B19: =A19 -> 18 | C19: ='HỢP ĐỒNG'!#REF! -> #REF! | D19: ='HỢP ĐỒNG'!#REF! -> #REF! | E19: ='HỢP ĐỒNG'!#REF! -> #REF! | F19: ='nhập máy'!G22 -> PCE | G19: =PACKINGLIST!#REF! -> #REF! | H19: KGM
A20: =A19+1 -> 19 | B20: =A20 -> 19 | C20: ='HỢP ĐỒNG'!#REF! -> #REF! | D20: ='HỢP ĐỒNG'!#REF! -> #REF! | E20: ='HỢP ĐỒNG'!#REF! -> #REF! | F20: ='nhập máy'!G23 -> PCE | G20: =PACKINGLIST!#REF! -> #REF! | H20: KGM
A21: =A20+1 -> 20 | B21: =A21 -> 20 | C21: ='HỢP ĐỒNG'!#REF! -> #REF! | D21: ='HỢP ĐỒNG'!#REF! -> #REF! | E21: ='HỢP ĐỒNG'!#REF! -> #REF! | F21: ='nhập máy'!G24 -> PCE | G21: =PACKINGLIST!#REF! -> #REF! | H21: KGM
A22: =A21+1 -> 21 | B22: =A22 -> 21 | C22: ='HỢP ĐỒNG'!#REF! -> #REF! | D22: ='HỢP ĐỒNG'!#REF! -> #REF! | E22: ='HỢP ĐỒNG'!#REF! -> #REF! | F22: ='nhập máy'!G25 -> PCE | G22: =PACKINGLIST!#REF! -> #REF! | H22: KGM
A23: =A22+1 -> 22 | B23: =A23 -> 22 | C23: ='HỢP ĐỒNG'!#REF! -> #REF! | D23: ='HỢP ĐỒNG'!#REF! -> #REF! | E23: ='HỢP ĐỒNG'!#REF! -> #REF! | F23: ='nhập máy'!G26 -> PCE | G23: =PACKINGLIST!#REF! -> #REF! | H23: KGM
A24: =A23+1 -> 23 | B24: =A24 -> 23 | C24: ='HỢP ĐỒNG'!#REF! -> #REF! | D24: ='HỢP ĐỒNG'!#REF! -> #REF! | E24: ='HỢP ĐỒNG'!#REF! -> #REF! | F24: ='nhập máy'!#REF! -> #REF! | G24: =PACKINGLIST!#REF! -> #REF! | H24: KGM
A25: =A24+1 -> 24 | B25: =A25 -> 24 | C25: ='HỢP ĐỒNG'!#REF! -> #REF! | D25: ='HỢP ĐỒNG'!#REF! -> #REF! | E25: ='HỢP ĐỒNG'!#REF! -> #REF! | F25: ='nhập máy'!#REF! -> #REF! | G25: =PACKINGLIST!#REF! -> #REF! | H25: KGM
A26: =A25+1 -> 25 | B26: =A26 -> 25 | C26: ='HỢP ĐỒNG'!#REF! -> #REF! | D26: ='HỢP ĐỒNG'!#REF! -> #REF! | E26: ='HỢP ĐỒNG'!#REF! -> #REF! | F26: ='nhập máy'!#REF! -> #REF! | G26: =PACKINGLIST!#REF! -> #REF! | H26: KGM
A27: =A26+1 -> 26 | B27: =A27 -> 26 | C27: ='HỢP ĐỒNG'!#REF! -> #REF! | D27: ='HỢP ĐỒNG'!#REF! -> #REF! | E27: ='HỢP ĐỒNG'!#REF! -> #REF! | F27: ='nhập máy'!#REF! -> #REF! | G27: =PACKINGLIST!#REF! -> #REF! | H27: KGM
A28: =A27+1 -> 27 | B28: =A28 -> 27 | C28: ='HỢP ĐỒNG'!#REF! -> #REF! | D28: ='HỢP ĐỒNG'!#REF! -> #REF! | E28: ='HỢP ĐỒNG'!#REF! -> #REF! | F28: ='nhập máy'!#REF! -> #REF! | G28: =PACKINGLIST!#REF! -> #REF! | H28: KGM
A29: =A28+1 -> 28 | B29: =A29 -> 28 | C29: ='HỢP ĐỒNG'!#REF! -> #REF! | D29: ='HỢP ĐỒNG'!#REF! -> #REF! | E29: ='HỢP ĐỒNG'!#REF! -> #REF! | F29: ='nhập máy'!#REF! -> #REF! | G29: =PACKINGLIST!#REF! -> #REF! | H29: KGM
A30: =A29+1 -> 29 | B30: =A30 -> 29 | C30: ='HỢP ĐỒNG'!#REF! -> #REF! | D30: ='HỢP ĐỒNG'!#REF! -> #REF! | E30: ='HỢP ĐỒNG'!#REF! -> #REF! | F30: ='nhập máy'!#REF! -> #REF! | G30: =PACKINGLIST!#REF! -> #REF! | H30: KGM
A31: =A30+1 -> 30 | B31: =A31 -> 30 | C31: ='HỢP ĐỒNG'!#REF! -> #REF! | D31: ='HỢP ĐỒNG'!#REF! -> #REF! | E31: ='HỢP ĐỒNG'!#REF! -> #REF! | F31: ='nhập máy'!#REF! -> #REF! | G31: =PACKINGLIST!#REF! -> #REF! | H31: KGM
A32: =A31+1 -> 31 | B32: =A32 -> 31 | C32: ='HỢP ĐỒNG'!#REF! -> #REF! | D32: ='HỢP ĐỒNG'!#REF! -> #REF! | E32: ='HỢP ĐỒNG'!#REF! -> #REF! | F32: ='nhập máy'!#REF! -> #REF! | G32: =PACKINGLIST!#REF! -> #REF! | H32: KGM
A33: =A32+1 -> 32 | B33: =A33 -> 32 | C33: ='HỢP ĐỒNG'!#REF! -> #REF! | D33: ='HỢP ĐỒNG'!#REF! -> #REF! | E33: ='HỢP ĐỒNG'!#REF! -> #REF! | F33: ='nhập máy'!#REF! -> #REF! | G33: =PACKINGLIST!#REF! -> #REF! | H33: KGM
A34: =A33+1 -> 33 | B34: =A34 -> 33 | C34: ='HỢP ĐỒNG'!#REF! -> #REF! | D34: ='HỢP ĐỒNG'!#REF! -> #REF! | E34: ='HỢP ĐỒNG'!#REF! -> #REF! | F34: ='nhập máy'!#REF! -> #REF! | G34: =PACKINGLIST!#REF! -> #REF! | H34: KGM
A35: =A34+1 -> 34 | B35: =A35 -> 34 | C35: ='HỢP ĐỒNG'!#REF! -> #REF! | D35: ='HỢP ĐỒNG'!#REF! -> #REF! | E35: ='HỢP ĐỒNG'!#REF! -> #REF! | F35: ='nhập máy'!#REF! -> #REF! | G35: =PACKINGLIST!#REF! -> #REF! | H35: KGM
... A51: =A50+1 -> 50 | B51: =A51 -> 50 | C51: ='HỢP ĐỒNG'!#REF! -> #REF! | D51: ='HỢP ĐỒNG'!#REF! -> #REF! | E51: ='HỢP ĐỒNG'!#REF! -> #REF! | F51: ='nhập máy'!#REF! -> #REF! | G51: =PACKINGLIST!#REF! -> #REF! | H51: KGM

Sheet HUONG_DAN
A1: Tên | B1: Mã | C1: Thông tin
A2: Thứ tự dòng hàng | B2: TT_DONG_HANG | C2: Nhập dạng số tối đa 4 kí tự
A3: Mã hàng hóa | B3: MA_HS | C3: Nhập text tối đa 6 kí tự
A4: Đơn vị tính trọng lượng | B4: MO_TA_HANG_HOA | C4: Nhập text tối đa 500 kí tự
A5: Số lượng | B5: SO_LUONG | C5: Nhập dạng số tối đa 15 kí tự
A6: Đơn vị tính trọng lượng | B6: DVT_SO_LUONG | C6: Nhập text tối đa 15 kí tự
A7: Đơn vị tính trọng lượng | B7: TRONG_LUONG | C7: Nhập số tối đa 17 số, trong đó có tối đa 2 số sau dấu thập phân
A8: Đơn vị tính trọng lượng | B8: DVT_TRONG_LUONG | C8: Nhập các giá trị: TNE/KGM/LBR
